Workbook

Sheet Dashboard & Global Settings
A1: Executive Dashboard & Global Settings
A2: Portfolio-level controls, KPIs, charts, and dorm-level filtering.
A3: Global Controls
A4: Current Month | B4: 46023
A5: Current Year | B5: 2026
A6: Dorm Filter | B6: All Dorms
A8: Revenue | B8: Total Portfolio Revenue
A9: Revenue | B9: Revenue This Month
A10: Revenue | B10: Revenue YTD | C10: =SUMPRODUCT((FinancialModel[Month]>=DATE(CurrentYear,1,1))*(FinancialModel[Month]<=EOMONTH(DATE(CurrentYear,MONTH(CurrentMonth),1),0))*(FinancialModel[Actual Revenue])*(IF(SelectedDorm="All Dorms",1,--(FinancialModel[[#This Row],[Dorm Name]]=SelectedDorm))))
A11: Expenses | B11: Total Operating Expenses | C11: =SUMPRODUCT((FinancialModel[Month]=DATE(CurrentYear,MONTH(CurrentMonth),1))*(FinancialModel[Operating Expenses])*(IF(SelectedDorm="All Dorms",1,--(FinancialModel[[#This Row],[Dorm Name]]=SelectedDorm))))
A12: Expenses | B12: Electricity Expenses | C12: =SUMPRODUCT((RoomElectricity[Month]=DATE(CurrentYear,MONTH(CurrentMonth),1))*(RoomElectricity[Total Room Electricity])*(IF(SelectedDorm="All Dorms",1,--(RoomElectricity[Dorm]=SelectedDorm))))+SUMPRODUCT(('Electricity Management'!$B$6:$B$300=DATE(CurrentYear,MONTH(CurrentMonth),1))*(CommonElectricity[Common Area Cost])*(IF(SelectedDorm="All Dorms",1,--(CommonElectricity[Dorm]=SelectedDorm))))
A13: Expenses | B13: Renovation Expenses | C13: =IF(SelectedDorm="All Dorms",SUM(RenovationTracker[Actual Cost]),SUMIFS(RenovationTracker[Actual Cost],RenovationTracker[Dorm Name],SelectedDorm))
A14: Expenses | B14: Rental Expenses | C14: =SUMPRODUCT((FinancialModel[Month]=DATE(CurrentYear,MONTH(CurrentMonth),1))*(FinancialModel[Building Rent])*(IF(SelectedDorm="All Dorms",1,--(FinancialModel[[#This Row],[Dorm Name]]=SelectedDorm))))
A15: Profitability | B15: Net Profit | C15: =C9-C11-C12
A16: Profitability | B16: Net Margin % | C16: =IFERROR(C15/C9,0)
A17: Occupancy | B17: Total Beds | C17: =IF(SelectedDorm="All Dorms",SUM(DormRegistry[Bed Capacity]),IFERROR(_xlfn.XLOOKUP(SelectedDorm,DormRegistry[Dorm Name],DormRegistry[Bed Capacity]),0))
A18: Occupancy | B18: Occupied Beds
A19: Occupancy | B19: Available Beds | C19: =C17-C18
A20: Occupancy | B20: Occupancy % | C20: =IFERROR(C18/C17,0)
A36: Month | B36: Revenue Trend | C36: Expense Trend | D36: Occupancy % | F36: Dorm | G36: Revenue
A37: =EDATE(DATE(CurrentYear,MONTH(CurrentMonth),1),-11) | B37: =SUMPRODUCT((FinancialModel[Month]=A37)*(FinancialModel[Actual Revenue])*(IF(SelectedDorm="All Dorms",1,--(FinancialModel[[#This Row],[Dorm Name]]=SelectedDorm)))) | C37: =SUMPRODUCT((FinancialModel[Month]=A37)*(FinancialModel[Operating Expenses])*(IF(SelectedDorm="All Dorms",1,--(FinancialModel[[#This Row],[Dorm Name]]=SelectedDorm)))) | F37: Dorm 1 | G37: =SUMIFS(FinancialModel[Actual Revenue],FinancialModel[Dorm Name],F37)
A38: =EDATE(DATE(CurrentYear,MONTH(CurrentMonth),1),-10) | B38: =SUMPRODUCT((FinancialModel[Month]=A38)*(FinancialModel[Actual Revenue])*(IF(SelectedDorm="All Dorms",1,--(FinancialModel[[#This Row],[Dorm Name]]=SelectedDorm)))) | C38: =SUMPRODUCT((FinancialModel[Month]=A38)*(FinancialModel[Operating Expenses])*(IF(SelectedDorm="All Dorms",1,--(FinancialModel[[#This Row],[Dorm Name]]=SelectedDorm)))) | F38: Dorm 2 | G38: =SUMIFS(FinancialModel[Actual Revenue],FinancialModel[Dorm Name],F38)
A39: =EDATE(DATE(CurrentYear,MONTH(CurrentMonth),1),-9) | B39: =SUMPRODUCT((FinancialModel[Month]=A39)*(FinancialModel[Actual Revenue])*(IF(SelectedDorm="All Dorms",1,--(FinancialModel[[#This Row],[Dorm Name]]=SelectedDorm)))) | C39: =SUMPRODUCT((FinancialModel[Month]=A39)*(FinancialModel[Operating Expenses])*(IF(SelectedDorm="All Dorms",1,--(FinancialModel[[#This Row],[Dorm Name]]=SelectedDorm)))) | F39: Dorm 3 | G39: =SUMIFS(FinancialModel[Actual Revenue],FinancialModel[Dorm Name],F39)
A40: =EDATE(DATE(CurrentYear,MONTH(CurrentMonth),1),-8) | B40: =SUMPRODUCT((FinancialModel[Month]=A40)*(FinancialModel[Actual Revenue])*(IF(SelectedDorm="All Dorms",1,--(FinancialModel[[#This Row],[Dorm Name]]=SelectedDorm)))) | C40: =SUMPRODUCT((FinancialModel[Month]=A40)*(FinancialModel[Operating Expenses])*(IF(SelectedDorm="All Dorms",1,--(FinancialModel[[#This Row],[Dorm Name]]=SelectedDorm))))
A41: =EDATE(DATE(CurrentYear,MONTH(CurrentMonth),1),-7) | B41: =SUMPRODUCT((FinancialModel[Month]=A41)*(FinancialModel[Actual Revenue])*(IF(SelectedDorm="All Dorms",1,--(FinancialModel[[#This Row],[Dorm Name]]=SelectedDorm)))) | C41: =SUMPRODUCT((FinancialModel[Month]=A41)*(FinancialModel[Operating Expenses])*(IF(SelectedDorm="All Dorms",1,--(FinancialModel[[#This Row],[Dorm Name]]=SelectedDorm))))
A42: =EDATE(DATE(CurrentYear,MONTH(CurrentMonth),1),-6) | B42: =SUMPRODUCT((FinancialModel[Month]=A42)*(FinancialModel[Actual Revenue])*(IF(SelectedDorm="All Dorms",1,--(FinancialModel[[#This Row],[Dorm Name]]=SelectedDorm)))) | C42: =SUMPRODUCT((FinancialModel[Month]=A42)*(FinancialModel[Operating Expenses])*(IF(SelectedDorm="All Dorms",1,--(FinancialModel[[#This Row],[Dorm Name]]=SelectedDorm))))
A43: =EDATE(DATE(CurrentYear,MONTH(CurrentMonth),1),-5) | B43: =SUMPRODUCT((FinancialModel[Month]=A43)*(FinancialModel[Actual Revenue])*(IF(SelectedDorm="All Dorms",1,--(FinancialModel[[#This Row],[Dorm Name]]=SelectedDorm)))) | C43: =SUMPRODUCT((FinancialModel[Month]=A43)*(FinancialModel[Operating Expenses])*(IF(SelectedDorm="All Dorms",1,--(FinancialModel[[#This Row],[Dorm Name]]=SelectedDorm))))
A44: =EDATE(DATE(CurrentYear,MONTH(CurrentMonth),1),-4) | B44: =SUMPRODUCT((FinancialModel[Month]=A44)*(FinancialModel[Actual Revenue])*(IF(SelectedDorm="All Dorms",1,--(FinancialModel[[#This Row],[Dorm Name]]=SelectedDorm)))) | C44: =SUMPRODUCT((FinancialModel[Month]=A44)*(FinancialModel[Operating Expenses])*(IF(SelectedDorm="All Dorms",1,--(FinancialModel[[#This Row],[Dorm Name]]=SelectedDorm))))
A45: =EDATE(DATE(CurrentYear,MONTH(CurrentMonth),1),-3) | B45: =SUMPRODUCT((FinancialModel[Month]=A45)*(FinancialModel[Actual Revenue])*(IF(SelectedDorm="All Dorms",1,--(FinancialModel[[#This Row],[Dorm Name]]=SelectedDorm)))) | C45: =SUMPRODUCT((FinancialModel[Month]=A45)*(FinancialModel[Operating Expenses])*(IF(SelectedDorm="All Dorms",1,--(FinancialModel[[#This Row],[Dorm Name]]=SelectedDorm))))
A46: =EDATE(DATE(CurrentYear,MONTH(CurrentMonth),1),-2) | B46: =SUMPRODUCT((FinancialModel[Month]=A46)*(FinancialModel[Actual Revenue])*(IF(SelectedDorm="All Dorms",1,--(FinancialModel[[#This Row],[Dorm Name]]=SelectedDorm)))) | C46: =SUMPRODUCT((FinancialModel[Month]=A46)*(FinancialModel[Operating Expenses])*(IF(SelectedDorm="All Dorms",1,--(FinancialModel[[#This Row],[Dorm Name]]=SelectedDorm))))
A47: =EDATE(DATE(CurrentYear,MONTH(CurrentMonth),1),-1) | B47: =SUMPRODUCT((FinancialModel[Month]=A47)*(FinancialModel[Actual Revenue])*(IF(SelectedDorm="All Dorms",1,--(FinancialModel[[#This Row],[Dorm Name]]=SelectedDorm)))) | C47: =SUMPRODUCT((FinancialModel[Month]=A47)*(FinancialModel[Operating Expenses])*(IF(SelectedDorm="All Dorms",1,--(FinancialModel[[#This Row],[Dorm Name]]=SelectedDorm))))
A48: =EDATE(DATE(CurrentYear,MONTH(CurrentMonth),1),0) | B48: =SUMPRODUCT((FinancialModel[Month]=A48)*(FinancialModel[Actual Revenue])*(IF(SelectedDorm="All Dorms",1,--(FinancialModel[[#This Row],[Dorm Name]]=SelectedDorm)))) | C48: =SUMPRODUCT((FinancialModel[Month]=A48)*(FinancialModel[Operating Expenses])*(IF(SelectedDorm="All Dorms",1,--(FinancialModel[[#This Row],[Dorm Name]]=SelectedDorm))))

Sheet Renovation & Projects
A1: Dorm Renovation & Project Tracker
A2: Budget, contractor, completion, and variance tracker for projects.
A4: Total Budget | B4: =SUM(RenovationTracker[Estimated Budget])
A5: Total Spent | B5: =SUM(RenovationTracker[Actual Cost])
A6: Remaining Budget | B6: =B5-B6
A7: Completion % | B7: =IFERROR(COUNTIF(RenovationTracker[Payment Status],"Paid")/COUNTA(RenovationTracker[Category]),0)
A10: Dorm Name | B10: Category | C10: Estimated Budget | D10: Actual Cost | E10: Variance | F10: Variance % | G10: Payment Status | H10: Contractor Name | I10: Contractor Phone | J10: Completion Date | K10: Notes
A11: Dorm 2 | B11: Painting | C11: 10 | D11: 15 | E11: =D11-C11 | F11: =IFERROR(E11/C11,0) | G11: Unpaid
A12: Dorm 2 | B12: Beds & Mattresses | C12: 0 | D12: 0 | E12: =D12-C12 | F12: =IFERROR(E12/C12,0) | G12: Unpaid
A13: Dorm 2 | B13: Kitchen Appliances | C13: 0 | D13: 0 | E13: =D13-C13 | F13: =IFERROR(E13/C13,0) | G13: Unpaid
A14: Dorm 2 | B14: Plumbing | C14: 0 | D14: 0 | E14: =D14-C14 | F14: =IFERROR(E14/C14,0) | G14: Unpaid
A15: Dorm 2 | B15: Furniture | C15: 0 | D15: 0 | E15: =D15-C15 | F15: =IFERROR(E15/C15,0) | G15: Unpaid
A16: Dorm 2 | B16: Electricity & Wiring | C16: 0 | D16: 0 | E16: =D16-C16 | F16: =IFERROR(E16/C16,0) | G16: Unpaid
A17: Dorm 2 | B17: CCTV Installation | C17: 0 | D17: 0 | E17: =D17-C17 | F17: =IFERROR(E17/C17,0) | G17: Unpaid
A18: Dorm 2 | B18: Internet Infrastructure | C18: 0 | D18: 0 | E18: =D18-C18 | F18: =IFERROR(E18/C18,0) | G18: Unpaid
A19: Dorm 2 | B19: Curtains & Decorations | C19: 0 | D19: 0 | E19: =D19-C19 | F19: =IFERROR(E19/C19,0) | G19: Unpaid
A20: Dorm 2 | B20: Cleaning Equipment | C20: 0 | D20: 0 | E20: =D20-C20 | F20: =IFERROR(E20/C20,0) | G20: Unpaid
A21: Dorm 2 | B21: Contingency / Miscellaneous | C21: 0 | D21: 0 | E21: =D21-C21 | F21: =IFERROR(E21/C21,0) | G21: Unpaid
E22: =D22-C22 | F22: =IFERROR(E22/C22,0)
E23: =D23-C23 | F23: =IFERROR(E23/C23,0)
E24: =D24-C24 | F24: =IFERROR(E24/C24,0)
E25: =D25-C25 | F25: =IFERROR(E25/C25,0)
E26: =D26-C26 | F26: =IFERROR(E26/C26,0)
E27: =D27-C27 | F27: =IFERROR(E27/C27,0)
E28: =D28-C28 | F28: =IFERROR(E28/C28,0)
E29: =D29-C29 | F29: =IFERROR(E29/C29,0)
E30: =D30-C30 | F30: =IFERROR(E30/C30,0)
E31: =D31-C31 | F31: =IFERROR(E31/C31,0)
E32: =D32-C32 | F32: =IFERROR(E32/C32,0)
E33: =D33-C33 | F33: =IFERROR(E33/C33,0)
... E200: =D200-C200 | F200: =IFERROR(E200/C200,0)

Sheet Client DB & Bed Mgmt
A1: Client Database & Bed Management
A2: Each row represents one bed. Use Dorm / Building for the property and Client Name for the person.
A3: IMPORTANT: Column A = Dorm / Building (Dorm 1, Dorm 2, Dorm 3). Column D = Client Name. Then use Room Number and Bed ID for the bed assignment.
A4: Dorm / Building | B4: Room Number | C4: Bed ID | D4: Client Name | E4: Status | F4: Entire Room Rental | G4: Monthly Rent | H4: Room Occupied Beds | I4: rent/moth | J4: Electricity Per Person | K4: Common Area Per Person | L4: Payment Status | M4: Move-in Date | N4: Move-out Date | O4: Security Deposit | P4: ID / Passport Number | Q4: Phone Number | R4: Emergency Contact | S4: Contract End Date | T4: Invoice Unit
A5: Dorm 1 | B5: Room 1-1 | C5: Dorm1-R1A | D5: ikr | E5: =IF(D5<>"","Occupied","Vacant") | F5: =IF(COUNTIFS($B:$B,B5,$E:$E,"Occupied")=2,"Yes","No") | G5: =DefaultRentPerBed | H5: =IF(E5<>"Occupied",0,COUNTIFS($B:$B,B5,$E:$E,"Occupied")) | I5: =IF(E5<>"Occupied",0,IF(H5=1,350,IF(H5=2,200,0))) | J5: =IF(E5="Occupied",IFERROR(SUMIFS('Electricity Management'!$J:$J,'Electricity Management'!$A:$A,A5,'Electricity Management'!$C:$C,B5),0),0) | K5: {=IF(E5="Occupied",IFERROR(INDEX('Electricity Management'!$T:$T,MATCH(1,('Electricity Management'!$K:$K=A5)*('Electricity Management'!$L:$L=B5),0)),0),"")} | L5: Partially Paid | M5: 46296 | N5: 46376 | Q5: 0657202020 | T5: =IF(F5="Yes",A5&"-"&B5,C5)
A6: Dorm 1 | B6: Room 1-1 | C6: Dorm1-R1B | D6: vrr | E6: =IF(D6<>"","Occupied","Vacant") | F6: =IF(COUNTIFS($B:$B,B6,$E:$E,"Occupied")=2,"Yes","No") | G6: =DefaultRentPerBed | H6: =IF(E6<>"Occupied",0,COUNTIFS($B:$B,B6,$E:$E,"Occupied")) | I6: =IF(E6<>"Occupied",0,IF(H6=1,350,IF(H6=2,200,0))) | J6: =IF(E6="Occupied",IFERROR(SUMIFS('Electricity Management'!$J:$J,'Electricity Management'!$A:$A,A6,'Electricity Management'!$C:$C,B6),0),0) | K6: {=IF(E6="Occupied",IFERROR(INDEX('Electricity Management'!$T:$T,MATCH(1,('Electricity Management'!$K:$K=A6)*('Electricity Management'!$L:$L=B6),0)),0),"")} | L6: unpaid | M6: 46297 | N6: 30 juin | T6: =IF(F6="Yes",A6&"-"&B6,C6)
A7: Dorm 1 | B7: Room 1-2 | C7: Dorm1-R2B | D7: vv | E7: =IF(D7<>"","Occupied","Vacant") | F7: =IF(COUNTIFS($B:$B,B7,$E:$E,"Occupied")=2,"Yes","No") | G7: =DefaultRentPerBed | H7: =IF(E7<>"Occupied",0,COUNTIFS($B:$B,B7,$E:$E,"Occupied")) | I7: =IF(E7<>"Occupied",0,IF(H7=1,350,IF(H7=2,200,0))) | J7: =IF(E7="Occupied",IFERROR(SUMIFS('Electricity Management'!$J:$J,'Electricity Management'!$A:$A,A7,'Electricity Management'!$C:$C,B7),0),0) | K7: {=IF(E7="Occupied",IFERROR(INDEX('Electricity Management'!$T:$T,MATCH(1,('Electricity Management'!$K:$K=A7)*('Electricity Management'!$L:$L=B7),0)),0),"")} | L7: Partially Paid | M7: 46298 | T7: =IF(F7="Yes",A7&"-"&B7,C7)
A8: Dorm 1 | B8: Room 1-2 | C8: Dorm1-R2C | E8: =IF(D8<>"","Occupied","Vacant") | F8: =IF(COUNTIFS($B:$B,B8,$E:$E,"Occupied")=2,"Yes","No") | G8: =DefaultRentPerBed | H8: =IF(E8<>"Occupied",0,COUNTIFS($B:$B,B8,$E:$E,"Occupied")) | I8: =IF(E8<>"Occupied",0,IF(H8=1,350,IF(H8=2,200,0))) | J8: =IF(E8="Occupied",IFERROR(SUMIFS('Electricity Management'!$J:$J,'Electricity Management'!$A:$A,A8,'Electricity Management'!$C:$C,B8),0),0) | K8: {=IF(E8="Occupied",IFERROR(INDEX('Electricity Management'!$T:$T,MATCH(1,('Electricity Management'!$K:$K=A8)*('Electricity Management'!$L:$L=B8),0)),0),"")} | T8: =IF(F8="Yes",A8&"-"&B8,C8)
A9: Dorm 1 | B9: Room 1-3 | C9: Dorm1-R3A | E9: =IF(D9<>"","Occupied","Vacant") | F9: =IF(COUNTIFS($B:$B,B9,$E:$E,"Occupied")=2,"Yes","No") | G9: =DefaultRentPerBed | H9: =IF(E9<>"Occupied",0,COUNTIFS($B:$B,B9,$E:$E,"Occupied")) | I9: =IF(E9<>"Occupied",0,IF(H9=1,350,IF(H9=2,200,0))) | J9: =IF(E9="Occupied",IFERROR(SUMIFS('Electricity Management'!$J:$J,'Electricity Management'!$A:$A,A9,'Electricity Management'!$C:$C,B9),0),0) | K9: {=IF(E9="Occupied",IFERROR(INDEX('Electricity Management'!$T:$T,MATCH(1,('Electricity Management'!$K:$K=A9)*('Electricity Management'!$L:$L=B9),0)),0),"")} | T9: =IF(F9="Yes",A9&"-"&B9,C9)
A10: Dorm 1 | B10: Room 1-3 | C10: Dorm1-R3B | E10: =IF(D10<>"","Occupied","Vacant") | F10: =IF(COUNTIFS($B:$B,B10,$E:$E,"Occupied")=2,"Yes","No") | G10: =DefaultRentPerBed | H10: =IF(E10<>"Occupied",0,COUNTIFS($B:$B,B10,$E:$E,"Occupied")) | I10: =IF(E10<>"Occupied",0,IF(H10=1,350,IF(H10=2,200,0))) | J10: =IF(E10="Occupied",IFERROR(SUMIFS('Electricity Management'!$J:$J,'Electricity Management'!$A:$A,A10,'Electricity Management'!$C:$C,B10),0),0) | K10: {=IF(E10="Occupied",IFERROR(INDEX('Electricity Management'!$T:$T,MATCH(1,('Electricity Management'!$K:$K=A10)*('Electricity Management'!$L:$L=B10),0)),0),"")} | T10: =IF(F10="Yes",A10&"-"&B10,C10)
A11: Dorm 1 | B11: Room 1-4 | C11: Dorm1-R4A | E11: =IF(D11<>"","Occupied","Vacant") | F11: =IF(COUNTIFS($B:$B,B11,$E:$E,"Occupied")=2,"Yes","No") | G11: =DefaultRentPerBed | H11: =IF(E11<>"Occupied",0,COUNTIFS($B:$B,B11,$E:$E,"Occupied")) | I11: =IF(E11<>"Occupied",0,IF(H11=1,350,IF(H11=2,200,0))) | J11: =IF(E11="Occupied",IFERROR(SUMIFS('Electricity Management'!$J:$J,'Electricity Management'!$A:$A,A11,'Electricity Management'!$C:$C,B11),0),0) | K11: {=IF(E11="Occupied",IFERROR(INDEX('Electricity Management'!$T:$T,MATCH(1,('Electricity Management'!$K:$K=A11)*('Electricity Management'!$L:$L=B11),0)),0),"")} | T11: =IF(F11="Yes",A11&"-"&B11,C11)
A12: Dorm 1 | B12: Room 1-4 | C12: Dorm1-R4B | E12: =IF(D12<>"","Occupied","Vacant") | F12: =IF(COUNTIFS($B:$B,B12,$E:$E,"Occupied")=2,"Yes","No") | G12: =DefaultRentPerBed | H12: =IF(E12<>"Occupied",0,COUNTIFS($B:$B,B12,$E:$E,"Occupied")) | I12: =IF(E12<>"Occupied",0,IF(H12=1,350,IF(H12=2,200,0))) | J12: =IF(E12="Occupied",IFERROR(SUMIFS('Electricity Management'!$J:$J,'Electricity Management'!$A:$A,A12,'Electricity Management'!$C:$C,B12),0),0) | K12: {=IF(E12="Occupied",IFERROR(INDEX('Electricity Management'!$T:$T,MATCH(1,('Electricity Management'!$K:$K=A12)*('Electricity Management'!$L:$L=B12),0)),0),"")} | T12: =IF(F12="Yes",A12&"-"&B12,C12)
A13: Dorm 1 | B13: Room 1-5 | C13: Dorm1-R5A | E13: =IF(D13<>"","Occupied","Vacant") | F13: =IF(COUNTIFS($B:$B,B13,$E:$E,"Occupied")=2,"Yes","No") | G13: =DefaultRentPerBed | H13: =IF(E13<>"Occupied",0,COUNTIFS($B:$B,B13,$E:$E,"Occupied")) | I13: =IF(E13<>"Occupied",0,IF(H13=1,350,IF(H13=2,200,0))) | J13: =IF(E13="Occupied",IFERROR(SUMIFS('Electricity Management'!$J:$J,'Electricity Management'!$A:$A,A13,'Electricity Management'!$C:$C,B13),0),0) | K13: {=IF(E13="Occupied",IFERROR(INDEX('Electricity Management'!$T:$T,MATCH(1,('Electricity Management'!$K:$K=A13)*('Electricity Management'!$L:$L=B13),0)),0),"")} | T13: =IF(F13="Yes",A13&"-"&B13,C13)
A14: Dorm 1 | B14: Room 1-5 | C14: Dorm1-R5B | E14: =IF(D14<>"","Occupied","Vacant") | F14: =IF(COUNTIFS($B:$B,B14,$E:$E,"Occupied")=2,"Yes","No") | G14: =DefaultRentPerBed | H14: =IF(E14<>"Occupied",0,COUNTIFS($B:$B,B14,$E:$E,"Occupied")) | I14: =IF(E14<>"Occupied",0,IF(H14=1,350,IF(H14=2,200,0))) | J14: =IF(E14="Occupied",IFERROR(SUMIFS('Electricity Management'!$J:$J,'Electricity Management'!$A:$A,A14,'Electricity Management'!$C:$C,B14),0),0) | K14: {=IF(E14="Occupied",IFERROR(INDEX('Electricity Management'!$T:$T,MATCH(1,('Electricity Management'!$K:$K=A14)*('Electricity Management'!$L:$L=B14),0)),0),"")} | T14: =IF(F14="Yes",A14&"-"&B14,C14)
A15: Dorm 1 | B15: Room 1-6 | C15: Dorm1-R6A | E15: =IF(D15<>"","Occupied","Vacant") | F15: =IF(COUNTIFS($B:$B,B15,$E:$E,"Occupied")=2,"Yes","No") | G15: =DefaultRentPerBed | H15: =IF(E15<>"Occupied",0,COUNTIFS($B:$B,B15,$E:$E,"Occupied")) | I15: =IF(E15<>"Occupied",0,IF(H15=1,350,IF(H15=2,200,0))) | J15: =IF(E15="Occupied",IFERROR(SUMIFS('Electricity Management'!$J:$J,'Electricity Management'!$A:$A,A15,'Electricity Management'!$C:$C,B15),0),0) | K15: {=IF(E15="Occupied",IFERROR(INDEX('Electricity Management'!$T:$T,MATCH(1,('Electricity Management'!$K:$K=A15)*('Electricity Management'!$L:$L=B15),0)),0),"")} | T15: =IF(F15="Yes",A15&"-"&B15,C15)
A16: Dorm 1 | B16: Room 1-6 | C16: Dorm1-R6B | E16: =IF(D16<>"","Occupied","Vacant") | F16: =IF(COUNTIFS($B:$B,B16,$E:$E,"Occupied")=2,"Yes","No") | G16: =DefaultRentPerBed | H16: =IF(E16<>"Occupied",0,COUNTIFS($B:$B,B16,$E:$E,"Occupied")) | I16: =IF(E16<>"Occupied",0,IF(H16=1,350,IF(H16=2,200,0))) | J16: =IF(E16="Occupied",IFERROR(SUMIFS('Electricity Management'!$J:$J,'Electricity Management'!$A:$A,A16,'Electricity Management'!$C:$C,B16),0),0) | K16: {=IF(E16="Occupied",IFERROR(INDEX('Electricity Management'!$T:$T,MATCH(1,('Electricity Management'!$K:$K=A16)*('Electricity Management'!$L:$L=B16),0)),0),"")} | T16: =IF(F16="Yes",A16&"-"&B16,C16)
A17: Dorm 2 | B17: Room 2-1 | C17: Dorm2-R1A | E17: =IF(D17<>"","Occupied","Vacant") | F17: =IF(COUNTIFS($B:$B,B17,$E:$E,"Occupied")=2,"Yes","No") | G17: =DefaultRentPerBed | H17: =IF(E17<>"Occupied",0,COUNTIFS($B:$B,B17,$E:$E,"Occupied")) | I17: =IF(E17<>"Occupied",0,IF(H17=1,350,IF(H17=2,200,0))) | J17: =IF(E17="Occupied",IFERROR(SUMIFS('Electricity Management'!$J:$J,'Electricity Management'!$A:$A,A17,'Electricity Management'!$C:$C,B17),0),0) | K17: {=IF(E17="Occupied",IFERROR(INDEX('Electricity Management'!$T:$T,MATCH(1,('Electricity Management'!$K:$K=A17)*('Electricity Management'!$L:$L=B17),0)),0),"")} | T17: =IF(F17="Yes",A17&"-"&B17,C17)
A18: Dorm 2 | B18: Room 2-1 | C18: Dorm2-R1B | E18: =IF(D18<>"","Occupied","Vacant") | F18: =IF(COUNTIFS($B:$B,B18,$E:$E,"Occupied")=2,"Yes","No") | G18: =DefaultRentPerBed | H18: =IF(E18<>"Occupied",0,COUNTIFS($B:$B,B18,$E:$E,"Occupied")) | I18: =IF(E18<>"Occupied",0,IF(H18=1,350,IF(H18=2,200,0))) | J18: =IF(E18="Occupied",IFERROR(SUMIFS('Electricity Management'!$J:$J,'Electricity Management'!$A:$A,A18,'Electricity Management'!$C:$C,B18),0),0) | K18: {=IF(E18="Occupied",IFERROR(INDEX('Electricity Management'!$T:$T,MATCH(1,('Electricity Management'!$K:$K=A18)*('Electricity Management'!$L:$L=B18),0)),0),"")} | T18: =IF(F18="Yes",A18&"-"&B18,C18)
A19: Dorm 2 | B19: Room 2-2 | C19: Dorm2-R2A | E19: =IF(D19<>"","Occupied","Vacant") | F19: =IF(COUNTIFS($B:$B,B19,$E:$E,"Occupied")=2,"Yes","No") | G19: =DefaultRentPerBed | H19: =IF(E19<>"Occupied",0,COUNTIFS($B:$B,B19,$E:$E,"Occupied")) | I19: =IF(E19<>"Occupied",0,IF(H19=1,350,IF(H19=2,200,0))) | J19: =IF(E19="Occupied",IFERROR(SUMIFS('Electricity Management'!$J:$J,'Electricity Management'!$A:$A,A19,'Electricity Management'!$C:$C,B19),0),0) | K19: {=IF(E19="Occupied",IFERROR(INDEX('Electricity Management'!$T:$T,MATCH(1,('Electricity Management'!$K:$K=A19)*('Electricity Management'!$L:$L=B19),0)),0),"")} | T19: =IF(F19="Yes",A19&"-"&B19,C19)
... A35: Dorm 3 | B35: Room 3-4 | C35: Dorm3-R4A | E35: =IF(D35<>"","Occupied","Vacant") | F35: =IF(COUNTIFS($B:$B,B35,$E:$E,"Occupied")=2,"Yes","No") | G35: =DefaultRentPerBed | H35: =IF(E35<>"Occupied",0,COUNTIFS($B:$B,B35,$E:$E,"Occupied")) | I35: =IF(E35<>"Occupied",0,IF(H35=1,350,IF(H35=2,200,0))) | J35: =IF(E35="Occupied",IFERROR(SUMIFS('Electricity Management'!$J:$J,'Electricity Management'!$A:$A,A35,'Electricity Management'!$C:$C,B35),0),0) | K35: {=IF(E35="Occupied",IFERROR(INDEX('Electricity Management'!$T:$T,MATCH(1,('Electricity Management'!$K:$K=A35)*('Electricity Management'!$L:$L=B35),0)),0),"")} | T35: =IF(F35="Yes",A35&"-"&B35,C35)
A36: Dorm 3 | B36: Room 3-4 | C36: Dorm3-R4B | E36: =IF(D36<>"","Occupied","Vacant") | F36: =IF(COUNTIFS($B:$B,B36,$E:$E,"Occupied")=2,"Yes","No") | G36: =DefaultRentPerBed | H36: =COUNTIFS($B:$B,B36,$E:$E,"Occupied") | I36: =IF(E36<>"Occupied",0,IF(H36=1,350,IF(H36=2,200,0))) | J36: =IF(E36="Occupied",IFERROR(SUMIFS('Electricity Management'!$J:$J,'Electricity Management'!$A:$A,A36,'Electricity Management'!$C:$C,B36),0),0) | K36: {=IF(E36="Occupied",IFERROR(INDEX('Electricity Management'!$T:$T,MATCH(1,('Electricity Management'!$K:$K=A36)*('Electricity Management'!$L:$L=B36),0)),0),"")} | T36: =IF(F36="Yes",A36&"-"&B36,C36)
A37: Dorm 3 | B37: Room 3-5 | C37: Dorm3-R5A | E37: =IF(D37<>"","Occupied","Vacant") | F37: =IF(COUNTIFS($B:$B,B37,$E:$E,"Occupied")=2,"Yes","No") | G37: =DefaultRentPerBed | H37: =COUNTIFS($B:$B,B37,$E:$E,"Occupied") | I37: =IF(E37<>"Occupied",0,IF(H37=1,350,IF(H37=2,200,0))) | J37: =IF(E37="Occupied",IFERROR(SUMIFS('Electricity Management'!$J:$J,'Electricity Management'!$A:$A,A37,'Electricity Management'!$C:$C,B37),0),0) | K37: {=IF(E37="Occupied",IFERROR(INDEX('Electricity Management'!$T:$T,MATCH(1,('Electricity Management'!$K:$K=A37)*('Electricity Management'!$L:$L=B37),0)),0),"")} | T37: =IF(F37="Yes",A37&"-"&B37,C37)
A38: Dorm 3 | B38: Room 3-5 | C38: Dorm3-R5B | E38: =IF(D38<>"","Occupied","Vacant") | F38: =IF(COUNTIFS($B:$B,B38,$E:$E,"Occupied")=2,"Yes","No") | G38: =DefaultRentPerBed | H38: =COUNTIFS($B:$B,B38,$E:$E,"Occupied") | I38: =IF(E38<>"Occupied",0,IF(H38=1,350,IF(H38=2,200,0))) | J38: =IF(E38="Occupied",IFERROR(SUMIFS('Electricity Management'!$J:$J,'Electricity Management'!$A:$A,A38,'Electricity Management'!$C:$C,B38),0),0) | K38: {=IF(E38="Occupied",IFERROR(INDEX('Electricity Management'!$T:$T,MATCH(1,('Electricity Management'!$K:$K=A38)*('Electricity Management'!$L:$L=B38),0)),0),"")} | T38: =IF(F38="Yes",A38&"-"&B38,C38)
A39: Dorm 3 | B39: Room 3-6 | C39: Dorm3-R6A | E39: =IF(D39<>"","Occupied","Vacant") | F39: =IF(COUNTIFS($B:$B,B39,$E:$E,"Occupied")=2,"Yes","No") | G39: =DefaultRentPerBed | H39: =COUNTIFS($B:$B,B39,$E:$E,"Occupied") | I39: =IF(E39<>"Occupied",0,IF(H39=1,350,IF(H39=2,200,0))) | J39: =IF(E39="Occupied",IFERROR(SUMIFS('Electricity Management'!$J:$J,'Electricity Management'!$A:$A,A39,'Electricity Management'!$C:$C,B39),0),0) | K39: {=IF(E39="Occupied",IFERROR(INDEX('Electricity Management'!$T:$T,MATCH(1,('Electricity Management'!$K:$K=A39)*('Electricity Management'!$L:$L=B39),0)),0),"")} | T39: =IF(F39="Yes",A39&"-"&B39,C39)
A40: Dorm 3 | B40: Room 3-6 | C40: Dorm3-R6B | E40: =IF(D40<>"","Occupied","Vacant") | F40: =IF(COUNTIFS($B:$B,B40,$E:$E,"Occupied")=2,"Yes","No") | G40: =DefaultRentPerBed | H40: =COUNTIFS($B:$B,B40,$E:$E,"Occupied") | I40: =IF(E40<>"Occupied",0,IF(H40=1,350,IF(H40=2,200,0))) | J40: =IF(E40="Occupied",IFERROR(SUMIFS('Electricity Management'!$J:$J,'Electricity Management'!$A:$A,A40,'Electricity Management'!$C:$C,B40),0),0) | K40: {=IF(E40="Occupied",IFERROR(INDEX('Electricity Management'!$T:$T,MATCH(1,('Electricity Management'!$K:$K=A40)*('Electricity Management'!$L:$L=B40),0)),0),"")} | T40: =IF(F40="Yes",A40&"-"&B40,C40)
E41: =IF(D41<>"","Occupied","Vacant") | H41: =COUNTIFS($B:$B,B41,$E:$E,"Occupied") | I41: =IF(E41<>"Occupied",0,IF(H41=1,350,IF(H41=2,200,0))) | J41: =IF(E41="Occupied",IFERROR(SUMIFS('Electricity Management'!$J:$J,'Electricity Management'!$A:$A,A41,'Electricity Management'!$C:$C,B41),0),0) | K41: {=IF(E41="Occupied",IFERROR(INDEX('Electricity Management'!$T:$T,MATCH(1,('Electricity Management'!$K:$K=A41)*('Electricity Management'!$L:$L=B41),0)),0),"")} | T41: =IF(F41="Yes",A41&"-"&B41,C41)
E42: =IF(D42<>"","Occupied","Vacant") | H42: =COUNTIFS($B:$B,B42,$E:$E,"Occupied") | I42: =IF(E42<>"Occupied",0,IF(H42=1,350,IF(H42=2,200,0))) | J42: =IF(E42="Occupied",IFERROR(SUMIFS('Electricity Management'!$J:$J,'Electricity Management'!$A:$A,A42,'Electricity Management'!$C:$C,B42),0),0) | K42: {=IF(E42="Occupied",IFERROR(INDEX('Electricity Management'!$T:$T,MATCH(1,('Electricity Management'!$K:$K=A42)*('Electricity Management'!$L:$L=B42),0)),0),"")} | T42: =IF(F42="Yes",A42&"-"&B42,C42)
E43: =IF(D43<>"","Occupied","Vacant") | H43: =COUNTIFS($B:$B,B43,$E:$E,"Occupied") | I43: =IF(E43<>"Occupied",0,IF(H43=1,350,IF(H43=2,200,0))) | J43: =IF(E43="Occupied",IFERROR(SUMIFS('Electricity Management'!$J:$J,'Electricity Management'!$A:$A,A43,'Electricity Management'!$C:$C,B43),0),0) | K43: {=IF(E43="Occupied",IFERROR(INDEX('Electricity Management'!$T:$T,MATCH(1,('Electricity Management'!$K:$K=A43)*('Electricity Management'!$L:$L=B43),0)),0),"")} | T43: =IF(F43="Yes",A43&"-"&B43,C43)
E44: =IF(D44<>"","Occupied","Vacant") | H44: =COUNTIFS($B:$B,B44,$E:$E,"Occupied") | I44: =IF(E44<>"Occupied",0,IF(H44=1,350,IF(H44=2,200,0))) | J44: =IF(E44="Occupied",IFERROR(SUMIFS('Electricity Management'!$J:$J,'Electricity Management'!$A:$A,A44,'Electricity Management'!$C:$C,B44),0),0) | K44: {=IF(E44="Occupied",IFERROR(INDEX('Electricity Management'!$T:$T,MATCH(1,('Electricity Management'!$K:$K=A44)*('Electricity Management'!$L:$L=B44),0)),0),"")} | T44: =IF(F44="Yes",A44&"-"&B44,C44)
E45: =IF(D45<>"","Occupied","Vacant") | H45: =COUNTIFS($B:$B,B45,$E:$E,"Occupied") | I45: =IF(E45<>"Occupied",0,IF(H45=1,350,IF(H45=2,200,0))) | J45: =IF(E45="Occupied",IFERROR(SUMIFS('Electricity Management'!$J:$J,'Electricity Management'!$A:$A,A45,'Electricity Management'!$C:$C,B45),0),0) | K45: {=IF(E45="Occupied",IFERROR(INDEX('Electricity Management'!$T:$T,MATCH(1,('Electricity Management'!$K:$K=A45)*('Electricity Management'!$L:$L=B45),0)),0),"")} | T45: =IF(F45="Yes",A45&"-"&B45,C45)
E46: =IF(D46<>"","Occupied","Vacant") | H46: =COUNTIFS($B:$B,B46,$E:$E,"Occupied") | I46: =IF(E46<>"Occupied",0,IF(H46=1,350,IF(H46=2,200,0))) | J46: =IF(E46="Occupied",IFERROR(SUMIFS('Electricity Management'!$J:$J,'Electricity Management'!$A:$A,A46,'Electricity Management'!$C:$C,B46),0),0) | K46: {=IF(E46="Occupied",IFERROR(INDEX('Electricity Management'!$T:$T,MATCH(1,('Electricity Management'!$K:$K=A46)*('Electricity Management'!$L:$L=B46),0)),0),"")} | T46: =IF(F46="Yes",A46&"-"&B46,C46)
E47: =IF(D47<>"","Occupied","Vacant") | H47: =COUNTIFS($B:$B,B47,$E:$E,"Occupied") | I47: =IF(E47<>"Occupied",0,IF(H47=1,350,IF(H47=2,200,0))) | J47: =IF(E47="Occupied",IFERROR(SUMIFS('Electricity Management'!$J:$J,'Electricity Management'!$A:$A,A47,'Electricity Management'!$C:$C,B47),0),0) | K47: {=IF(E47="Occupied",IFERROR(INDEX('Electricity Management'!$T:$T,MATCH(1,('Electricity Management'!$K:$K=A47)*('Electricity Management'!$L:$L=B47),0)),0),"")} | T47: =IF(F47="Yes",A47&"-"&B47,C47)
E48: =IF(D48<>"","Occupied","Vacant") | H48: =COUNTIFS($B:$B,B48,$E:$E,"Occupied") | I48: =IF(E48<>"Occupied",0,IF(H48=1,350,IF(H48=2,200,0))) | J48: =IF(E48="Occupied",IFERROR(SUMIFS('Electricity Management'!$J:$J,'Electricity Management'!$A:$A,A48,'Electricity Management'!$C:$C,B48),0),0) | K48: {=IF(E48="Occupied",IFERROR(INDEX('Electricity Management'!$T:$T,MATCH(1,('Electricity Management'!$K:$K=A48)*('Electricity Management'!$L:$L=B48),0)),0),"")} | T48: =IF(F48="Yes",A48&"-"&B48,C48)
E49: =IF(D49<>"","Occupied","Vacant") | H49: =COUNTIFS($B:$B,B49,$E:$E,"Occupied") | I49: =IF(E49<>"Occupied",0,IF(H49=1,350,IF(H49=2,200,0))) | J49: =IF(E49="Occupied",IFERROR(SUMIFS('Electricity Management'!$J:$J,'Electricity Management'!$A:$A,A49,'Electricity Management'!$C:$C,B49),0),0) | K49: {=IF(E49="Occupied",IFERROR(INDEX('Electricity Management'!$T:$T,MATCH(1,('Electricity Management'!$K:$K=A49)*('Electricity Management'!$L:$L=B49),0)),0),"")} | T49: =IF(F49="Yes",A49&"-"&B49,C49)
E50: =IF(D50<>"","Occupied","Vacant") | H50: =COUNTIFS($B:$B,B50,$E:$E,"Occupied") | I50: =IF(E50<>"Occupied",0,IF(H50=1,350,IF(H50=2,200,0))) | J50: =IF(E50="Occupied",IFERROR(SUMIFS('Electricity Management'!$J:$J,'Electricity Management'!$A:$A,A50,'Electricity Management'!$C:$C,B50),0),0) | K50: {=IF(E50="Occupied",IFERROR(INDEX('Electricity Management'!$T:$T,MATCH(1,('Electricity Management'!$K:$K=A50)*('Electricity Management'!$L:$L=B50),0)),0),"")} | T50: =IF(F50="Yes",A50&"-"&B50,C50)
E51: =IF(D51<>"","Occupied","Vacant") | H51: =COUNTIFS($B:$B,B51,$E:$E,"Occupied") | I51: =IF(E51<>"Occupied",0,IF(H51=1,350,IF(H51=2,200,0))) | J51: =IF(E51="Occupied",IFERROR(SUMIFS('Electricity Management'!$J:$J,'Electricity Management'!$A:$A,A51,'Electricity Management'!$C:$C,B51),0),0) | K51: {=IF(E51="Occupied",IFERROR(INDEX('Electricity Management'!$T:$T,MATCH(1,('Electricity Management'!$K:$K=A51)*('Electricity Management'!$L:$L=B51),0)),0),"")} | T51: =IF(F51="Yes",A51&"-"&B51,C51)
E52: =IF(D52<>"","Occupied","Vacant") | H52: =COUNTIFS($B:$B,B52,$E:$E,"Occupied") | I52: =IF(E52<>"Occupied",0,IF(H52=1,350,IF(H52=2,200,0))) | J52: =IF(E52="Occupied",IFERROR(SUMIFS('Electricity Management'!$J:$J,'Electricity Management'!$A:$A,A52,'Electricity Management'!$C:$C,B52),0),0) | K52: {=IF(E52="Occupied",IFERROR(INDEX('Electricity Management'!$T:$T,MATCH(1,('Electricity Management'!$K:$K=A52)*('Electricity Management'!$L:$L=B52),0)),0),"")} | T52: =IF(F52="Yes",A52&"-"&B52,C52)
... E110: =IF(D110<>"","Occupied","Vacant") | H110: =COUNTIFS($B:$B,B110,$E:$E,"Occupied") | I110: =IF(E110<>"Occupied",0,IF(H110=1,350,IF(H110=2,200,0))) | J110: =IF(E110="Occupied",IFERROR(SUMIFS('Electricity Management'!$J:$J,'Electricity Management'!$A:$A,A110,'Electricity Management'!$C:$C,B110),0),0) | K110: {=IF(E110="Occupied",IFERROR(INDEX('Electricity Management'!$T:$T,MATCH(1,('Electricity Management'!$K:$K=A110)*('Electricity Management'!$L:$L=B110),0)),0),"")} | T110: =IF(F110="Yes",A110&"-"&B110,C110)
E111: =IF(D111<>"","Occupied","Vacant") | H111: =COUNTIFS($B:$B,B111,$E:$E,"Occupied") | I111: =IF(E111<>"Occupied",0,IF(H111=1,350,IF(H111=2,200,0))) | J111: =IF(E111="Occupied",IFERROR(SUMIFS('Electricity Management'!$J:$J,'Electricity Management'!$A:$A,A111,'Electricity Management'!$C:$C,B111),0),0) | K111: =IF(E111="Occupied",IFERROR(SUMIFS('Electricity Management'!$T:$T,'Electricity Management'!$K:$K,A111,'Electricity Management'!$L:$L,B111),0),0) | T111: =IF(F111="Yes",A111&"-"&B111,C111)
E112: =IF(D112<>"","Occupied","Vacant") | H112: =COUNTIFS($B:$B,B112,$E:$E,"Occupied") | I112: =IF(E112<>"Occupied",0,IF(H112=1,350,IF(H112=2,200,0))) | J112: =IF(E112="Occupied",IFERROR(SUMIFS('Electricity Management'!$J:$J,'Electricity Management'!$A:$A,A112,'Electricity Management'!$C:$C,B112),0),0) | K112: =IF(E112="Occupied",IFERROR(SUMIFS('Electricity Management'!$T:$T,'Electricity Management'!$K:$K,A112,'Electricity Management'!$L:$L,B112),0),0) | T112: =IF(F112="Yes",A112&"-"&B112,C112)
E113: =IF(D113<>"","Occupied","Vacant") | H113: =COUNTIFS($B:$B,B113,$E:$E,"Occupied") | I113: =IF(E113<>"Occupied",0,IF(H113=1,350,IF(H113=2,200,0))) | J113: =IF(E113="Occupied",IFERROR(SUMIFS('Electricity Management'!$J:$J,'Electricity Management'!$A:$A,A113,'Electricity Management'!$C:$C,B113),0),0) | K113: =IF(E113="Occupied",IFERROR(SUMIFS('Electricity Management'!$T:$T,'Electricity Management'!$K:$K,A113,'Electricity Management'!$L:$L,B113),0),0) | T113: =IF(F113="Yes",A113&"-"&B113,C113)
E114: =IF(D114<>"","Occupied","Vacant") | H114: =COUNTIFS($B:$B,B114,$E:$E,"Occupied") | I114: =IF(E114<>"Occupied",0,IF(H114=1,350,IF(H114=2,200,0))) | J114: =IF(E114="Occupied",IFERROR(SUMIFS('Electricity Management'!$J:$J,'Electricity Management'!$A:$A,A114,'Electricity Management'!$C:$C,B114),0),0) | K114: =IF(E114="Occupied",IFERROR(SUMIFS('Electricity Management'!$T:$T,'Electricity Management'!$K:$K,A114,'Electricity Management'!$L:$L,B114),0),0) | T114: =IF(F114="Yes",A114&"-"&B114,C114)
E115: =IF(D115<>"","Occupied","Vacant") | H115: =COUNTIFS($B:$B,B115,$E:$E,"Occupied") | I115: =IF(E115<>"Occupied",0,IF(H115=1,350,IF(H115=2,200,0))) | J115: =IF(E115="Occupied",IFERROR(SUMIFS('Electricity Management'!$J:$J,'Electricity Management'!$A:$A,A115,'Electricity Management'!$C:$C,B115),0),0) | K115: =IF(E115="Occupied",IFERROR(SUMIFS('Electricity Management'!$T:$T,'Electricity Management'!$K:$K,A115,'Electricity Management'!$L:$L,B115),0),0) | T115: =IF(F115="Yes",A115&"-"&B115,C115)
E116: =IF(D116<>"","Occupied","Vacant") | H116: =COUNTIFS($B:$B,B116,$E:$E,"Occupied") | I116: =IF(E116<>"Occupied",0,IF(H116=1,350,IF(H116=2,200,0))) | J116: =IF(E116="Occupied",IFERROR(SUMIFS('Electricity Management'!$J:$J,'Electricity Management'!$A:$A,A116,'Electricity Management'!$C:$C,B116),0),0) | K116: =IF(E116="Occupied",IFERROR(SUMIFS('Electricity Management'!$T:$T,'Electricity Management'!$K:$K,A116,'Electricity Management'!$L:$L,B116),0),0) | T116: =IF(F116="Yes",A116&"-"&B116,C116)
E117: =IF(D117<>"","Occupied","Vacant") | H117: =COUNTIFS($B:$B,B117,$E:$E,"Occupied") | I117: =IF(E117<>"Occupied",0,IF(H117=1,350,IF(H117=2,200,0))) | J117: =IF(E117="Occupied",IFERROR(SUMIFS('Electricity Management'!$J:$J,'Electricity Management'!$A:$A,A117,'Electricity Management'!$C:$C,B117),0),0) | K117: =IF(E117="Occupied",IFERROR(SUMIFS('Electricity Management'!$T:$T,'Electricity Management'!$K:$K,A117,'Electricity Management'!$L:$L,B117),0),0) | T117: =IF(F117="Yes",A117&"-"&B117,C117)
E118: =IF(D118<>"","Occupied","Vacant") | H118: =COUNTIFS($B:$B,B118,$E:$E,"Occupied") | I118: =IF(E118<>"Occupied",0,IF(H118=1,350,IF(H118=2,200,0))) | J118: =IF(E118="Occupied",IFERROR(SUMIFS('Electricity Management'!$J:$J,'Electricity Management'!$A:$A,A118,'Electricity Management'!$C:$C,B118),0),0) | K118: =IF(E118="Occupied",IFERROR(SUMIFS('Electricity Management'!$T:$T,'Electricity Management'!$K:$K,A118,'Electricity Management'!$L:$L,B118),0),0) | T118: =IF(F118="Yes",A118&"-"&B118,C118)
E119: =IF(D119<>"","Occupied","Vacant") | H119: =COUNTIFS($B:$B,B119,$E:$E,"Occupied") | I119: =IF(E119<>"Occupied",0,IF(H119=1,350,IF(H119=2,200,0))) | J119: =IF(E119="Occupied",IFERROR(SUMIFS('Electricity Management'!$J:$J,'Electricity Management'!$A:$A,A119,'Electricity Management'!$C:$C,B119),0),0) | K119: =IF(E119="Occupied",IFERROR(SUMIFS('Electricity Management'!$T:$T,'Electricity Management'!$K:$K,A119,'Electricity Management'!$L:$L,B119),0),0) | T119: =IF(F119="Yes",A119&"-"&B119,C119)
E120: =IF(D120<>"","Occupied","Vacant") | H120: =COUNTIFS($B:$B,B120,$E:$E,"Occupied") | I120: =IF(E120<>"Occupied",0,IF(H120=1,350,IF(H120=2,200,0))) | J120: =IF(E120="Occupied",IFERROR(SUMIFS('Electricity Management'!$J:$J,'Electricity Management'!$A:$A,A120,'Electricity Management'!$C:$C,B120),0),0) | K120: =IF(E120="Occupied",IFERROR(SUMIFS('Electricity Management'!$T:$T,'Electricity Management'!$K:$K,A120,'Electricity Management'!$L:$L,B120),0),0) | T120: =IF(F120="Yes",A120&"-"&B120,C120)
E121: =IF(D121<>"","Occupied","Vacant") | H121: =COUNTIFS($B:$B,B121,$E:$E,"Occupied") | I121: =IF(E121<>"Occupied",0,IF(H121=1,350,IF(H121=2,200,0))) | J121: =IF(E121="Occupied",IFERROR(SUMIFS('Electricity Management'!$J:$J,'Electricity Management'!$A:$A,A121,'Electricity Management'!$C:$C,B121),0),0) | K121: =IF(E121="Occupied",IFERROR(SUMIFS('Electricity Management'!$T:$T,'Electricity Management'!$K:$K,A121,'Electricity Management'!$L:$L,B121),0),0) | T121: =IF(F121="Yes",A121&"-"&B121,C121)
E122: =IF(D122<>"","Occupied","Vacant") | H122: =COUNTIFS($B:$B,B122,$E:$E,"Occupied") | I122: =IF(E122<>"Occupied",0,IF(H122=1,350,IF(H122=2,200,0))) | J122: =IF(E122="Occupied",IFERROR(SUMIFS('Electricity Management'!$J:$J,'Electricity Management'!$A:$A,A122,'Electricity Management'!$C:$C,B122),0),0) | K122: =IF(E122="Occupied",IFERROR(SUMIFS('Electricity Management'!$T:$T,'Electricity Management'!$K:$K,A122,'Electricity Management'!$L:$L,B122),0),0) | T122: =IF(F122="Yes",A122&"-"&B122,C122)
... E428: =IF(D428<>"","Occupied","Vacant") | H428: =COUNTIFS($B:$B,B428,$E:$E,"Occupied") | I428: =IF(E428<>"Occupied",0,IF(H428=1,350,IF(H428=2,200,0))) | J428: =IF(E428="Occupied",IFERROR(SUMIFS('Electricity Management'!$J:$J,'Electricity Management'!$A:$A,A428,'Electricity Management'!$C:$C,B428),0),0) | K428: =IF(E428="Occupied",IFERROR(SUMIFS('Electricity Management'!$T:$T,'Electricity Management'!$K:$K,A428,'Electricity Management'!$L:$L,B428),0),0) | T428: =IF(F428="Yes",A428&"-"&B428,C428)

Sheet Electricity Management
A1: Advanced Electricity Management System
A2: Room, generator, government, and common-area split calculations.
A3: IMPORTANT: Dorm column = Dorm 1 / Dorm 2 / Dorm 3. Do NOT type client names here. Client names stay in Client DB column D.
A4: SECTION A - ROOM ELECTRICITY | K4: SECTION B - COMMON AREA ELECTRICITY | U4: SECTION C - PRORATA FACTURE
A5: Dorm | B5: Month | C5: Room Number | D5: Total Room Meter kWh | E5: Generator kWh Supplied | F5: Government kWh | G5: Generator Charge | H5: Government Charge | I5: Total Room Electricity | J5: elec/ocupaied | K5: Dorm | L5: room | M5: Total Occupied Beds | N5: Common Area Meter kWh | O5: Generator kWh Supplied | P5: Government kWh | Q5: Generator Charge | R5: Government Charge | S5: Common Area Cost | T5: Common Area Per Person | U5: Invoice Month | V5: Client | W5: Dorm | X5: Room | Y5: Prorata Days | Z5: Prorata Factor | AA5: Room Elec Prorata | AB5: Area Elec Prorata
A6: Dorm 1 | B6: 46023 | C6: Room 1-1 | D6: 500 | E6: 0 | F6: =MAX(D6-E6,0) | G6: =E6*GeneratorRate | H6: =F6*GovernmentRate | I6: =G6+H6 | J6: =IFERROR(I6/COUNTIFS('Client DB & Bed Mgmt'!$A:$A,A6,'Client DB & Bed Mgmt'!$B:$B,C6,'Client DB & Bed Mgmt'!$D:$D,"<>"),0) | K6: Dorm 1 | L6: Room 1-1 | M6: =COUNTIFS('Client DB & Bed Mgmt'!$A:$A,$K6,'Client DB & Bed Mgmt'!$B:$B,$L6,'Client DB & Bed Mgmt'!$D:$D,"<>") | N6: 100 | O6: 600 | P6: =MAX(N6-O6,0) | Q6: =O6*GeneratorRate | R6: =P6*GovernmentRate | S6: =Q6+R6 | T6: =IF(M6=0,0,S6/M6) | U6: ='Invoice Generator'!$C$7 | V6: ='Invoice Generator'!$C$6 | W6: ='Invoice Generator'!$C$11 | X6: ='Invoice Generator'!$C$12 | Y6: =IFERROR(MAX(0,MIN(IF(OR('Invoice Generator'!$G$13="",NOT(ISNUMBER('Invoice Generator'!$G$13))),EOMONTH($U$6,0),'Invoice Generator'!$G$13),EOMONTH($U$6,0))-MAX(IF(OR('Invoice Generator'!$G$12="",NOT(ISNUMBER('Invoice Generator'!$G$12))),DATE(YEAR($U$6),MONTH($U$6),1),'Invoice Generator'!$G$12),DATE(YEAR($U$6),MONTH($U$6),1))+1),0) | Z6: =IFERROR($Y$6/DAY(EOMONTH($U$6,0)),0) | AA6: ='Invoice Generator'!$G$19*$Z$6 | AB6: ='Invoice Generator'!$G$20*$Z$6
A7: Dorm 1 | B7: 46023 | C7: Room 1-2 | D7: 0 | E7: 0 | F7: =MAX(D7-E7,0) | G7: =E7*GeneratorRate | H7: =F7*GovernmentRate | I7: =G7+H7 | J7: =IFERROR(I7/COUNTIFS('Client DB & Bed Mgmt'!$A:$A,A7,'Client DB & Bed Mgmt'!$B:$B,C7,'Client DB & Bed Mgmt'!$D:$D,"<>"),0) | K7: Dorm 1 | L7: Room 1-2 | M7: =COUNTIFS('Client DB & Bed Mgmt'!$A:$A,$K7,'Client DB & Bed Mgmt'!$B:$B,$L7,'Client DB & Bed Mgmt'!$D:$D,"<>") | N7: 100 | O7: 455 | P7: =MAX(N7-O7,0) | Q7: =O7*GeneratorRate | R7: =P7*GovernmentRate | S7: =Q7+R7 | T7: =IF(M7=0,0,S7/M7)
A8: Dorm 1 | B8: 46023 | C8: Room 1-3 | D8: 0 | E8: 0 | F8: =MAX(D8-E8,0) | G8: =E8*GeneratorRate | H8: =F8*GovernmentRate | I8: =G8+H8 | J8: =IFERROR(I8/COUNTIFS('Client DB & Bed Mgmt'!$A:$A,A8,'Client DB & Bed Mgmt'!$B:$B,C8,'Client DB & Bed Mgmt'!$D:$D,"<>"),0) | K8: Dorm 1 | L8: Room 1-3 | M8: =COUNTIFS('Client DB & Bed Mgmt'!$A:$A,$K8,'Client DB & Bed Mgmt'!$B:$B,$L8,'Client DB & Bed Mgmt'!$D:$D,"<>") | N8: 0 | O8: 0 | P8: =MAX(N8-O8,0) | Q8: =O8*GeneratorRate | R8: =P8*GovernmentRate | S8: =Q8+R8 | T8: =IF(M8=0,0,S8/M8)
A9: Dorm 1 | B9: 46023 | C9: Room 1-4 | D9: 0 | E9: 0 | F9: =MAX(D9-E9,0) | G9: =E9*GeneratorRate | H9: =F9*GovernmentRate | I9: =G9+H9 | J9: =IFERROR(I9/COUNTIFS('Client DB & Bed Mgmt'!$A:$A,A9,'Client DB & Bed Mgmt'!$B:$B,C9,'Client DB & Bed Mgmt'!$D:$D,"<>"),0) | K9: Dorm 1 | L9: Room 1-4 | M9: =COUNTIFS('Client DB & Bed Mgmt'!$A:$A,$K9,'Client DB & Bed Mgmt'!$B:$B,$L9,'Client DB & Bed Mgmt'!$D:$D,"<>") | N9: 0 | O9: 0 | P9: =MAX(N9-O9,0) | Q9: =O9*GeneratorRate | R9: =P9*GovernmentRate | S9: =Q9+R9 | T9: =IF(M9=0,0,S9/M9)
A10: Dorm 1 | B10: 46023 | C10: Room 1-5 | D10: 0 | E10: 0 | F10: =MAX(D10-E10,0) | G10: =E10*GeneratorRate | H10: =F10*GovernmentRate | I10: =G10+H10 | J10: =IFERROR(I10/COUNTIFS('Client DB & Bed Mgmt'!$A:$A,A10,'Client DB & Bed Mgmt'!$B:$B,C10,'Client DB & Bed Mgmt'!$D:$D,"<>"),0) | K10: Dorm 1 | L10: Room 1-5 | M10: =COUNTIFS('Client DB & Bed Mgmt'!$A:$A,$K10,'Client DB & Bed Mgmt'!$B:$B,$L10,'Client DB & Bed Mgmt'!$D:$D,"<>") | N10: 700 | O10: 0 | P10: =MAX(N10-O10,0) | Q10: =O10*GeneratorRate | R10: =P10*GovernmentRate | S10: =Q10+R10 | T10: =IF(M10=0,0,S10/M10)
A11: Dorm 1 | B11: 46023 | C11: Room 1-6 | D11: 0 | E11: 0 | F11: =MAX(D11-E11,0) | G11: =E11*GeneratorRate | H11: =F11*GovernmentRate | I11: =G11+H11 | J11: =IFERROR(I11/COUNTIFS('Client DB & Bed Mgmt'!$A:$A,A11,'Client DB & Bed Mgmt'!$B:$B,C11,'Client DB & Bed Mgmt'!$D:$D,"<>"),0) | K11: Dorm 1 | L11: Room 1-6 | M11: =COUNTIFS('Client DB & Bed Mgmt'!$A:$A,$K11,'Client DB & Bed Mgmt'!$B:$B,$L11,'Client DB & Bed Mgmt'!$D:$D,"<>") | N11: 0 | O11: 0 | P11: =MAX(N11-O11,0) | Q11: =O11*GeneratorRate | R11: =P11*GovernmentRate | S11: =Q11+R11 | T11: =IF(M11=0,0,S11/M11)
A12: Dorm 1 | B12: 46054 | C12: Room 1-1 | D12: 1550 | E12: 0 | F12: =MAX(D12-E12,0) | G12: =E12*GeneratorRate | H12: =F12*GovernmentRate | I12: =G12+H12 | J12: =IFERROR(I12/COUNTIFS('Client DB & Bed Mgmt'!$A:$A,A12,'Client DB & Bed Mgmt'!$B:$B,C12,'Client DB & Bed Mgmt'!$D:$D,"<>"),0) | K12: Dorm 1 | L12: Room 1-1 | M12: =COUNTIFS('Client DB & Bed Mgmt'!$A:$A,$K12,'Client DB & Bed Mgmt'!$B:$B,$L12,'Client DB & Bed Mgmt'!$D:$D,"<>") | N12: 0 | O12: 0 | P12: =MAX(N12-O12,0) | Q12: =O12*GeneratorRate | R12: =P12*GovernmentRate | S12: =Q12+R12 | T12: =IF(M12=0,0,S12/M12)
A13: Dorm 1 | B13: 46054 | C13: Room 1-2 | D13: 100 | E13: 0 | F13: =MAX(D13-E13,0) | G13: =E13*GeneratorRate | H13: =F13*GovernmentRate | I13: =G13+H13 | J13: =IFERROR(I13/COUNTIFS('Client DB & Bed Mgmt'!$A:$A,A13,'Client DB & Bed Mgmt'!$B:$B,C13,'Client DB & Bed Mgmt'!$D:$D,"<>"),0) | K13: Dorm 1 | L13: Room 1-2 | M13: =COUNTIFS('Client DB & Bed Mgmt'!$A:$A,$K13,'Client DB & Bed Mgmt'!$B:$B,$L13,'Client DB & Bed Mgmt'!$D:$D,"<>") | N13: 0 | O13: 0 | P13: =MAX(N13-O13,0) | Q13: =O13*GeneratorRate | R13: =P13*GovernmentRate | S13: =Q13+R13 | T13: =IF(M13=0,0,S13/M13)
A14: Dorm 1 | B14: 46054 | C14: Room 1-3 | D14: 0 | E14: 0 | F14: =MAX(D14-E14,0) | G14: =E14*GeneratorRate | H14: =F14*GovernmentRate | I14: =G14+H14 | J14: =IFERROR(I14/COUNTIFS('Client DB & Bed Mgmt'!$A:$A,A14,'Client DB & Bed Mgmt'!$B:$B,C14,'Client DB & Bed Mgmt'!$D:$D,"<>"),0) | K14: Dorm 1 | L14: Room 1-3 | M14: =COUNTIFS('Client DB & Bed Mgmt'!$A:$A,$K14,'Client DB & Bed Mgmt'!$B:$B,$L14,'Client DB & Bed Mgmt'!$D:$D,"<>") | N14: 0 | O14: 0 | P14: =MAX(N14-O14,0) | Q14: =O14*GeneratorRate | R14: =P14*GovernmentRate | S14: =Q14+R14 | T14: =IF(M14=0,0,S14/M14)
A15: Dorm 1 | B15: 46054 | C15: Room 1-4 | D15: 0 | E15: 0 | F15: =MAX(D15-E15,0) | G15: =E15*GeneratorRate | H15: =F15*GovernmentRate | I15: =G15+H15 | J15: =IFERROR(I15/COUNTIFS('Client DB & Bed Mgmt'!$A:$A,A15,'Client DB & Bed Mgmt'!$B:$B,C15,'Client DB & Bed Mgmt'!$D:$D,"<>"),0) | K15: Dorm 1 | L15: Room 1-4 | M15: =COUNTIFS('Client DB & Bed Mgmt'!$A:$A,$K15,'Client DB & Bed Mgmt'!$B:$B,$L15,'Client DB & Bed Mgmt'!$D:$D,"<>") | N15: 0 | O15: 0 | P15: =MAX(N15-O15,0) | Q15: =O15*GeneratorRate | R15: =P15*GovernmentRate | S15: =Q15+R15 | T15: =IF(M15=0,0,S15/M15)
A16: Dorm 1 | B16: 46054 | C16: Room 1-5 | D16: 0 | E16: 0 | F16: =MAX(D16-E16,0) | G16: =E16*GeneratorRate | H16: =F16*GovernmentRate | I16: =G16+H16 | J16: =IFERROR(I16/COUNTIFS('Client DB & Bed Mgmt'!$A:$A,A16,'Client DB & Bed Mgmt'!$B:$B,C16,'Client DB & Bed Mgmt'!$D:$D,"<>"),0) | K16: Dorm 1 | L16: Room 1-5 | M16: =COUNTIFS('Client DB & Bed Mgmt'!$A:$A,$K16,'Client DB & Bed Mgmt'!$B:$B,$L16,'Client DB & Bed Mgmt'!$D:$D,"<>") | N16: 0 | O16: 0 | P16: =MAX(N16-O16,0) | Q16: =O16*GeneratorRate | R16: =P16*GovernmentRate | S16: =Q16+R16 | T16: =IF(M16=0,0,S16/M16)
A17: Dorm 1 | B17: 46054 | C17: Room 1-6 | D17: 0 | E17: 0 | F17: =MAX(D17-E17,0) | G17: =E17*GeneratorRate | H17: =F17*GovernmentRate | I17: =G17+H17 | J17: =IFERROR(I17/COUNTIFS('Client DB & Bed Mgmt'!$A:$A,A17,'Client DB & Bed Mgmt'!$B:$B,C17,'Client DB & Bed Mgmt'!$D:$D,"<>"),0) | K17: Dorm 1 | L17: Room 1-6 | M17: =COUNTIFS('Client DB & Bed Mgmt'!$A:$A,$K17,'Client DB & Bed Mgmt'!$B:$B,$L17,'Client DB & Bed Mgmt'!$D:$D,"<>") | N17: 0 | O17: 0 | P17: =MAX(N17-O17,0) | Q17: =O17*GeneratorRate | R17: =P17*GovernmentRate | S17: =Q17+R17 | T17: =IF(M17=0,0,S17/M17)
A18: Dorm 1 | B18: 46082 | C18: Room 1-1 | D18: 0 | E18: 0 | F18: =MAX(D18-E18,0) | G18: =E18*GeneratorRate | H18: =F18*GovernmentRate | I18: =G18+H18 | J18: =IFERROR(I18/COUNTIFS('Client DB & Bed Mgmt'!$A:$A,A18,'Client DB & Bed Mgmt'!$B:$B,C18,'Client DB & Bed Mgmt'!$D:$D,"<>"),0) | K18: Dorm 1 | L18: Room 1-1 | M18: =COUNTIFS('Client DB & Bed Mgmt'!$A:$A,$K18,'Client DB & Bed Mgmt'!$B:$B,$L18,'Client DB & Bed Mgmt'!$D:$D,"<>") | N18: 0 | O18: 0 | P18: =MAX(N18-O18,0) | Q18: =O18*GeneratorRate | R18: =P18*GovernmentRate | S18: =Q18+R18 | T18: =IF(M18=0,0,S18/M18)
... A41: Dorm 1 | B41: 46174 | C41: Room 1-6 | D41: 0 | E41: 0 | F41: =MAX(D41-E41,0) | G41: =E41*GeneratorRate | H41: =F41*GovernmentRate | I41: =G41+H41 | J41: =IFERROR(I41/COUNTIFS('Client DB & Bed Mgmt'!$A:$A,A41,'Client DB & Bed Mgmt'!$B:$B,C41,'Client DB & Bed Mgmt'!$D:$D,"<>"),0) | K41: Dorm 1 | L41: Room 1-6 | M41: =COUNTIFS('Client DB & Bed Mgmt'!$A:$A,$K41,'Client DB & Bed Mgmt'!$B:$B,$L41,'Client DB & Bed Mgmt'!$D:$D,"<>") | N41: 0 | O41: 0 | P41: =MAX(N41-O41,0) | Q41: =O41*GeneratorRate | R41: =P41*GovernmentRate | S41: =Q41+R41 | T41: =IF(M41=0,0,S41/M41)
A42: Dorm 1 | B42: 46204 | C42: Room 1-1 | D42: 0 | E42: 0 | F42: =MAX(D42-E42,0) | G42: =E42*GeneratorRate | H42: =F42*GovernmentRate | I42: =G42+H42 | J42: =IFERROR(I42/COUNTIFS('Client DB & Bed Mgmt'!$A:$A,A42,'Client DB & Bed Mgmt'!$B:$B,C42,'Client DB & Bed Mgmt'!$D:$D,"<>"),0) | K42: Dorm 1 | L42: Room 1-1 | M42: =COUNTIFS('Client DB & Bed Mgmt'!$A:$A,$K42,'Client DB & Bed Mgmt'!$B:$B,$L42,'Client DB & Bed Mgmt'!$D:$D,"<>") | P42: =IF(N42="","",MAX(N42-O42,0)) | Q42: =IF(O42="","",O42*GeneratorRate) | R42: =IF(P42="","",P42*GovernmentRate) | S42: =IF(N42="","",Q42+R42) | T42: =IF(M42=0,0,S42/M42)
A43: Dorm 1 | B43: 46204 | C43: Room 1-2 | D43: 0 | E43: 0 | F43: =MAX(D43-E43,0) | G43: =E43*GeneratorRate | H43: =F43*GovernmentRate | I43: =G43+H43 | J43: =IFERROR(I43/COUNTIFS('Client DB & Bed Mgmt'!$A:$A,A43,'Client DB & Bed Mgmt'!$B:$B,C43,'Client DB & Bed Mgmt'!$D:$D,"<>"),0) | K43: Dorm 1 | L43: Room 1-2 | M43: =COUNTIFS('Client DB & Bed Mgmt'!$A:$A,$K43,'Client DB & Bed Mgmt'!$B:$B,$L43,'Client DB & Bed Mgmt'!$D:$D,"<>") | P43: =IF(N43="","",MAX(N43-O43,0)) | Q43: =IF(O43="","",O43*GeneratorRate) | R43: =IF(P43="","",P43*GovernmentRate) | S43: =IF(N43="","",Q43+R43) | T43: =IF(M43=0,0,S43/M43)
A44: Dorm 1 | B44: 46204 | C44: Room 1-3 | D44: 0 | E44: 0 | F44: =MAX(D44-E44,0) | G44: =E44*GeneratorRate | H44: =F44*GovernmentRate | I44: =G44+H44 | J44: =IFERROR(I44/COUNTIFS('Client DB & Bed Mgmt'!$A:$A,A44,'Client DB & Bed Mgmt'!$B:$B,C44,'Client DB & Bed Mgmt'!$D:$D,"<>"),0) | K44: Dorm 1 | L44: Room 1-3 | M44: =COUNTIFS('Client DB & Bed Mgmt'!$A:$A,$K44,'Client DB & Bed Mgmt'!$B:$B,$L44,'Client DB & Bed Mgmt'!$D:$D,"<>") | P44: =IF(N44="","",MAX(N44-O44,0)) | Q44: =IF(O44="","",O44*GeneratorRate) | R44: =IF(P44="","",P44*GovernmentRate) | S44: =IF(N44="","",Q44+R44) | T44: =IF(M44=0,0,S44/M44)
A45: Dorm 1 | B45: 46204 | C45: Room 1-4 | D45: 0 | E45: 0 | F45: =MAX(D45-E45,0) | G45: =E45*GeneratorRate | H45: =F45*GovernmentRate | I45: =G45+H45 | J45: =IFERROR(I45/COUNTIFS('Client DB & Bed Mgmt'!$A:$A,A45,'Client DB & Bed Mgmt'!$B:$B,C45,'Client DB & Bed Mgmt'!$D:$D,"<>"),0) | K45: Dorm 1 | L45: Room 1-4 | M45: =COUNTIFS('Client DB & Bed Mgmt'!$A:$A,$K45,'Client DB & Bed Mgmt'!$B:$B,$L45,'Client DB & Bed Mgmt'!$D:$D,"<>") | P45: =IF(N45="","",MAX(N45-O45,0)) | Q45: =IF(O45="","",O45*GeneratorRate) | R45: =IF(P45="","",P45*GovernmentRate) | S45: =IF(N45="","",Q45+R45) | T45: =IF(M45=0,0,S45/M45)
A46: Dorm 1 | B46: 46204 | C46: Room 1-5 | D46: 0 | E46: 0 | F46: =MAX(D46-E46,0) | G46: =E46*GeneratorRate | H46: =F46*GovernmentRate | I46: =G46+H46 | J46: =IFERROR(I46/COUNTIFS('Client DB & Bed Mgmt'!$A:$A,A46,'Client DB & Bed Mgmt'!$B:$B,C46,'Client DB & Bed Mgmt'!$D:$D,"<>"),0) | K46: Dorm 1 | L46: Room 1-5 | M46: =COUNTIFS('Client DB & Bed Mgmt'!$A:$A,$K46,'Client DB & Bed Mgmt'!$B:$B,$L46,'Client DB & Bed Mgmt'!$D:$D,"<>") | P46: =IF(N46="","",MAX(N46-O46,0)) | Q46: =IF(O46="","",O46*GeneratorRate) | R46: =IF(P46="","",P46*GovernmentRate) | S46: =IF(N46="","",Q46+R46) | T46: =IF(M46=0,0,S46/M46)
A47: Dorm 1 | B47: 46204 | C47: Room 1-6 | D47: 0 | E47: 0 | F47: =MAX(D47-E47,0) | G47: =E47*GeneratorRate | H47: =F47*GovernmentRate | I47: =G47+H47 | J47: =IFERROR(I47/COUNTIFS('Client DB & Bed Mgmt'!$A:$A,A47,'Client DB & Bed Mgmt'!$B:$B,C47,'Client DB & Bed Mgmt'!$D:$D,"<>"),0) | K47: Dorm 1 | L47: Room 1-6 | M47: =COUNTIFS('Client DB & Bed Mgmt'!$A:$A,$K47,'Client DB & Bed Mgmt'!$B:$B,$L47,'Client DB & Bed Mgmt'!$D:$D,"<>") | P47: =IF(N47="","",MAX(N47-O47,0)) | Q47: =IF(O47="","",O47*GeneratorRate) | R47: =IF(P47="","",P47*GovernmentRate) | S47: =IF(N47="","",Q47+R47) | T47: =IF(M47=0,0,S47/M47)
A48: Dorm 1 | B48: 46235 | C48: Room 1-1 | D48: 0 | E48: 0 | F48: =MAX(D48-E48,0) | G48: =E48*GeneratorRate | H48: =F48*GovernmentRate | I48: =G48+H48 | J48: =IFERROR(I48/COUNTIFS('Client DB & Bed Mgmt'!$A:$A,A48,'Client DB & Bed Mgmt'!$B:$B,C48,'Client DB & Bed Mgmt'!$D:$D,"<>"),0) | K48: Dorm 1 | L48: Room 1-1 | M48: =COUNTIFS('Client DB & Bed Mgmt'!$A:$A,$K48,'Client DB & Bed Mgmt'!$B:$B,$L48,'Client DB & Bed Mgmt'!$D:$D,"<>") | P48: =IF(N48="","",MAX(N48-O48,0)) | Q48: =IF(O48="","",O48*GeneratorRate) | R48: =IF(P48="","",P48*GovernmentRate) | S48: =IF(N48="","",Q48+R48) | T48: =IF(M48=0,0,S48/M48)
A49: Dorm 1 | B49: 46235 | C49: Room 1-2 | D49: 0 | E49: 0 | F49: =MAX(D49-E49,0) | G49: =E49*GeneratorRate | H49: =F49*GovernmentRate | I49: =G49+H49 | J49: =IFERROR(I49/COUNTIFS('Client DB & Bed Mgmt'!$A:$A,A49,'Client DB & Bed Mgmt'!$B:$B,C49,'Client DB & Bed Mgmt'!$D:$D,"<>"),0) | K49: Dorm 1 | L49: Room 1-2 | M49: =COUNTIFS('Client DB & Bed Mgmt'!$A:$A,$K49,'Client DB & Bed Mgmt'!$B:$B,$L49,'Client DB & Bed Mgmt'!$D:$D,"<>") | P49: =IF(N49="","",MAX(N49-O49,0)) | Q49: =IF(O49="","",O49*GeneratorRate) | R49: =IF(P49="","",P49*GovernmentRate) | S49: =IF(N49="","",Q49+R49) | T49: =IF(M49=0,0,S49/M49)
A50: Dorm 1 | B50: 46235 | C50: Room 1-3 | D50: 0 | E50: 0 | F50: =MAX(D50-E50,0) | G50: =E50*GeneratorRate | H50: =F50*GovernmentRate | I50: =G50+H50 | J50: =IFERROR(I50/COUNTIFS('Client DB & Bed Mgmt'!$A:$A,A50,'Client DB & Bed Mgmt'!$B:$B,C50,'Client DB & Bed Mgmt'!$D:$D,"<>"),0) | K50: Dorm 1 | L50: Room 1-3 | M50: =COUNTIFS('Client DB & Bed Mgmt'!$A:$A,$K50,'Client DB & Bed Mgmt'!$B:$B,$L50,'Client DB & Bed Mgmt'!$D:$D,"<>") | P50: =IF(N50="","",MAX(N50-O50,0)) | Q50: =IF(O50="","",O50*GeneratorRate) | R50: =IF(P50="","",P50*GovernmentRate) | S50: =IF(N50="","",Q50+R50) | T50: =IF(M50=0,0,S50/M50)
A51: Dorm 1 | B51: 46235 | C51: Room 1-4 | D51: 0 | E51: 0 | F51: =MAX(D51-E51,0) | G51: =E51*GeneratorRate | H51: =F51*GovernmentRate | I51: =G51+H51 | J51: =IFERROR(I51/COUNTIFS('Client DB & Bed Mgmt'!$A:$A,A51,'Client DB & Bed Mgmt'!$B:$B,C51,'Client DB & Bed Mgmt'!$D:$D,"<>"),0) | K51: Dorm 1 | L51: Room 1-4 | M51: =COUNTIFS('Client DB & Bed Mgmt'!$A:$A,$K51,'Client DB & Bed Mgmt'!$B:$B,$L51,'Client DB & Bed Mgmt'!$D:$D,"<>") | P51: =IF(N51="","",MAX(N51-O51,0)) | Q51: =IF(O51="","",O51*GeneratorRate) | R51: =IF(P51="","",P51*GovernmentRate) | S51: =IF(N51="","",Q51+R51) | T51: =IF(M51=0,0,S51/M51)
A52: Dorm 1 | B52: 46235 | C52: Room 1-5 | D52: 0 | E52: 0 | F52: =MAX(D52-E52,0) | G52: =E52*GeneratorRate | H52: =F52*GovernmentRate | I52: =G52+H52 | J52: =IFERROR(I52/COUNTIFS('Client DB & Bed Mgmt'!$A:$A,A52,'Client DB & Bed Mgmt'!$B:$B,C52,'Client DB & Bed Mgmt'!$D:$D,"<>"),0) | K52: Dorm 1 | L52: Room 1-5 | M52: =COUNTIFS('Client DB & Bed Mgmt'!$A:$A,$K52,'Client DB & Bed Mgmt'!$B:$B,$L52,'Client DB & Bed Mgmt'!$D:$D,"<>") | P52: =IF(N52="","",MAX(N52-O52,0)) | Q52: =IF(O52="","",O52*GeneratorRate) | R52: =IF(P52="","",P52*GovernmentRate) | S52: =IF(N52="","",Q52+R52) | T52: =IF(M52=0,0,S52/M52)
A53: Dorm 1 | B53: 46235 | C53: Room 1-6 | D53: 0 | E53: 0 | F53: =MAX(D53-E53,0) | G53: =E53*GeneratorRate | H53: =F53*GovernmentRate | I53: =G53+H53 | J53: =IFERROR(I53/COUNTIFS('Client DB & Bed Mgmt'!$A:$A,A53,'Client DB & Bed Mgmt'!$B:$B,C53,'Client DB & Bed Mgmt'!$D:$D,"<>"),0) | K53: Dorm 1 | L53: Room 1-6 | M53: =COUNTIFS('Client DB & Bed Mgmt'!$A:$A,$K53,'Client DB & Bed Mgmt'!$B:$B,$L53,'Client DB & Bed Mgmt'!$D:$D,"<>") | P53: =IF(N53="","",MAX(N53-O53,0)) | Q53: =IF(O53="","",O53*GeneratorRate) | R53: =IF(P53="","",P53*GovernmentRate) | S53: =IF(N53="","",Q53+R53) | T53: =IF(M53=0,0,S53/M53)
... A221: Dorm 3 | B221: 46357 | C221: Room 3-6 | D221: 0 | E221: 0 | F221: =MAX(D221-E221,0) | G221: =E221*GeneratorRate | H221: =F221*GovernmentRate | I221: =G221+H221 | J221: =IFERROR(I221/COUNTIFS('Client DB & Bed Mgmt'!$A:$A,A221,'Client DB & Bed Mgmt'!$B:$B,C221,'Client DB & Bed Mgmt'!$D:$D,"<>"),0) | K221: Dorm 3 | L221: Room 3-6 | M221: =COUNTIFS('Client DB & Bed Mgmt'!$A:$A,$K221,'Client DB & Bed Mgmt'!$B:$B,$L221,'Client DB & Bed Mgmt'!$D:$D,"<>") | P221: =IF(N221="","",MAX(N221-O221,0)) | Q221: =IF(O221="","",O221*GeneratorRate) | R221: =IF(P221="","",P221*GovernmentRate) | S221: =IF(N221="","",Q221+R221) | T221: =IF(M221=0,0,S221/M221)
F222: =IF(D222="","",MAX(D222-E222,0)) | G222: =IF(E222="","",E222*GeneratorRate) | H222: =IF(F222="","",F222*GovernmentRate) | I222: =IF(D222="","",G222+H222) | J222: =IFERROR(I222/COUNTIFS('Client DB & Bed Mgmt'!$A:$A,A222,'Client DB & Bed Mgmt'!$B:$B,C222,'Client DB & Bed Mgmt'!$D:$D,"<>"),0) | M222: =COUNTIFS('Client DB & Bed Mgmt'!$A:$A,$K222,'Client DB & Bed Mgmt'!$B:$B,$L222,'Client DB & Bed Mgmt'!$D:$D,"<>") | P222: =IF(N222="","",MAX(N222-O222,0)) | Q222: =IF(O222="","",O222*GeneratorRate) | R222: =IF(P222="","",P222*GovernmentRate) | S222: =IF(N222="","",Q222+R222) | T222: =IF(M222=0,0,S222/M222)
F223: =IF(D223="","",MAX(D223-E223,0)) | G223: =IF(E223="","",E223*GeneratorRate) | H223: =IF(F223="","",F223*GovernmentRate) | I223: =IF(D223="","",G223+H223) | J223: =IFERROR(I223/COUNTIFS('Client DB & Bed Mgmt'!$A:$A,A223,'Client DB & Bed Mgmt'!$B:$B,C223,'Client DB & Bed Mgmt'!$D:$D,"<>"),0) | M223: =COUNTIFS('Client DB & Bed Mgmt'!$A:$A,$K223,'Client DB & Bed Mgmt'!$B:$B,$L223,'Client DB & Bed Mgmt'!$D:$D,"<>") | P223: =IF(N223="","",MAX(N223-O223,0)) | Q223: =IF(O223="","",O223*GeneratorRate) | R223: =IF(P223="","",P223*GovernmentRate) | S223: =IF(N223="","",Q223+R223) | T223: =IF(M223=0,0,S223/M223)
F224: =IF(D224="","",MAX(D224-E224,0)) | G224: =IF(E224="","",E224*GeneratorRate) | H224: =IF(F224="","",F224*GovernmentRate) | I224: =IF(D224="","",G224+H224) | J224: =IFERROR(I224/COUNTIFS('Client DB & Bed Mgmt'!$A:$A,A224,'Client DB & Bed Mgmt'!$B:$B,C224,'Client DB & Bed Mgmt'!$D:$D,"<>"),0) | M224: =COUNTIFS('Client DB & Bed Mgmt'!$A:$A,$K224,'Client DB & Bed Mgmt'!$B:$B,$L224,'Client DB & Bed Mgmt'!$D:$D,"<>") | P224: =IF(N224="","",MAX(N224-O224,0)) | Q224: =IF(O224="","",O224*GeneratorRate) | R224: =IF(P224="","",P224*GovernmentRate) | S224: =IF(N224="","",Q224+R224) | T224: =IF(M224=0,0,S224/M224)
F225: =IF(D225="","",MAX(D225-E225,0)) | G225: =IF(E225="","",E225*GeneratorRate) | H225: =IF(F225="","",F225*GovernmentRate) | I225: =IF(D225="","",G225+H225) | J225: =IFERROR(I225/COUNTIFS('Client DB & Bed Mgmt'!$A:$A,A225,'Client DB & Bed Mgmt'!$B:$B,C225,'Client DB & Bed Mgmt'!$D:$D,"<>"),0) | M225: =COUNTIFS('Client DB & Bed Mgmt'!$A:$A,$K225,'Client DB & Bed Mgmt'!$B:$B,$L225,'Client DB & Bed Mgmt'!$D:$D,"<>") | P225: =IF(N225="","",MAX(N225-O225,0)) | Q225: =IF(O225="","",O225*GeneratorRate) | R225: =IF(P225="","",P225*GovernmentRate) | S225: =IF(N225="","",Q225+R225) | T225: =IF(M225=0,0,S225/M225)
F226: =IF(D226="","",MAX(D226-E226,0)) | G226: =IF(E226="","",E226*GeneratorRate) | H226: =IF(F226="","",F226*GovernmentRate) | I226: =IF(D226="","",G226+H226) | J226: =IFERROR(I226/COUNTIFS('Client DB & Bed Mgmt'!$A:$A,A226,'Client DB & Bed Mgmt'!$B:$B,C226,'Client DB & Bed Mgmt'!$D:$D,"<>"),0) | M226: =COUNTIFS('Client DB & Bed Mgmt'!$A:$A,$K226,'Client DB & Bed Mgmt'!$B:$B,$L226,'Client DB & Bed Mgmt'!$D:$D,"<>") | P226: =IF(N226="","",MAX(N226-O226,0)) | Q226: =IF(O226="","",O226*GeneratorRate) | R226: =IF(P226="","",P226*GovernmentRate) | S226: =IF(N226="","",Q226+R226) | T226: =IF(M226=0,0,S226/M226)
F227: =IF(D227="","",MAX(D227-E227,0)) | G227: =IF(E227="","",E227*GeneratorRate) | H227: =IF(F227="","",F227*GovernmentRate) | I227: =IF(D227="","",G227+H227) | J227: =IFERROR(I227/COUNTIFS('Client DB & Bed Mgmt'!$A:$A,A227,'Client DB & Bed Mgmt'!$B:$B,C227,'Client DB & Bed Mgmt'!$D:$D,"<>"),0) | M227: =COUNTIFS('Client DB & Bed Mgmt'!$A:$A,$K227,'Client DB & Bed Mgmt'!$B:$B,$L227,'Client DB & Bed Mgmt'!$D:$D,"<>") | P227: =IF(N227="","",MAX(N227-O227,0)) | Q227: =IF(O227="","",O227*GeneratorRate) | R227: =IF(P227="","",P227*GovernmentRate) | S227: =IF(N227="","",Q227+R227) | T227: =IF(M227=0,0,S227/M227)
F228: =IF(D228="","",MAX(D228-E228,0)) | G228: =IF(E228="","",E228*GeneratorRate) | H228: =IF(F228="","",F228*GovernmentRate) | I228: =IF(D228="","",G228+H228) | J228: =IFERROR(I228/COUNTIFS('Client DB & Bed Mgmt'!$A:$A,A228,'Client DB & Bed Mgmt'!$B:$B,C228,'Client DB & Bed Mgmt'!$D:$D,"<>"),0) | M228: =COUNTIFS('Client DB & Bed Mgmt'!$A:$A,$K228,'Client DB & Bed Mgmt'!$B:$B,$L228,'Client DB & Bed Mgmt'!$D:$D,"<>") | P228: =IF(N228="","",MAX(N228-O228,0)) | Q228: =IF(O228="","",O228*GeneratorRate) | R228: =IF(P228="","",P228*GovernmentRate) | S228: =IF(N228="","",Q228+R228) | T228: =IF(M228=0,0,S228/M228)
F229: =IF(D229="","",MAX(D229-E229,0)) | G229: =IF(E229="","",E229*GeneratorRate) | H229: =IF(F229="","",F229*GovernmentRate) | I229: =IF(D229="","",G229+H229) | J229: =IFERROR(I229/COUNTIFS('Client DB & Bed Mgmt'!$A:$A,A229,'Client DB & Bed Mgmt'!$B:$B,C229,'Client DB & Bed Mgmt'!$D:$D,"<>"),0) | M229: =COUNTIFS('Client DB & Bed Mgmt'!$A:$A,$K229,'Client DB & Bed Mgmt'!$B:$B,$L229,'Client DB & Bed Mgmt'!$D:$D,"<>") | P229: =IF(N229="","",MAX(N229-O229,0)) | Q229: =IF(O229="","",O229*GeneratorRate) | R229: =IF(P229="","",P229*GovernmentRate) | S229: =IF(N229="","",Q229+R229) | T229: =IF(M229=0,0,S229/M229)
F230: =IF(D230="","",MAX(D230-E230,0)) | G230: =IF(E230="","",E230*GeneratorRate) | H230: =IF(F230="","",F230*GovernmentRate) | I230: =IF(D230="","",G230+H230) | J230: =IFERROR(I230/COUNTIFS('Client DB & Bed Mgmt'!$A:$A,A230,'Client DB & Bed Mgmt'!$B:$B,C230,'Client DB & Bed Mgmt'!$D:$D,"<>"),0) | M230: =COUNTIFS('Client DB & Bed Mgmt'!$A:$A,$K230,'Client DB & Bed Mgmt'!$B:$B,$L230,'Client DB & Bed Mgmt'!$D:$D,"<>") | P230: =IF(N230="","",MAX(N230-O230,0)) | Q230: =IF(O230="","",O230*GeneratorRate) | R230: =IF(P230="","",P230*GovernmentRate) | S230: =IF(N230="","",Q230+R230) | T230: =IF(M230=0,0,S230/M230)
F231: =IF(D231="","",MAX(D231-E231,0)) | G231: =IF(E231="","",E231*GeneratorRate) | H231: =IF(F231="","",F231*GovernmentRate) | I231: =IF(D231="","",G231+H231) | J231: =IFERROR(I231/COUNTIFS('Client DB & Bed Mgmt'!$A:$A,A231,'Client DB & Bed Mgmt'!$B:$B,C231,'Client DB & Bed Mgmt'!$D:$D,"<>"),0) | M231: =COUNTIFS('Client DB & Bed Mgmt'!$A:$A,$K231,'Client DB & Bed Mgmt'!$B:$B,$L231,'Client DB & Bed Mgmt'!$D:$D,"<>") | P231: =IF(N231="","",MAX(N231-O231,0)) | Q231: =IF(O231="","",O231*GeneratorRate) | R231: =IF(P231="","",P231*GovernmentRate) | S231: =IF(N231="","",Q231+R231) | T231: =IF(M231=0,0,S231/M231)
F232: =IF(D232="","",MAX(D232-E232,0)) | G232: =IF(E232="","",E232*GeneratorRate) | H232: =IF(F232="","",F232*GovernmentRate) | I232: =IF(D232="","",G232+H232) | J232: =IFERROR(I232/COUNTIFS('Client DB & Bed Mgmt'!$A:$A,A232,'Client DB & Bed Mgmt'!$B:$B,C232,'Client DB & Bed Mgmt'!$D:$D,"<>"),0) | M232: =COUNTIFS('Client DB & Bed Mgmt'!$A:$A,$K232,'Client DB & Bed Mgmt'!$B:$B,$L232,'Client DB & Bed Mgmt'!$D:$D,"<>") | P232: =IF(N232="","",MAX(N232-O232,0)) | Q232: =IF(O232="","",O232*GeneratorRate) | R232: =IF(P232="","",P232*GovernmentRate) | S232: =IF(N232="","",Q232+R232) | T232: =IF(M232=0,0,S232/M232)
F233: =IF(D233="","",MAX(D233-E233,0)) | G233: =IF(E233="","",E233*GeneratorRate) | H233: =IF(F233="","",F233*GovernmentRate) | I233: =IF(D233="","",G233+H233) | J233: =IFERROR(I233/COUNTIFS('Client DB & Bed Mgmt'!$A:$A,A233,'Client DB & Bed Mgmt'!$B:$B,C233,'Client DB & Bed Mgmt'!$D:$D,"<>"),0) | M233: =COUNTIFS('Client DB & Bed Mgmt'!$A:$A,$K233,'Client DB & Bed Mgmt'!$B:$B,$L233,'Client DB & Bed Mgmt'!$D:$D,"<>") | P233: =IF(N233="","",MAX(N233-O233,0)) | Q233: =IF(O233="","",O233*GeneratorRate) | R233: =IF(P233="","",P233*GovernmentRate) | S233: =IF(N233="","",Q233+R233) | T233: =IF(M233=0,0,S233/M233)
... F300: =IF(D300="","",MAX(D300-E300,0)) | G300: =IF(E300="","",E300*GeneratorRate) | H300: =IF(F300="","",F300*GovernmentRate) | I300: =IF(D300="","",G300+H300) | J300: =IFERROR(I300/COUNTIFS('Client DB & Bed Mgmt'!$A:$A,A300,'Client DB & Bed Mgmt'!$B:$B,C300,'Client DB & Bed Mgmt'!$D:$D,"<>"),0) | M300: =COUNTIFS('Client DB & Bed Mgmt'!$A:$A,$K300,'Client DB & Bed Mgmt'!$B:$B,$L300,'Client DB & Bed Mgmt'!$D:$D,"<>") | P300: =IF(N300="","",MAX(N300-O300,0)) | Q300: =IF(O300="","",O300*GeneratorRate) | R300: =IF(P300="","",P300*GovernmentRate) | S300: =IF(N300="","",Q300+R300) | T300: =IF(M300=0,0,S300/M300)
F301: =IF(D301="","",MAX(D301-E301,0)) | G301: =IF(E301="","",E301*GeneratorRate) | H301: =IF(F301="","",F301*GovernmentRate) | I301: =IF(D301="","",G301+H301) | J301: =IFERROR(I301/COUNTIFS('Client DB & Bed Mgmt'!$A:$A,A301,'Client DB & Bed Mgmt'!$B:$B,C301,'Client DB & Bed Mgmt'!$D:$D,"<>"),0) | M301: =COUNTIFS('Client DB & Bed Mgmt'!$B:$B,L301,'Client DB & Bed Mgmt'!$E:$E,"Occupied")
F302: =IF(D302="","",MAX(D302-E302,0)) | G302: =IF(E302="","",E302*GeneratorRate) | H302: =IF(F302="","",F302*GovernmentRate) | I302: =IF(D302="","",G302+H302) | J302: =IFERROR(I302/COUNTIFS('Client DB & Bed Mgmt'!$A:$A,A302,'Client DB & Bed Mgmt'!$B:$B,C302,'Client DB & Bed Mgmt'!$D:$D,"<>"),0) | M302: =COUNTIFS('Client DB & Bed Mgmt'!$B:$B,L302,'Client DB & Bed Mgmt'!$E:$E,"Occupied")
F303: =IF(D303="","",MAX(D303-E303,0)) | G303: =IF(E303="","",E303*GeneratorRate) | H303: =IF(F303="","",F303*GovernmentRate) | I303: =IF(D303="","",G303+H303) | J303: =IFERROR(I303/COUNTIFS('Client DB & Bed Mgmt'!$A:$A,A303,'Client DB & Bed Mgmt'!$B:$B,C303,'Client DB & Bed Mgmt'!$D:$D,"<>"),0) | M303: =COUNTIFS('Client DB & Bed Mgmt'!$B:$B,L303,'Client DB & Bed Mgmt'!$E:$E,"Occupied")
F304: =IF(D304="","",MAX(D304-E304,0)) | G304: =IF(E304="","",E304*GeneratorRate) | H304: =IF(F304="","",F304*GovernmentRate) | I304: =IF(D304="","",G304+H304) | J304: =IFERROR(I304/COUNTIFS('Client DB & Bed Mgmt'!$A:$A,A304,'Client DB & Bed Mgmt'!$B:$B,C304,'Client DB & Bed Mgmt'!$D:$D,"<>"),0) | M304: =COUNTIFS('Client DB & Bed Mgmt'!$B:$B,L304,'Client DB & Bed Mgmt'!$E:$E,"Occupied")
F305: =IF(D305="","",MAX(D305-E305,0)) | G305: =IF(E305="","",E305*GeneratorRate) | H305: =IF(F305="","",F305*GovernmentRate) | I305: =IF(D305="","",G305+H305) | J305: =IFERROR(I305/COUNTIFS('Client DB & Bed Mgmt'!$A:$A,A305,'Client DB & Bed Mgmt'!$B:$B,C305,'Client DB & Bed Mgmt'!$D:$D,"<>"),0) | M305: =COUNTIFS('Client DB & Bed Mgmt'!$B:$B,L305,'Client DB & Bed Mgmt'!$E:$E,"Occupied")
F306: =IF(D306="","",MAX(D306-E306,0)) | G306: =IF(E306="","",E306*GeneratorRate) | H306: =IF(F306="","",F306*GovernmentRate) | I306: =IF(D306="","",G306+H306) | J306: =IFERROR(I306/COUNTIFS('Client DB & Bed Mgmt'!$A:$A,A306,'Client DB & Bed Mgmt'!$B:$B,C306,'Client DB & Bed Mgmt'!$D:$D,"<>"),0) | M306: =COUNTIFS('Client DB & Bed Mgmt'!$B:$B,L306,'Client DB & Bed Mgmt'!$E:$E,"Occupied")
F307: =IF(D307="","",MAX(D307-E307,0)) | G307: =IF(E307="","",E307*GeneratorRate) | H307: =IF(F307="","",F307*GovernmentRate) | I307: =IF(D307="","",G307+H307) | J307: =IFERROR(I307/COUNTIFS('Client DB & Bed Mgmt'!$A:$A,A307,'Client DB & Bed Mgmt'!$B:$B,C307,'Client DB & Bed Mgmt'!$D:$D,"<>"),0) | M307: =COUNTIFS('Client DB & Bed Mgmt'!$B:$B,L307,'Client DB & Bed Mgmt'!$E:$E,"Occupied")
F308: =IF(D308="","",MAX(D308-E308,0)) | G308: =IF(E308="","",E308*GeneratorRate) | H308: =IF(F308="","",F308*GovernmentRate) | I308: =IF(D308="","",G308+H308) | J308: =IFERROR(I308/COUNTIFS('Client DB & Bed Mgmt'!$A:$A,A308,'Client DB & Bed Mgmt'!$B:$B,C308,'Client DB & Bed Mgmt'!$D:$D,"<>"),0) | M308: =COUNTIFS('Client DB & Bed Mgmt'!$B:$B,L308,'Client DB & Bed Mgmt'!$E:$E,"Occupied")
F309: =IF(D309="","",MAX(D309-E309,0)) | G309: =IF(E309="","",E309*GeneratorRate) | H309: =IF(F309="","",F309*GovernmentRate) | I309: =IF(D309="","",G309+H309) | J309: =IFERROR(I309/COUNTIFS('Client DB & Bed Mgmt'!$A:$A,A309,'Client DB & Bed Mgmt'!$B:$B,C309,'Client DB & Bed Mgmt'!$D:$D,"<>"),0) | M309: =COUNTIFS('Client DB & Bed Mgmt'!$B:$B,L309,'Client DB & Bed Mgmt'!$E:$E,"Occupied")
F310: =IF(D310="","",MAX(D310-E310,0)) | G310: =IF(E310="","",E310*GeneratorRate) | H310: =IF(F310="","",F310*GovernmentRate) | I310: =IF(D310="","",G310+H310) | J310: =IFERROR(I310/COUNTIFS('Client DB & Bed Mgmt'!$A:$A,A310,'Client DB & Bed Mgmt'!$B:$B,C310,'Client DB & Bed Mgmt'!$D:$D,"<>"),0) | M310: =COUNTIFS('Client DB & Bed Mgmt'!$B:$B,L310,'Client DB & Bed Mgmt'!$E:$E,"Occupied")
F311: =IF(D311="","",MAX(D311-E311,0)) | G311: =IF(E311="","",E311*GeneratorRate) | H311: =IF(F311="","",F311*GovernmentRate) | I311: =IF(D311="","",G311+H311) | J311: =IFERROR(I311/COUNTIFS('Client DB & Bed Mgmt'!$A:$A,A311,'Client DB & Bed Mgmt'!$B:$B,C311,'Client DB & Bed Mgmt'!$D:$D,"<>"),0) | M311: =COUNTIFS('Client DB & Bed Mgmt'!$B:$B,L311,'Client DB & Bed Mgmt'!$E:$E,"Occupied")
F312: =IF(D312="","",MAX(D312-E312,0)) | G312: =IF(E312="","",E312*GeneratorRate) | H312: =IF(F312="","",F312*GovernmentRate) | I312: =IF(D312="","",G312+H312) | J312: =IFERROR(I312/COUNTIFS('Client DB & Bed Mgmt'!$A:$A,A312,'Client DB & Bed Mgmt'!$B:$B,C312,'Client DB & Bed Mgmt'!$D:$D,"<>"),0) | M312: =COUNTIFS('Client DB & Bed Mgmt'!$B:$B,L312,'Client DB & Bed Mgmt'!$E:$E,"Occupied")
... F799: =IF(D799="","",MAX(D799-E799,0)) | G799: =IF(E799="","",E799*GeneratorRate) | H799: =IF(F799="","",F799*GovernmentRate) | I799: =IF(D799="","",G799+H799) | J799: =IFERROR(I799/COUNTIFS('Client DB & Bed Mgmt'!$A:$A,A799,'Client DB & Bed Mgmt'!$B:$B,C799,'Client DB & Bed Mgmt'!$D:$D,"<>"),0) | M799: =COUNTIFS('Client DB & Bed Mgmt'!$B:$B,L799,'Client DB & Bed Mgmt'!$E:$E,"Occupied")
F800: =IF(D800="","",MAX(D800-E800,0)) | G800: =IF(E800="","",E800*GeneratorRate) | H800: =IF(F800="","",F800*GovernmentRate) | I800: =IF(D800="","",G800+H800) | J800: =IFERROR(I800/COUNTIFS('Client DB & Bed Mgmt'!$A:$A,A800,'Client DB & Bed Mgmt'!$B:$B,C800,'Client DB & Bed Mgmt'!$D:$D,"<>"),0)

Sheet Invoice Generator
B2: DooRm Invoice
B3: Professional student housing / dormitory billing statement
B5: Lookup By | C5: Client Name | F5: Payment Status | G5: =IFERROR(_xlfn.XLOOKUP($C$6,'Client DB & Bed Mgmt'!$D:$D,'Client DB & Bed Mgmt'!$L:$L,""),"")
B6: Client / Bed Selection | C6: ikr | F6: Due Date | G6: =EOMONTH(C7,0)
B7: Billing Month | C7: =IFERROR(DATE(YEAR($G$12),MONTH($G$12),1),CurrentMonth) | F7: Invoice #
B10: Client Name | C10: =C6 | F10: Phone | G10: =IFERROR(_xlfn.XLOOKUP($C$6,'Client DB & Bed Mgmt'!$D:$D,'Client DB & Bed Mgmt'!$Q:$Q,""),"")
B11: Dorm | C11: =IFERROR(_xlfn.XLOOKUP($C$6,'Client DB & Bed Mgmt'!$D:$D,'Client DB & Bed Mgmt'!$A:$A,""),"") | F11: Contract End | G11: =IFERROR(_xlfn.XLOOKUP($C$6,'Client DB & Bed Mgmt'!$D:$D,'Client DB & Bed Mgmt'!$S:$S,""),"")
B12: Room | C12: =IFERROR(_xlfn.XLOOKUP($C$6,'Client DB & Bed Mgmt'!$D:$D,'Client DB & Bed Mgmt'!$B:$B,""),"") | F12: Move-in Date | G12: =IFERROR(_xlfn.XLOOKUP($C$6,'Client DB & Bed Mgmt'!$D:$D,'Client DB & Bed Mgmt'!$M:$M,""),"")
B13: Bed | C13: =IFERROR(_xlfn.XLOOKUP($C$6,'Client DB & Bed Mgmt'!$D:$D,'Client DB & Bed Mgmt'!$C:$C,""),"") | F13: Move-out Date | G13: =IFERROR(_xlfn.XLOOKUP($C$6,'Client DB & Bed Mgmt'!$D:$D,'Client DB & Bed Mgmt'!$N:$N,""),"")
B14: Billing Month | C14: =$C$7
B17: Charges | H17: Prorata
B18: Base Rent / Loyer Par Personne | G18: =IFERROR(_xlfn.XLOOKUP($C$6,'Client DB & Bed Mgmt'!$D:$D,'Client DB & Bed Mgmt'!$I:$I,0),0) | H18: =G18*$H$24
B19: Electricity Per Person | G19: =IFERROR(_xlfn.XLOOKUP($C$6,'Client DB & Bed Mgmt'!$D:$D,'Client DB & Bed Mgmt'!$J:$J,0),0) | H19: ='Electricity Management'!$AA$6
B20: Common Area Electricity | G20: =IFERROR(_xlfn.XLOOKUP($C$6,'Client DB & Bed Mgmt'!$D:$D,'Client DB & Bed Mgmt'!$K:$K,0),0) | H20: ='Electricity Management'!$AB$6
B21: Fixed Generator Fee | G21: =FixedGeneratorFee | H21: =G21*$H$24
B22: Fixed Government Fee | G22: =FixedGovernmentFee | H22: =G22*$H$24
B24: Calculs visibles: Client DB colonne S = Loyer Par Personne; Electricity colonne J = Electricity Per Personne. | H24: ='Electricity Management'!$Z$6
B25: Total Amount Due | G25: =SUM(G18:G22) | H25: =SUM(H18:H22)
B28: Notes
B29: Payment instructions / client notes

Sheet 12-Month Financial Model
A1: 12-Month Financial Model & Cash Flow
A2: Rolling forecast for revenue, operating expenses, rent, and profitability.
A4: Start Date | B4: 46082
A5: Bed Capacity | B5: =SUM(DormRegistry[Bed Capacity])
A6: Rent Per Bed | B6: =DefaultRentPerBed
A7: Target Occupancy % | B7: =TargetOccupancy
A8: Inflation % | B8: =InflationRate
A9: Generator Rate per kWh | B9: =GeneratorRate
A10: Government Rate per kWh | B10: =GovernmentRate
A13: Month | B13: Dorm Name | C13: Ownership Type | D13: Bed Capacity | E13: Rent Per Bed | F13: Target Occupancy % | G13: Inflation % | H13: Maximum Gross Revenue | I13: Actual Revenue | J13: Target Revenue | K13: Municipality Fees | L13: Building Subscription Fees | M13: Cleaning | N13: Maintenance | O13: Internet | P13: Supplies | Q13: Marketing | R13: Building Rent | S13: Operating Expenses | T13: Net Profit | U13: Net Margin
A14: =EDATE(StartDate,0) | B14: Dorm 1 | C14: =IFERROR(_xlfn.XLOOKUP(B14,DormRegistry[Dorm Name],DormRegistry[Ownership Type]),"") | D14: =IFERROR(_xlfn.XLOOKUP(B14,DormRegistry[Dorm Name],DormRegistry[Bed Capacity]),0) | E14: =$B$6*(1+$B$8)^(YEAR(A14)-YEAR(StartDate)) | F14: =$B$7 | G14: =$B$8 | H14: =D14*E14 | J14: =D14*F14*E14 | K14: 75 | L14: 50 | M14: 150 | N14: 125 | O14: 60 | P14: 80 | Q14: 40 | R14: =IF(C14="Owned",0,2500) | S14: =SUM(K14:R14) | T14: =I14-S14 | U14: =IFERROR(T14/I14,0)
A15: =EDATE(StartDate,0) | B15: Dorm 2 | C15: =IFERROR(_xlfn.XLOOKUP(B15,DormRegistry[Dorm Name],DormRegistry[Ownership Type]),"") | D15: =IFERROR(_xlfn.XLOOKUP(B15,DormRegistry[Dorm Name],DormRegistry[Bed Capacity]),0) | E15: =$B$6*(1+$B$8)^(YEAR(A15)-YEAR(StartDate)) | F15: =$B$7 | G15: =$B$8 | H15: =D15*E15 | J15: =D15*F15*E15 | K15: 75 | L15: 50 | M15: 150 | N15: 125 | O15: 60 | P15: 80 | Q15: 40 | R15: =IF(C15="Owned",0,2500) | S15: =SUM(K15:R15) | T15: =I15-S15 | U15: =IFERROR(T15/I15,0)
A16: =EDATE(StartDate,0) | B16: Dorm 3 | C16: =IFERROR(_xlfn.XLOOKUP(B16,DormRegistry[Dorm Name],DormRegistry[Ownership Type]),"") | D16: =IFERROR(_xlfn.XLOOKUP(B16,DormRegistry[Dorm Name],DormRegistry[Bed Capacity]),0) | E16: =$B$6*(1+$B$8)^(YEAR(A16)-YEAR(StartDate)) | F16: =$B$7 | G16: =$B$8 | H16: =D16*E16 | J16: =D16*F16*E16 | K16: 75 | L16: 50 | M16: 150 | N16: 125 | O16: 60 | P16: 80 | Q16: 40 | R16: =IF(C16="Owned",0,2500) | S16: =SUM(K16:R16) | T16: =I16-S16 | U16: =IFERROR(T16/I16,0)
A17: =EDATE(StartDate,1) | B17: Dorm 1 | C17: =IFERROR(_xlfn.XLOOKUP(B17,DormRegistry[Dorm Name],DormRegistry[Ownership Type]),"") | D17: =IFERROR(_xlfn.XLOOKUP(B17,DormRegistry[Dorm Name],DormRegistry[Bed Capacity]),0) | E17: =$B$6*(1+$B$8)^(YEAR(A17)-YEAR(StartDate)) | F17: =$B$7 | G17: =$B$8 | H17: =D17*E17 | J17: =D17*F17*E17 | K17: 75 | L17: 50 | M17: 150 | N17: 125 | O17: 60 | P17: 80 | Q17: 40 | R17: =IF(C17="Owned",0,2500) | S17: =SUM(K17:R17) | T17: =I17-S17 | U17: =IFERROR(T17/I17,0)
A18: =EDATE(StartDate,1) | B18: Dorm 2 | C18: =IFERROR(_xlfn.XLOOKUP(B18,DormRegistry[Dorm Name],DormRegistry[Ownership Type]),"") | D18: =IFERROR(_xlfn.XLOOKUP(B18,DormRegistry[Dorm Name],DormRegistry[Bed Capacity]),0) | E18: =$B$6*(1+$B$8)^(YEAR(A18)-YEAR(StartDate)) | F18: =$B$7 | G18: =$B$8 | H18: =D18*E18 | J18: =D18*F18*E18 | K18: 75 | L18: 50 | M18: 150 | N18: 125 | O18: 60 | P18: 80 | Q18: 40 | R18: =IF(C18="Owned",0,2500) | S18: =SUM(K18:R18) | T18: =I18-S18 | U18: =IFERROR(T18/I18,0)
A19: =EDATE(StartDate,1) | B19: Dorm 3 | C19: =IFERROR(_xlfn.XLOOKUP(B19,DormRegistry[Dorm Name],DormRegistry[Ownership Type]),"") | D19: =IFERROR(_xlfn.XLOOKUP(B19,DormRegistry[Dorm Name],DormRegistry[Bed Capacity]),0) | E19: =$B$6*(1+$B$8)^(YEAR(A19)-YEAR(StartDate)) | F19: =$B$7 | G19: =$B$8 | H19: =D19*E19 | J19: =D19*F19*E19 | K19: 75 | L19: 50 | M19: 150 | N19: 125 | O19: 60 | P19: 80 | Q19: 40 | R19: =IF(C19="Owned",0,2500) | S19: =SUM(K19:R19) | T19: =I19-S19 | U19: =IFERROR(T19/I19,0)
A20: =EDATE(StartDate,2) | B20: Dorm 1 | C20: =IFERROR(_xlfn.XLOOKUP(B20,DormRegistry[Dorm Name],DormRegistry[Ownership Type]),"") | D20: =IFERROR(_xlfn.XLOOKUP(B20,DormRegistry[Dorm Name],DormRegistry[Bed Capacity]),0) | E20: =$B$6*(1+$B$8)^(YEAR(A20)-YEAR(StartDate)) | F20: =$B$7 | G20: =$B$8 | H20: =D20*E20 | J20: =D20*F20*E20 | K20: 75 | L20: 50 | M20: 150 | N20: 125 | O20: 60 | P20: 80 | Q20: 40 | R20: =IF(C20="Owned",0,2500) | S20: =SUM(K20:R20) | T20: =I20-S20 | U20: =IFERROR(T20/I20,0)
A21: =EDATE(StartDate,2) | B21: Dorm 2 | C21: =IFERROR(_xlfn.XLOOKUP(B21,DormRegistry[Dorm Name],DormRegistry[Ownership Type]),"") | D21: =IFERROR(_xlfn.XLOOKUP(B21,DormRegistry[Dorm Name],DormRegistry[Bed Capacity]),0) | E21: =$B$6*(1+$B$8)^(YEAR(A21)-YEAR(StartDate)) | F21: =$B$7 | G21: =$B$8 | H21: =D21*E21 | J21: =D21*F21*E21 | K21: 75 | L21: 50 | M21: 150 | N21: 125 | O21: 60 | P21: 80 | Q21: 40 | R21: =IF(C21="Owned",0,2500) | S21: =SUM(K21:R21) | T21: =I21-S21 | U21: =IFERROR(T21/I21,0)
A22: =EDATE(StartDate,2) | B22: Dorm 3 | C22: =IFERROR(_xlfn.XLOOKUP(B22,DormRegistry[Dorm Name],DormRegistry[Ownership Type]),"") | D22: =IFERROR(_xlfn.XLOOKUP(B22,DormRegistry[Dorm Name],DormRegistry[Bed Capacity]),0) | E22: =$B$6*(1+$B$8)^(YEAR(A22)-YEAR(StartDate)) | F22: =$B$7 | G22: =$B$8 | H22: =D22*E22 | J22: =D22*F22*E22 | K22: 75 | L22: 50 | M22: 150 | N22: 125 | O22: 60 | P22: 80 | Q22: 40 | R22: =IF(C22="Owned",0,2500) | S22: =SUM(K22:R22) | T22: =I22-S22 | U22: =IFERROR(T22/I22,0)
A23: =EDATE(StartDate,3) | B23: Dorm 1 | C23: =IFERROR(_xlfn.XLOOKUP(B23,DormRegistry[Dorm Name],DormRegistry[Ownership Type]),"") | D23: =IFERROR(_xlfn.XLOOKUP(B23,DormRegistry[Dorm Name],DormRegistry[Bed Capacity]),0) | E23: =$B$6*(1+$B$8)^(YEAR(A23)-YEAR(StartDate)) | F23: =$B$7 | G23: =$B$8 | H23: =D23*E23 | J23: =D23*F23*E23 | K23: 75 | L23: 50 | M23: 150 | N23: 125 | O23: 60 | P23: 80 | Q23: 40 | R23: =IF(C23="Owned",0,2500) | S23: =SUM(K23:R23) | T23: =I23-S23 | U23: =IFERROR(T23/I23,0)
A24: =EDATE(StartDate,3) | B24: Dorm 2 | C24: =IFERROR(_xlfn.XLOOKUP(B24,DormRegistry[Dorm Name],DormRegistry[Ownership Type]),"") | D24: =IFERROR(_xlfn.XLOOKUP(B24,DormRegistry[Dorm Name],DormRegistry[Bed Capacity]),0) | E24: =$B$6*(1+$B$8)^(YEAR(A24)-YEAR(StartDate)) | F24: =$B$7 | G24: =$B$8 | H24: =D24*E24 | J24: =D24*F24*E24 | K24: 75 | L24: 50 | M24: 150 | N24: 125 | O24: 60 | P24: 80 | Q24: 40 | R24: =IF(C24="Owned",0,2500) | S24: =SUM(K24:R24) | T24: =I24-S24 | U24: =IFERROR(T24/I24,0)
A25: =EDATE(StartDate,3) | B25: Dorm 3 | C25: =IFERROR(_xlfn.XLOOKUP(B25,DormRegistry[Dorm Name],DormRegistry[Ownership Type]),"") | D25: =IFERROR(_xlfn.XLOOKUP(B25,DormRegistry[Dorm Name],DormRegistry[Bed Capacity]),0) | E25: =$B$6*(1+$B$8)^(YEAR(A25)-YEAR(StartDate)) | F25: =$B$7 | G25: =$B$8 | H25: =D25*E25 | J25: =D25*F25*E25 | K25: 75 | L25: 50 | M25: 150 | N25: 125 | O25: 60 | P25: 80 | Q25: 40 | R25: =IF(C25="Owned",0,2500) | S25: =SUM(K25:R25) | T25: =I25-S25 | U25: =IFERROR(T25/I25,0)
A26: =EDATE(StartDate,4) | B26: Dorm 1 | C26: =IFERROR(_xlfn.XLOOKUP(B26,DormRegistry[Dorm Name],DormRegistry[Ownership Type]),"") | D26: =IFERROR(_xlfn.XLOOKUP(B26,DormRegistry[Dorm Name],DormRegistry[Bed Capacity]),0) | E26: =$B$6*(1+$B$8)^(YEAR(A26)-YEAR(StartDate)) | F26: =$B$7 | G26: =$B$8 | H26: =D26*E26 | J26: =D26*F26*E26 | K26: 75 | L26: 50 | M26: 150 | N26: 125 | O26: 60 | P26: 80 | Q26: 40 | R26: =IF(C26="Owned",0,2500) | S26: =SUM(K26:R26) | T26: =I26-S26 | U26: =IFERROR(T26/I26,0)
A27: =EDATE(StartDate,4) | B27: Dorm 2 | C27: =IFERROR(_xlfn.XLOOKUP(B27,DormRegistry[Dorm Name],DormRegistry[Ownership Type]),"") | D27: =IFERROR(_xlfn.XLOOKUP(B27,DormRegistry[Dorm Name],DormRegistry[Bed Capacity]),0) | E27: =$B$6*(1+$B$8)^(YEAR(A27)-YEAR(StartDate)) | F27: =$B$7 | G27: =$B$8 | H27: =D27*E27 | J27: =D27*F27*E27 | K27: 75 | L27: 50 | M27: 150 | N27: 125 | O27: 60 | P27: 80 | Q27: 40 | R27: =IF(C27="Owned",0,2500) | S27: =SUM(K27:R27) | T27: =I27-S27 | U27: =IFERROR(T27/I27,0)
A28: =EDATE(StartDate,4) | B28: Dorm 3 | C28: =IFERROR(_xlfn.XLOOKUP(B28,DormRegistry[Dorm Name],DormRegistry[Ownership Type]),"") | D28: =IFERROR(_xlfn.XLOOKUP(B28,DormRegistry[Dorm Name],DormRegistry[Bed Capacity]),0) | E28: =$B$6*(1+$B$8)^(YEAR(A28)-YEAR(StartDate)) | F28: =$B$7 | G28: =$B$8 | H28: =D28*E28 | J28: =D28*F28*E28 | K28: 75 | L28: 50 | M28: 150 | N28: 125 | O28: 60 | P28: 80 | Q28: 40 | R28: =IF(C28="Owned",0,2500) | S28: =SUM(K28:R28) | T28: =I28-S28 | U28: =IFERROR(T28/I28,0)
A29: =EDATE(StartDate,5) | B29: Dorm 1 | C29: =IFERROR(_xlfn.XLOOKUP(B29,DormRegistry[Dorm Name],DormRegistry[Ownership Type]),"") | D29: =IFERROR(_xlfn.XLOOKUP(B29,DormRegistry[Dorm Name],DormRegistry[Bed Capacity]),0) | E29: =$B$6*(1+$B$8)^(YEAR(A29)-YEAR(StartDate)) | F29: =$B$7 | G29: =$B$8 | H29: =D29*E29 | J29: =D29*F29*E29 | K29: 75 | L29: 50 | M29: 150 | N29: 125 | O29: 60 | P29: 80 | Q29: 40 | R29: =IF(C29="Owned",0,2500) | S29: =SUM(K29:R29) | T29: =I29-S29 | U29: =IFERROR(T29/I29,0)
A30: =EDATE(StartDate,5) | B30: Dorm 2 | C30: =IFERROR(_xlfn.XLOOKUP(B30,DormRegistry[Dorm Name],DormRegistry[Ownership Type]),"") | D30: =IFERROR(_xlfn.XLOOKUP(B30,DormRegistry[Dorm Name],DormRegistry[Bed Capacity]),0) | E30: =$B$6*(1+$B$8)^(YEAR(A30)-YEAR(StartDate)) | F30: =$B$7 | G30: =$B$8 | H30: =D30*E30 | J30: =D30*F30*E30 | K30: 75 | L30: 50 | M30: 150 | N30: 125 | O30: 60 | P30: 80 | Q30: 40 | R30: =IF(C30="Owned",0,2500) | S30: =SUM(K30:R30) | T30: =I30-S30 | U30: =IFERROR(T30/I30,0)
A31: =EDATE(StartDate,5) | B31: Dorm 3 | C31: =IFERROR(_xlfn.XLOOKUP(B31,DormRegistry[Dorm Name],DormRegistry[Ownership Type]),"") | D31: =IFERROR(_xlfn.XLOOKUP(B31,DormRegistry[Dorm Name],DormRegistry[Bed Capacity]),0) | E31: =$B$6*(1+$B$8)^(YEAR(A31)-YEAR(StartDate)) | F31: =$B$7 | G31: =$B$8 | H31: =D31*E31 | J31: =D31*F31*E31 | K31: 75 | L31: 50 | M31: 150 | N31: 125 | O31: 60 | P31: 80 | Q31: 40 | R31: =IF(C31="Owned",0,2500) | S31: =SUM(K31:R31) | T31: =I31-S31 | U31: =IFERROR(T31/I31,0)
A32: =EDATE(StartDate,6) | B32: Dorm 1 | C32: =IFERROR(_xlfn.XLOOKUP(B32,DormRegistry[Dorm Name],DormRegistry[Ownership Type]),"") | D32: =IFERROR(_xlfn.XLOOKUP(B32,DormRegistry[Dorm Name],DormRegistry[Bed Capacity]),0) | E32: =$B$6*(1+$B$8)^(YEAR(A32)-YEAR(StartDate)) | F32: =$B$7 | G32: =$B$8 | H32: =D32*E32 | J32: =D32*F32*E32 | K32: 75 | L32: 50 | M32: 150 | N32: 125 | O32: 60 | P32: 80 | Q32: 40 | R32: =IF(C32="Owned",0,2500) | S32: =SUM(K32:R32) | T32: =I32-S32 | U32: =IFERROR(T32/I32,0)
A33: =EDATE(StartDate,6) | B33: Dorm 2 | C33: =IFERROR(_xlfn.XLOOKUP(B33,DormRegistry[Dorm Name],DormRegistry[Ownership Type]),"") | D33: =IFERROR(_xlfn.XLOOKUP(B33,DormRegistry[Dorm Name],DormRegistry[Bed Capacity]),0) | E33: =$B$6*(1+$B$8)^(YEAR(A33)-YEAR(StartDate)) | F33: =$B$7 | G33: =$B$8 | H33: =D33*E33 | J33: =D33*F33*E33 | K33: 75 | L33: 50 | M33: 150 | N33: 125 | O33: 60 | P33: 80 | Q33: 40 | R33: =IF(C33="Owned",0,2500) | S33: =SUM(K33:R33) | T33: =I33-S33 | U33: =IFERROR(T33/I33,0)
A34: =EDATE(StartDate,6) | B34: Dorm 3 | C34: =IFERROR(_xlfn.XLOOKUP(B34,DormRegistry[Dorm Name],DormRegistry[Ownership Type]),"") | D34: =IFERROR(_xlfn.XLOOKUP(B34,DormRegistry[Dorm Name],DormRegistry[Bed Capacity]),0) | E34: =$B$6*(1+$B$8)^(YEAR(A34)-YEAR(StartDate)) | F34: =$B$7 | G34: =$B$8 | H34: =D34*E34 | J34: =D34*F34*E34 | K34: 75 | L34: 50 | M34: 150 | N34: 125 | O34: 60 | P34: 80 | Q34: 40 | R34: =IF(C34="Owned",0,2500) | S34: =SUM(K34:R34) | T34: =I34-S34 | U34: =IFERROR(T34/I34,0)
A35: =EDATE(StartDate,7) | B35: Dorm 1 | C35: =IFERROR(_xlfn.XLOOKUP(B35,DormRegistry[Dorm Name],DormRegistry[Ownership Type]),"") | D35: =IFERROR(_xlfn.XLOOKUP(B35,DormRegistry[Dorm Name],DormRegistry[Bed Capacity]),0) | E35: =$B$6*(1+$B$8)^(YEAR(A35)-YEAR(StartDate)) | F35: =$B$7 | G35: =$B$8 | H35: =D35*E35 | J35: =D35*F35*E35 | K35: 75 | L35: 50 | M35: 150 | N35: 125 | O35: 60 | P35: 80 | Q35: 40 | R35: =IF(C35="Owned",0,2500) | S35: =SUM(K35:R35) | T35: =I35-S35 | U35: =IFERROR(T35/I35,0)
A36: =EDATE(StartDate,7) | B36: Dorm 2 | C36: =IFERROR(_xlfn.XLOOKUP(B36,DormRegistry[Dorm Name],DormRegistry[Ownership Type]),"") | D36: =IFERROR(_xlfn.XLOOKUP(B36,DormRegistry[Dorm Name],DormRegistry[Bed Capacity]),0) | E36: =$B$6*(1+$B$8)^(YEAR(A36)-YEAR(StartDate)) | F36: =$B$7 | G36: =$B$8 | H36: =D36*E36 | J36: =D36*F36*E36 | K36: 75 | L36: 50 | M36: 150 | N36: 125 | O36: 60 | P36: 80 | Q36: 40 | R36: =IF(C36="Owned",0,2500) | S36: =SUM(K36:R36) | T36: =I36-S36 | U36: =IFERROR(T36/I36,0)
A37: =EDATE(StartDate,7) | B37: Dorm 3 | C37: =IFERROR(_xlfn.XLOOKUP(B37,DormRegistry[Dorm Name],DormRegistry[Ownership Type]),"") | D37: =IFERROR(_xlfn.XLOOKUP(B37,DormRegistry[Dorm Name],DormRegistry[Bed Capacity]),0) | E37: =$B$6*(1+$B$8)^(YEAR(A37)-YEAR(StartDate)) | F37: =$B$7 | G37: =$B$8 | H37: =D37*E37 | J37: =D37*F37*E37 | K37: 75 | L37: 50 | M37: 150 | N37: 125 | O37: 60 | P37: 80 | Q37: 40 | R37: =IF(C37="Owned",0,2500) | S37: =SUM(K37:R37) | T37: =I37-S37 | U37: =IFERROR(T37/I37,0)
A38: =EDATE(StartDate,8) | B38: Dorm 1 | C38: =IFERROR(_xlfn.XLOOKUP(B38,DormRegistry[Dorm Name],DormRegistry[Ownership Type]),"") | D38: =IFERROR(_xlfn.XLOOKUP(B38,DormRegistry[Dorm Name],DormRegistry[Bed Capacity]),0) | E38: =$B$6*(1+$B$8)^(YEAR(A38)-YEAR(StartDate)) | F38: =$B$7 | G38: =$B$8 | H38: =D38*E38 | J38: =D38*F38*E38 | K38: 75 | L38: 50 | M38: 150 | N38: 125 | O38: 60 | P38: 80 | Q38: 40 | R38: =IF(C38="Owned",0,2500) | S38: =SUM(K38:R38) | T38: =I38-S38 | U38: =IFERROR(T38/I38,0)
A39: =EDATE(StartDate,8) | B39: Dorm 2 | C39: =IFERROR(_xlfn.XLOOKUP(B39,DormRegistry[Dorm Name],DormRegistry[Ownership Type]),"") | D39: =IFERROR(_xlfn.XLOOKUP(B39,DormRegistry[Dorm Name],DormRegistry[Bed Capacity]),0) | E39: =$B$6*(1+$B$8)^(YEAR(A39)-YEAR(StartDate)) | F39: =$B$7 | G39: =$B$8 | H39: =D39*E39 | J39: =D39*F39*E39 | K39: 75 | L39: 50 | M39: 150 | N39: 125 | O39: 60 | P39: 80 | Q39: 40 | R39: =IF(C39="Owned",0,2500) | S39: =SUM(K39:R39) | T39: =I39-S39 | U39: =IFERROR(T39/I39,0)
A40: =EDATE(StartDate,8) | B40: Dorm 3 | C40: =IFERROR(_xlfn.XLOOKUP(B40,DormRegistry[Dorm Name],DormRegistry[Ownership Type]),"") | D40: =IFERROR(_xlfn.XLOOKUP(B40,DormRegistry[Dorm Name],DormRegistry[Bed Capacity]),0) | E40: =$B$6*(1+$B$8)^(YEAR(A40)-YEAR(StartDate)) | F40: =$B$7 | G40: =$B$8 | H40: =D40*E40 | J40: =D40*F40*E40 | K40: 75 | L40: 50 | M40: 150 | N40: 125 | O40: 60 | P40: 80 | Q40: 40 | R40: =IF(C40="Owned",0,2500) | S40: =SUM(K40:R40) | T40: =I40-S40 | U40: =IFERROR(T40/I40,0)
A41: =EDATE(StartDate,9) | B41: Dorm 1 | C41: =IFERROR(_xlfn.XLOOKUP(B41,DormRegistry[Dorm Name],DormRegistry[Ownership Type]),"") | D41: =IFERROR(_xlfn.XLOOKUP(B41,DormRegistry[Dorm Name],DormRegistry[Bed Capacity]),0) | E41: =$B$6*(1+$B$8)^(YEAR(A41)-YEAR(StartDate)) | F41: =$B$7 | G41: =$B$8 | H41: =D41*E41 | J41: =D41*F41*E41 | K41: 75 | L41: 50 | M41: 150 | N41: 125 | O41: 60 | P41: 80 | Q41: 40 | R41: =IF(C41="Owned",0,2500) | S41: =SUM(K41:R41) | T41: =I41-S41 | U41: =IFERROR(T41/I41,0)
A42: =EDATE(StartDate,9) | B42: Dorm 2 | C42: =IFERROR(_xlfn.XLOOKUP(B42,DormRegistry[Dorm Name],DormRegistry[Ownership Type]),"") | D42: =IFERROR(_xlfn.XLOOKUP(B42,DormRegistry[Dorm Name],DormRegistry[Bed Capacity]),0) | E42: =$B$6*(1+$B$8)^(YEAR(A42)-YEAR(StartDate)) | F42: =$B$7 | G42: =$B$8 | H42: =D42*E42 | J42: =D42*F42*E42 | K42: 75 | L42: 50 | M42: 150 | N42: 125 | O42: 60 | P42: 80 | Q42: 40 | R42: =IF(C42="Owned",0,2500) | S42: =SUM(K42:R42) | T42: =I42-S42 | U42: =IFERROR(T42/I42,0)
A43: =EDATE(StartDate,9) | B43: Dorm 3 | C43: =IFERROR(_xlfn.XLOOKUP(B43,DormRegistry[Dorm Name],DormRegistry[Ownership Type]),"") | D43: =IFERROR(_xlfn.XLOOKUP(B43,DormRegistry[Dorm Name],DormRegistry[Bed Capacity]),0) | E43: =$B$6*(1+$B$8)^(YEAR(A43)-YEAR(StartDate)) | F43: =$B$7 | G43: =$B$8 | H43: =D43*E43 | J43: =D43*F43*E43 | K43: 75 | L43: 50 | M43: 150 | N43: 125 | O43: 60 | P43: 80 | Q43: 40 | R43: =IF(C43="Owned",0,2500) | S43: =SUM(K43:R43) | T43: =I43-S43 | U43: =IFERROR(T43/I43,0)
A44: =EDATE(StartDate,10) | B44: Dorm 1 | C44: =IFERROR(_xlfn.XLOOKUP(B44,DormRegistry[Dorm Name],DormRegistry[Ownership Type]),"") | D44: =IFERROR(_xlfn.XLOOKUP(B44,DormRegistry[Dorm Name],DormRegistry[Bed Capacity]),0) | E44: =$B$6*(1+$B$8)^(YEAR(A44)-YEAR(StartDate)) | F44: =$B$7 | G44: =$B$8 | H44: =D44*E44 | J44: =D44*F44*E44 | K44: 75 | L44: 50 | M44: 150 | N44: 125 | O44: 60 | P44: 80 | Q44: 40 | R44: =IF(C44="Owned",0,2500) | S44: =SUM(K44:R44) | T44: =I44-S44 | U44: =IFERROR(T44/I44,0)
A45: =EDATE(StartDate,10) | B45: Dorm 2 | C45: =IFERROR(_xlfn.XLOOKUP(B45,DormRegistry[Dorm Name],DormRegistry[Ownership Type]),"") | D45: =IFERROR(_xlfn.XLOOKUP(B45,DormRegistry[Dorm Name],DormRegistry[Bed Capacity]),0) | E45: =$B$6*(1+$B$8)^(YEAR(A45)-YEAR(StartDate)) | F45: =$B$7 | G45: =$B$8 | H45: =D45*E45 | J45: =D45*F45*E45 | K45: 75 | L45: 50 | M45: 150 | N45: 125 | O45: 60 | P45: 80 | Q45: 40 | R45: =IF(C45="Owned",0,2500) | S45: =SUM(K45:R45) | T45: =I45-S45 | U45: =IFERROR(T45/I45,0)
A46: =EDATE(StartDate,10) | B46: Dorm 3 | C46: =IFERROR(_xlfn.XLOOKUP(B46,DormRegistry[Dorm Name],DormRegistry[Ownership Type]),"") | D46: =IFERROR(_xlfn.XLOOKUP(B46,DormRegistry[Dorm Name],DormRegistry[Bed Capacity]),0) | E46: =$B$6*(1+$B$8)^(YEAR(A46)-YEAR(StartDate)) | F46: =$B$7 | G46: =$B$8 | H46: =D46*E46 | J46: =D46*F46*E46 | K46: 75 | L46: 50 | M46: 150 | N46: 125 | O46: 60 | P46: 80 | Q46: 40 | R46: =IF(C46="Owned",0,2500) | S46: =SUM(K46:R46) | T46: =I46-S46 | U46: =IFERROR(T46/I46,0)
A47: =EDATE(StartDate,11) | B47: Dorm 1 | C47: =IFERROR(_xlfn.XLOOKUP(B47,DormRegistry[Dorm Name],DormRegistry[Ownership Type]),"") | D47: =IFERROR(_xlfn.XLOOKUP(B47,DormRegistry[Dorm Name],DormRegistry[Bed Capacity]),0) | E47: =$B$6*(1+$B$8)^(YEAR(A47)-YEAR(StartDate)) | F47: =$B$7 | G47: =$B$8 | H47: =D47*E47 | J47: =D47*F47*E47 | K47: 75 | L47: 50 | M47: 150 | N47: 125 | O47: 60 | P47: 80 | Q47: 40 | R47: =IF(C47="Owned",0,2500) | S47: =SUM(K47:R47) | T47: =I47-S47 | U47: =IFERROR(T47/I47,0)
A48: =EDATE(StartDate,11) | B48: Dorm 2 | C48: =IFERROR(_xlfn.XLOOKUP(B48,DormRegistry[Dorm Name],DormRegistry[Ownership Type]),"") | D48: =IFERROR(_xlfn.XLOOKUP(B48,DormRegistry[Dorm Name],DormRegistry[Bed Capacity]),0) | E48: =$B$6*(1+$B$8)^(YEAR(A48)-YEAR(StartDate)) | F48: =$B$7 | G48: =$B$8 | H48: =D48*E48 | J48: =D48*F48*E48 | K48: 75 | L48: 50 | M48: 150 | N48: 125 | O48: 60 | P48: 80 | Q48: 40 | R48: =IF(C48="Owned",0,2500) | S48: =SUM(K48:R48) | T48: =I48-S48 | U48: =IFERROR(T48/I48,0)
A49: =EDATE(StartDate,11) | B49: Dorm 3 | C49: =IFERROR(_xlfn.XLOOKUP(B49,DormRegistry[Dorm Name],DormRegistry[Ownership Type]),"") | D49: =IFERROR(_xlfn.XLOOKUP(B49,DormRegistry[Dorm Name],DormRegistry[Bed Capacity]),0) | E49: =$B$6*(1+$B$8)^(YEAR(A49)-YEAR(StartDate)) | F49: =$B$7 | G49: =$B$8 | H49: =D49*E49 | J49: =D49*F49*E49 | K49: 75 | L49: 50 | M49: 150 | N49: 125 | O49: 60 | P49: 80 | Q49: 40 | R49: =IF(C49="Owned",0,2500) | S49: =SUM(K49:R49) | T49: =I49-S49 | U49: =IFERROR(T49/I49,0)
C50: =IFERROR(_xlfn.XLOOKUP(B50,DormRegistry[Dorm Name],DormRegistry[Ownership Type]),"") | D50: =IFERROR(_xlfn.XLOOKUP(B50,DormRegistry[Dorm Name],DormRegistry[Bed Capacity]),0) | E50: =IF(A50="","",$B$6*(1+$B$8)^(YEAR(A50)-YEAR(StartDate))) | F50: =$B$7 | G50: =$B$8 | H50: =IFERROR(D50*E50,0) | J50: =IFERROR(D50*F50*E50,0) | R50: =IF(C50="Owned",0,IF(B50<>"",2500,0)) | S50: =SUM(K50:R50) | T50: =I50-S50 | U50: =IFERROR(T50/I50,0)
C51: =IFERROR(_xlfn.XLOOKUP(B51,DormRegistry[Dorm Name],DormRegistry[Ownership Type]),"") | D51: =IFERROR(_xlfn.XLOOKUP(B51,DormRegistry[Dorm Name],DormRegistry[Bed Capacity]),0) | E51: =IF(A51="","",$B$6*(1+$B$8)^(YEAR(A51)-YEAR(StartDate))) | F51: =$B$7 | G51: =$B$8 | H51: =IFERROR(D51*E51,0) | J51: =IFERROR(D51*F51*E51,0) | R51: =IF(C51="Owned",0,IF(B51<>"",2500,0)) | S51: =SUM(K51:R51) | T51: =I51-S51 | U51: =IFERROR(T51/I51,0)
C52: =IFERROR(_xlfn.XLOOKUP(B52,DormRegistry[Dorm Name],DormRegistry[Ownership Type]),"") | D52: =IFERROR(_xlfn.XLOOKUP(B52,DormRegistry[Dorm Name],DormRegistry[Bed Capacity]),0) | E52: =IF(A52="","",$B$6*(1+$B$8)^(YEAR(A52)-YEAR(StartDate))) | F52: =$B$7 | G52: =$B$8 | H52: =IFERROR(D52*E52,0) | J52: =IFERROR(D52*F52*E52,0) | R52: =IF(C52="Owned",0,IF(B52<>"",2500,0)) | S52: =SUM(K52:R52) | T52: =I52-S52 | U52: =IFERROR(T52/I52,0)
C53: =IFERROR(_xlfn.XLOOKUP(B53,DormRegistry[Dorm Name],DormRegistry[Ownership Type]),"") | D53: =IFERROR(_xlfn.XLOOKUP(B53,DormRegistry[Dorm Name],DormRegistry[Bed Capacity]),0) | E53: =IF(A53="","",$B$6*(1+$B$8)^(YEAR(A53)-YEAR(StartDate))) | F53: =$B$7 | G53: =$B$8 | H53: =IFERROR(D53*E53,0) | J53: =IFERROR(D53*F53*E53,0) | R53: =IF(C53="Owned",0,IF(B53<>"",2500,0)) | S53: =SUM(K53:R53) | T53: =I53-S53 | U53: =IFERROR(T53/I53,0)
C54: =IFERROR(_xlfn.XLOOKUP(B54,DormRegistry[Dorm Name],DormRegistry[Ownership Type]),"") | D54: =IFERROR(_xlfn.XLOOKUP(B54,DormRegistry[Dorm Name],DormRegistry[Bed Capacity]),0) | E54: =IF(A54="","",$B$6*(1+$B$8)^(YEAR(A54)-YEAR(StartDate))) | F54: =$B$7 | G54: =$B$8 | H54: =IFERROR(D54*E54,0) | J54: =IFERROR(D54*F54*E54,0) | R54: =IF(C54="Owned",0,IF(B54<>"",2500,0)) | S54: =SUM(K54:R54) | T54: =I54-S54 | U54: =IFERROR(T54/I54,0)
C55: =IFERROR(_xlfn.XLOOKUP(B55,DormRegistry[Dorm Name],DormRegistry[Ownership Type]),"") | D55: =IFERROR(_xlfn.XLOOKUP(B55,DormRegistry[Dorm Name],DormRegistry[Bed Capacity]),0) | E55: =IF(A55="","",$B$6*(1+$B$8)^(YEAR(A55)-YEAR(StartDate))) | F55: =$B$7 | G55: =$B$8 | H55: =IFERROR(D55*E55,0) | J55: =IFERROR(D55*F55*E55,0) | R55: =IF(C55="Owned",0,IF(B55<>"",2500,0)) | S55: =SUM(K55:R55) | T55: =I55-S55 | U55: =IFERROR(T55/I55,0)
C56: =IFERROR(_xlfn.XLOOKUP(B56,DormRegistry[Dorm Name],DormRegistry[Ownership Type]),"") | D56: =IFERROR(_xlfn.XLOOKUP(B56,DormRegistry[Dorm Name],DormRegistry[Bed Capacity]),0) | E56: =IF(A56="","",$B$6*(1+$B$8)^(YEAR(A56)-YEAR(StartDate))) | F56: =$B$7 | G56: =$B$8 | H56: =IFERROR(D56*E56,0) | J56: =IFERROR(D56*F56*E56,0) | R56: =IF(C56="Owned",0,IF(B56<>"",2500,0)) | S56: =SUM(K56:R56) | T56: =I56-S56 | U56: =IFERROR(T56/I56,0)
C57: =IFERROR(_xlfn.XLOOKUP(B57,DormRegistry[Dorm Name],DormRegistry[Ownership Type]),"") | D57: =IFERROR(_xlfn.XLOOKUP(B57,DormRegistry[Dorm Name],DormRegistry[Bed Capacity]),0) | E57: =IF(A57="","",$B$6*(1+$B$8)^(YEAR(A57)-YEAR(StartDate))) | F57: =$B$7 | G57: =$B$8 | H57: =IFERROR(D57*E57,0) | J57: =IFERROR(D57*F57*E57,0) | R57: =IF(C57="Owned",0,IF(B57<>"",2500,0)) | S57: =SUM(K57:R57) | T57: =I57-S57 | U57: =IFERROR(T57/I57,0)
C58: =IFERROR(_xlfn.XLOOKUP(B58,DormRegistry[Dorm Name],DormRegistry[Ownership Type]),"") | D58: =IFERROR(_xlfn.XLOOKUP(B58,DormRegistry[Dorm Name],DormRegistry[Bed Capacity]),0) | E58: =IF(A58="","",$B$6*(1+$B$8)^(YEAR(A58)-YEAR(StartDate))) | F58: =$B$7 | G58: =$B$8 | H58: =IFERROR(D58*E58,0) | J58: =IFERROR(D58*F58*E58,0) | R58: =IF(C58="Owned",0,IF(B58<>"",2500,0)) | S58: =SUM(K58:R58) | T58: =I58-S58 | U58: =IFERROR(T58/I58,0)
C59: =IFERROR(_xlfn.XLOOKUP(B59,DormRegistry[Dorm Name],DormRegistry[Ownership Type]),"") | D59: =IFERROR(_xlfn.XLOOKUP(B59,DormRegistry[Dorm Name],DormRegistry[Bed Capacity]),0) | E59: =IF(A59="","",$B$6*(1+$B$8)^(YEAR(A59)-YEAR(StartDate))) | F59: =$B$7 | G59: =$B$8 | H59: =IFERROR(D59*E59,0) | J59: =IFERROR(D59*F59*E59,0) | R59: =IF(C59="Owned",0,IF(B59<>"",2500,0)) | S59: =SUM(K59:R59) | T59: =I59-S59 | U59: =IFERROR(T59/I59,0)
C60: =IFERROR(_xlfn.XLOOKUP(B60,DormRegistry[Dorm Name],DormRegistry[Ownership Type]),"") | D60: =IFERROR(_xlfn.XLOOKUP(B60,DormRegistry[Dorm Name],DormRegistry[Bed Capacity]),0) | E60: =IF(A60="","",$B$6*(1+$B$8)^(YEAR(A60)-YEAR(StartDate))) | F60: =$B$7 | G60: =$B$8 | H60: =IFERROR(D60*E60,0) | J60: =IFERROR(D60*F60*E60,0) | R60: =IF(C60="Owned",0,IF(B60<>"",2500,0)) | S60: =SUM(K60:R60) | T60: =I60-S60 | U60: =IFERROR(T60/I60,0)
C61: =IFERROR(_xlfn.XLOOKUP(B61,DormRegistry[Dorm Name],DormRegistry[Ownership Type]),"") | D61: =IFERROR(_xlfn.XLOOKUP(B61,DormRegistry[Dorm Name],DormRegistry[Bed Capacity]),0) | E61: =IF(A61="","",$B$6*(1+$B$8)^(YEAR(A61)-YEAR(StartDate))) | F61: =$B$7 | G61: =$B$8 | H61: =IFERROR(D61*E61,0) | J61: =IFERROR(D61*F61*E61,0) | R61: =IF(C61="Owned",0,IF(B61<>"",2500,0)) | S61: =SUM(K61:R61) | T61: =I61-S61 | U61: =IFERROR(T61/I61,0)
... C300: =IFERROR(_xlfn.XLOOKUP(B300,DormRegistry[Dorm Name],DormRegistry[Ownership Type]),"") | D300: =IFERROR(_xlfn.XLOOKUP(B300,DormRegistry[Dorm Name],DormRegistry[Bed Capacity]),0) | E300: =IF(A300="","",$B$6*(1+$B$8)^(YEAR(A300)-YEAR(StartDate))) | F300: =$B$7 | G300: =$B$8 | H300: =IFERROR(D300*E300,0) | J300: =IFERROR(D300*F300*E300,0) | R300: =IF(C300="Owned",0,IF(B300<>"",2500,0)) | S300: =SUM(K300:R300) | T300: =I300-S300 | U300: =IFERROR(T300/I300,0)

Sheet 12-Month Financial Model (2)
A1: 12-Month Financial Model & Cash Flow
A2: Rolling forecast for revenue, operating expenses, rent, and profitability.
A4: Start Date | B4: 46082
A5: Bed Capacity | B5: =SUM(DormRegistry[Bed Capacity])
A6: Rent Per Bed | B6: =DefaultRentPerBed
A7: Target Occupancy % | B7: =TargetOccupancy
A8: Inflation % | B8: =InflationRate
A9: Generator Rate per kWh | B9: =GeneratorRate
A10: Government Rate per kWh | B10: =GovernmentRate
A13: Month | B13: Dorm Name | C13: Ownership Type | D13: Bed Capacity | E13: Rent Per Bed | F13: Target Occupancy % | G13: Inflation % | H13: Maximum Gross Revenue | I13: Actual Revenue | J13: Target Revenue | K13: Municipality Fees | L13: Building Subscription Fees | M13: Cleaning | N13: Maintenance | O13: Internet | P13: Supplies | Q13: Marketing | R13: Building Rent | S13: Operating Expenses | T13: Net Profit | U13: Net Margin
A14: =EDATE(StartDate,0) | B14: Dorm 1 | C14: =IFERROR(_xlfn.XLOOKUP(B14,DormRegistry[Dorm Name],DormRegistry[Ownership Type]),"") | D14: =IFERROR(_xlfn.XLOOKUP(B14,DormRegistry[Dorm Name],DormRegistry[Bed Capacity]),0) | E14: =$B$6*(1+$B$8)^(YEAR(A14)-YEAR(StartDate)) | F14: =$B$7 | G14: =$B$8 | H14: =D14*E14 | J14: =D14*F14*E14 | K14: 75 | L14: 50 | M14: 150 | N14: 125 | O14: 60 | P14: 80 | Q14: 40 | R14: =IF(C14="Owned",0,2500) | S14: =SUM(K14:R14) | T14: =I14-S14 | U14: =IFERROR(T14/I14,0)
A15: =EDATE(StartDate,0) | B15: Dorm 2 | C15: =IFERROR(_xlfn.XLOOKUP(B15,DormRegistry[Dorm Name],DormRegistry[Ownership Type]),"") | D15: =IFERROR(_xlfn.XLOOKUP(B15,DormRegistry[Dorm Name],DormRegistry[Bed Capacity]),0) | E15: =$B$6*(1+$B$8)^(YEAR(A15)-YEAR(StartDate)) | F15: =$B$7 | G15: =$B$8 | H15: =D15*E15 | J15: =D15*F15*E15 | K15: 75 | L15: 50 | M15: 150 | N15: 125 | O15: 60 | P15: 80 | Q15: 40 | R15: =IF(C15="Owned",0,2500) | S15: =SUM(K15:R15) | T15: =I15-S15 | U15: =IFERROR(T15/I15,0)
A16: =EDATE(StartDate,0) | B16: Dorm 3 | C16: =IFERROR(_xlfn.XLOOKUP(B16,DormRegistry[Dorm Name],DormRegistry[Ownership Type]),"") | D16: =IFERROR(_xlfn.XLOOKUP(B16,DormRegistry[Dorm Name],DormRegistry[Bed Capacity]),0) | E16: =$B$6*(1+$B$8)^(YEAR(A16)-YEAR(StartDate)) | F16: =$B$7 | G16: =$B$8 | H16: =D16*E16 | J16: =D16*F16*E16 | K16: 75 | L16: 50 | M16: 150 | N16: 125 | O16: 60 | P16: 80 | Q16: 40 | R16: =IF(C16="Owned",0,2500) | S16: =SUM(K16:R16) | T16: =I16-S16 | U16: =IFERROR(T16/I16,0)
A17: =EDATE(StartDate,1) | B17: Dorm 1 | C17: =IFERROR(_xlfn.XLOOKUP(B17,DormRegistry[Dorm Name],DormRegistry[Ownership Type]),"") | D17: =IFERROR(_xlfn.XLOOKUP(B17,DormRegistry[Dorm Name],DormRegistry[Bed Capacity]),0) | E17: =$B$6*(1+$B$8)^(YEAR(A17)-YEAR(StartDate)) | F17: =$B$7 | G17: =$B$8 | H17: =D17*E17 | J17: =D17*F17*E17 | K17: 75 | L17: 50 | M17: 150 | N17: 125 | O17: 60 | P17: 80 | Q17: 40 | R17: =IF(C17="Owned",0,2500) | S17: =SUM(K17:R17) | T17: =I17-S17 | U17: =IFERROR(T17/I17,0)
A18: =EDATE(StartDate,1) | B18: Dorm 2 | C18: =IFERROR(_xlfn.XLOOKUP(B18,DormRegistry[Dorm Name],DormRegistry[Ownership Type]),"") | D18: =IFERROR(_xlfn.XLOOKUP(B18,DormRegistry[Dorm Name],DormRegistry[Bed Capacity]),0) | E18: =$B$6*(1+$B$8)^(YEAR(A18)-YEAR(StartDate)) | F18: =$B$7 | G18: =$B$8 | H18: =D18*E18 | J18: =D18*F18*E18 | K18: 75 | L18: 50 | M18: 150 | N18: 125 | O18: 60 | P18: 80 | Q18: 40 | R18: =IF(C18="Owned",0,2500) | S18: =SUM(K18:R18) | T18: =I18-S18 | U18: =IFERROR(T18/I18,0)
A19: =EDATE(StartDate,1) | B19: Dorm 3 | C19: =IFERROR(_xlfn.XLOOKUP(B19,DormRegistry[Dorm Name],DormRegistry[Ownership Type]),"") | D19: =IFERROR(_xlfn.XLOOKUP(B19,DormRegistry[Dorm Name],DormRegistry[Bed Capacity]),0) | E19: =$B$6*(1+$B$8)^(YEAR(A19)-YEAR(StartDate)) | F19: =$B$7 | G19: =$B$8 | H19: =D19*E19 | J19: =D19*F19*E19 | K19: 75 | L19: 50 | M19: 150 | N19: 125 | O19: 60 | P19: 80 | Q19: 40 | R19: =IF(C19="Owned",0,2500) | S19: =SUM(K19:R19) | T19: =I19-S19 | U19: =IFERROR(T19/I19,0)
A20: =EDATE(StartDate,2) | B20: Dorm 1 | C20: =IFERROR(_xlfn.XLOOKUP(B20,DormRegistry[Dorm Name],DormRegistry[Ownership Type]),"") | D20: =IFERROR(_xlfn.XLOOKUP(B20,DormRegistry[Dorm Name],DormRegistry[Bed Capacity]),0) | E20: =$B$6*(1+$B$8)^(YEAR(A20)-YEAR(StartDate)) | F20: =$B$7 | G20: =$B$8 | H20: =D20*E20 | J20: =D20*F20*E20 | K20: 75 | L20: 50 | M20: 150 | N20: 125 | O20: 60 | P20: 80 | Q20: 40 | R20: =IF(C20="Owned",0,2500) | S20: =SUM(K20:R20) | T20: =I20-S20 | U20: =IFERROR(T20/I20,0)
A21: =EDATE(StartDate,2) | B21: Dorm 2 | C21: =IFERROR(_xlfn.XLOOKUP(B21,DormRegistry[Dorm Name],DormRegistry[Ownership Type]),"") | D21: =IFERROR(_xlfn.XLOOKUP(B21,DormRegistry[Dorm Name],DormRegistry[Bed Capacity]),0) | E21: =$B$6*(1+$B$8)^(YEAR(A21)-YEAR(StartDate)) | F21: =$B$7 | G21: =$B$8 | H21: =D21*E21 | J21: =D21*F21*E21 | K21: 75 | L21: 50 | M21: 150 | N21: 125 | O21: 60 | P21: 80 | Q21: 40 | R21: =IF(C21="Owned",0,2500) | S21: =SUM(K21:R21) | T21: =I21-S21 | U21: =IFERROR(T21/I21,0)
A22: =EDATE(StartDate,2) | B22: Dorm 3 | C22: =IFERROR(_xlfn.XLOOKUP(B22,DormRegistry[Dorm Name],DormRegistry[Ownership Type]),"") | D22: =IFERROR(_xlfn.XLOOKUP(B22,DormRegistry[Dorm Name],DormRegistry[Bed Capacity]),0) | E22: =$B$6*(1+$B$8)^(YEAR(A22)-YEAR(StartDate)) | F22: =$B$7 | G22: =$B$8 | H22: =D22*E22 | J22: =D22*F22*E22 | K22: 75 | L22: 50 | M22: 150 | N22: 125 | O22: 60 | P22: 80 | Q22: 40 | R22: =IF(C22="Owned",0,2500) | S22: =SUM(K22:R22) | T22: =I22-S22 | U22: =IFERROR(T22/I22,0)
A23: =EDATE(StartDate,3) | B23: Dorm 1 | C23: =IFERROR(_xlfn.XLOOKUP(B23,DormRegistry[Dorm Name],DormRegistry[Ownership Type]),"") | D23: =IFERROR(_xlfn.XLOOKUP(B23,DormRegistry[Dorm Name],DormRegistry[Bed Capacity]),0) | E23: =$B$6*(1+$B$8)^(YEAR(A23)-YEAR(StartDate)) | F23: =$B$7 | G23: =$B$8 | H23: =D23*E23 | J23: =D23*F23*E23 | K23: 75 | L23: 50 | M23: 150 | N23: 125 | O23: 60 | P23: 80 | Q23: 40 | R23: =IF(C23="Owned",0,2500) | S23: =SUM(K23:R23) | T23: =I23-S23 | U23: =IFERROR(T23/I23,0)
A24: =EDATE(StartDate,3) | B24: Dorm 2 | C24: =IFERROR(_xlfn.XLOOKUP(B24,DormRegistry[Dorm Name],DormRegistry[Ownership Type]),"") | D24: =IFERROR(_xlfn.XLOOKUP(B24,DormRegistry[Dorm Name],DormRegistry[Bed Capacity]),0) | E24: =$B$6*(1+$B$8)^(YEAR(A24)-YEAR(StartDate)) | F24: =$B$7 | G24: =$B$8 | H24: =D24*E24 | J24: =D24*F24*E24 | K24: 75 | L24: 50 | M24: 150 | N24: 125 | O24: 60 | P24: 80 | Q24: 40 | R24: =IF(C24="Owned",0,2500) | S24: =SUM(K24:R24) | T24: =I24-S24 | U24: =IFERROR(T24/I24,0)
A25: =EDATE(StartDate,3) | B25: Dorm 3 | C25: =IFERROR(_xlfn.XLOOKUP(B25,DormRegistry[Dorm Name],DormRegistry[Ownership Type]),"") | D25: =IFERROR(_xlfn.XLOOKUP(B25,DormRegistry[Dorm Name],DormRegistry[Bed Capacity]),0) | E25: =$B$6*(1+$B$8)^(YEAR(A25)-YEAR(StartDate)) | F25: =$B$7 | G25: =$B$8 | H25: =D25*E25 | J25: =D25*F25*E25 | K25: 75 | L25: 50 | M25: 150 | N25: 125 | O25: 60 | P25: 80 | Q25: 40 | R25: =IF(C25="Owned",0,2500) | S25: =SUM(K25:R25) | T25: =I25-S25 | U25: =IFERROR(T25/I25,0)
A26: =EDATE(StartDate,4) | B26: Dorm 1 | C26: =IFERROR(_xlfn.XLOOKUP(B26,DormRegistry[Dorm Name],DormRegistry[Ownership Type]),"") | D26: =IFERROR(_xlfn.XLOOKUP(B26,DormRegistry[Dorm Name],DormRegistry[Bed Capacity]),0) | E26: =$B$6*(1+$B$8)^(YEAR(A26)-YEAR(StartDate)) | F26: =$B$7 | G26: =$B$8 | H26: =D26*E26 | J26: =D26*F26*E26 | K26: 75 | L26: 50 | M26: 150 | N26: 125 | O26: 60 | P26: 80 | Q26: 40 | R26: =IF(C26="Owned",0,2500) | S26: =SUM(K26:R26) | T26: =I26-S26 | U26: =IFERROR(T26/I26,0)
A27: =EDATE(StartDate,4) | B27: Dorm 2 | C27: =IFERROR(_xlfn.XLOOKUP(B27,DormRegistry[Dorm Name],DormRegistry[Ownership Type]),"") | D27: =IFERROR(_xlfn.XLOOKUP(B27,DormRegistry[Dorm Name],DormRegistry[Bed Capacity]),0) | E27: =$B$6*(1+$B$8)^(YEAR(A27)-YEAR(StartDate)) | F27: =$B$7 | G27: =$B$8 | H27: =D27*E27 | J27: =D27*F27*E27 | K27: 75 | L27: 50 | M27: 150 | N27: 125 | O27: 60 | P27: 80 | Q27: 40 | R27: =IF(C27="Owned",0,2500) | S27: =SUM(K27:R27) | T27: =I27-S27 | U27: =IFERROR(T27/I27,0)
A28: =EDATE(StartDate,4) | B28: Dorm 3 | C28: =IFERROR(_xlfn.XLOOKUP(B28,DormRegistry[Dorm Name],DormRegistry[Ownership Type]),"") | D28: =IFERROR(_xlfn.XLOOKUP(B28,DormRegistry[Dorm Name],DormRegistry[Bed Capacity]),0) | E28: =$B$6*(1+$B$8)^(YEAR(A28)-YEAR(StartDate)) | F28: =$B$7 | G28: =$B$8 | H28: =D28*E28 | J28: =D28*F28*E28 | K28: 75 | L28: 50 | M28: 150 | N28: 125 | O28: 60 | P28: 80 | Q28: 40 | R28: =IF(C28="Owned",0,2500) | S28: =SUM(K28:R28) | T28: =I28-S28 | U28: =IFERROR(T28/I28,0)
A29: =EDATE(StartDate,5) | B29: Dorm 1 | C29: =IFERROR(_xlfn.XLOOKUP(B29,DormRegistry[Dorm Name],DormRegistry[Ownership Type]),"") | D29: =IFERROR(_xlfn.XLOOKUP(B29,DormRegistry[Dorm Name],DormRegistry[Bed Capacity]),0) | E29: =$B$6*(1+$B$8)^(YEAR(A29)-YEAR(StartDate)) | F29: =$B$7 | G29: =$B$8 | H29: =D29*E29 | J29: =D29*F29*E29 | K29: 75 | L29: 50 | M29: 150 | N29: 125 | O29: 60 | P29: 80 | Q29: 40 | R29: =IF(C29="Owned",0,2500) | S29: =SUM(K29:R29) | T29: =I29-S29 | U29: =IFERROR(T29/I29,0)
A30: =EDATE(StartDate,5) | B30: Dorm 2 | C30: =IFERROR(_xlfn.XLOOKUP(B30,DormRegistry[Dorm Name],DormRegistry[Ownership Type]),"") | D30: =IFERROR(_xlfn.XLOOKUP(B30,DormRegistry[Dorm Name],DormRegistry[Bed Capacity]),0) | E30: =$B$6*(1+$B$8)^(YEAR(A30)-YEAR(StartDate)) | F30: =$B$7 | G30: =$B$8 | H30: =D30*E30 | J30: =D30*F30*E30 | K30: 75 | L30: 50 | M30: 150 | N30: 125 | O30: 60 | P30: 80 | Q30: 40 | R30: =IF(C30="Owned",0,2500) | S30: =SUM(K30:R30) | T30: =I30-S30 | U30: =IFERROR(T30/I30,0)
A31: =EDATE(StartDate,5) | B31: Dorm 3 | C31: =IFERROR(_xlfn.XLOOKUP(B31,DormRegistry[Dorm Name],DormRegistry[Ownership Type]),"") | D31: =IFERROR(_xlfn.XLOOKUP(B31,DormRegistry[Dorm Name],DormRegistry[Bed Capacity]),0) | E31: =$B$6*(1+$B$8)^(YEAR(A31)-YEAR(StartDate)) | F31: =$B$7 | G31: =$B$8 | H31: =D31*E31 | J31: =D31*F31*E31 | K31: 75 | L31: 50 | M31: 150 | N31: 125 | O31: 60 | P31: 80 | Q31: 40 | R31: =IF(C31="Owned",0,2500) | S31: =SUM(K31:R31) | T31: =I31-S31 | U31: =IFERROR(T31/I31,0)
A32: =EDATE(StartDate,6) | B32: Dorm 1 | C32: =IFERROR(_xlfn.XLOOKUP(B32,DormRegistry[Dorm Name],DormRegistry[Ownership Type]),"") | D32: =IFERROR(_xlfn.XLOOKUP(B32,DormRegistry[Dorm Name],DormRegistry[Bed Capacity]),0) | E32: =$B$6*(1+$B$8)^(YEAR(A32)-YEAR(StartDate)) | F32: =$B$7 | G32: =$B$8 | H32: =D32*E32 | J32: =D32*F32*E32 | K32: 75 | L32: 50 | M32: 150 | N32: 125 | O32: 60 | P32: 80 | Q32: 40 | R32: =IF(C32="Owned",0,2500) | S32: =SUM(K32:R32) | T32: =I32-S32 | U32: =IFERROR(T32/I32,0)
A33: =EDATE(StartDate,6) | B33: Dorm 2 | C33: =IFERROR(_xlfn.XLOOKUP(B33,DormRegistry[Dorm Name],DormRegistry[Ownership Type]),"") | D33: =IFERROR(_xlfn.XLOOKUP(B33,DormRegistry[Dorm Name],DormRegistry[Bed Capacity]),0) | E33: =$B$6*(1+$B$8)^(YEAR(A33)-YEAR(StartDate)) | F33: =$B$7 | G33: =$B$8 | H33: =D33*E33 | J33: =D33*F33*E33 | K33: 75 | L33: 50 | M33: 150 | N33: 125 | O33: 60 | P33: 80 | Q33: 40 | R33: =IF(C33="Owned",0,2500) | S33: =SUM(K33:R33) | T33: =I33-S33 | U33: =IFERROR(T33/I33,0)
A34: =EDATE(StartDate,6) | B34: Dorm 3 | C34: =IFERROR(_xlfn.XLOOKUP(B34,DormRegistry[Dorm Name],DormRegistry[Ownership Type]),"") | D34: =IFERROR(_xlfn.XLOOKUP(B34,DormRegistry[Dorm Name],DormRegistry[Bed Capacity]),0) | E34: =$B$6*(1+$B$8)^(YEAR(A34)-YEAR(StartDate)) | F34: =$B$7 | G34: =$B$8 | H34: =D34*E34 | J34: =D34*F34*E34 | K34: 75 | L34: 50 | M34: 150 | N34: 125 | O34: 60 | P34: 80 | Q34: 40 | R34: =IF(C34="Owned",0,2500) | S34: =SUM(K34:R34) | T34: =I34-S34 | U34: =IFERROR(T34/I34,0)
A35: =EDATE(StartDate,7) | B35: Dorm 1 | C35: =IFERROR(_xlfn.XLOOKUP(B35,DormRegistry[Dorm Name],DormRegistry[Ownership Type]),"") | D35: =IFERROR(_xlfn.XLOOKUP(B35,DormRegistry[Dorm Name],DormRegistry[Bed Capacity]),0) | E35: =$B$6*(1+$B$8)^(YEAR(A35)-YEAR(StartDate)) | F35: =$B$7 | G35: =$B$8 | H35: =D35*E35 | J35: =D35*F35*E35 | K35: 75 | L35: 50 | M35: 150 | N35: 125 | O35: 60 | P35: 80 | Q35: 40 | R35: =IF(C35="Owned",0,2500) | S35: =SUM(K35:R35) | T35: =I35-S35 | U35: =IFERROR(T35/I35,0)
A36: =EDATE(StartDate,7) | B36: Dorm 2 | C36: =IFERROR(_xlfn.XLOOKUP(B36,DormRegistry[Dorm Name],DormRegistry[Ownership Type]),"") | D36: =IFERROR(_xlfn.XLOOKUP(B36,DormRegistry[Dorm Name],DormRegistry[Bed Capacity]),0) | E36: =$B$6*(1+$B$8)^(YEAR(A36)-YEAR(StartDate)) | F36: =$B$7 | G36: =$B$8 | H36: =D36*E36 | J36: =D36*F36*E36 | K36: 75 | L36: 50 | M36: 150 | N36: 125 | O36: 60 | P36: 80 | Q36: 40 | R36: =IF(C36="Owned",0,2500) | S36: =SUM(K36:R36) | T36: =I36-S36 | U36: =IFERROR(T36/I36,0)
A37: =EDATE(StartDate,7) | B37: Dorm 3 | C37: =IFERROR(_xlfn.XLOOKUP(B37,DormRegistry[Dorm Name],DormRegistry[Ownership Type]),"") | D37: =IFERROR(_xlfn.XLOOKUP(B37,DormRegistry[Dorm Name],DormRegistry[Bed Capacity]),0) | E37: =$B$6*(1+$B$8)^(YEAR(A37)-YEAR(StartDate)) | F37: =$B$7 | G37: =$B$8 | H37: =D37*E37 | J37: =D37*F37*E37 | K37: 75 | L37: 50 | M37: 150 | N37: 125 | O37: 60 | P37: 80 | Q37: 40 | R37: =IF(C37="Owned",0,2500) | S37: =SUM(K37:R37) | T37: =I37-S37 | U37: =IFERROR(T37/I37,0)
A38: =EDATE(StartDate,8) | B38: Dorm 1 | C38: =IFERROR(_xlfn.XLOOKUP(B38,DormRegistry[Dorm Name],DormRegistry[Ownership Type]),"") | D38: =IFERROR(_xlfn.XLOOKUP(B38,DormRegistry[Dorm Name],DormRegistry[Bed Capacity]),0) | E38: =$B$6*(1+$B$8)^(YEAR(A38)-YEAR(StartDate)) | F38: =$B$7 | G38: =$B$8 | H38: =D38*E38 | J38: =D38*F38*E38 | K38: 75 | L38: 50 | M38: 150 | N38: 125 | O38: 60 | P38: 80 | Q38: 40 | R38: =IF(C38="Owned",0,2500) | S38: =SUM(K38:R38) | T38: =I38-S38 | U38: =IFERROR(T38/I38,0)
A39: =EDATE(StartDate,8) | B39: Dorm 2 | C39: =IFERROR(_xlfn.XLOOKUP(B39,DormRegistry[Dorm Name],DormRegistry[Ownership Type]),"") | D39: =IFERROR(_xlfn.XLOOKUP(B39,DormRegistry[Dorm Name],DormRegistry[Bed Capacity]),0) | E39: =$B$6*(1+$B$8)^(YEAR(A39)-YEAR(StartDate)) | F39: =$B$7 | G39: =$B$8 | H39: =D39*E39 | J39: =D39*F39*E39 | K39: 75 | L39: 50 | M39: 150 | N39: 125 | O39: 60 | P39: 80 | Q39: 40 | R39: =IF(C39="Owned",0,2500) | S39: =SUM(K39:R39) | T39: =I39-S39 | U39: =IFERROR(T39/I39,0)
A40: =EDATE(StartDate,8) | B40: Dorm 3 | C40: =IFERROR(_xlfn.XLOOKUP(B40,DormRegistry[Dorm Name],DormRegistry[Ownership Type]),"") | D40: =IFERROR(_xlfn.XLOOKUP(B40,DormRegistry[Dorm Name],DormRegistry[Bed Capacity]),0) | E40: =$B$6*(1+$B$8)^(YEAR(A40)-YEAR(StartDate)) | F40: =$B$7 | G40: =$B$8 | H40: =D40*E40 | J40: =D40*F40*E40 | K40: 75 | L40: 50 | M40: 150 | N40: 125 | O40: 60 | P40: 80 | Q40: 40 | R40: =IF(C40="Owned",0,2500) | S40: =SUM(K40:R40) | T40: =I40-S40 | U40: =IFERROR(T40/I40,0)
A41: =EDATE(StartDate,9) | B41: Dorm 1 | C41: =IFERROR(_xlfn.XLOOKUP(B41,DormRegistry[Dorm Name],DormRegistry[Ownership Type]),"") | D41: =IFERROR(_xlfn.XLOOKUP(B41,DormRegistry[Dorm Name],DormRegistry[Bed Capacity]),0) | E41: =$B$6*(1+$B$8)^(YEAR(A41)-YEAR(StartDate)) | F41: =$B$7 | G41: =$B$8 | H41: =D41*E41 | J41: =D41*F41*E41 | K41: 75 | L41: 50 | M41: 150 | N41: 125 | O41: 60 | P41: 80 | Q41: 40 | R41: =IF(C41="Owned",0,2500) | S41: =SUM(K41:R41) | T41: =I41-S41 | U41: =IFERROR(T41/I41,0)
A42: =EDATE(StartDate,9) | B42: Dorm 2 | C42: =IFERROR(_xlfn.XLOOKUP(B42,DormRegistry[Dorm Name],DormRegistry[Ownership Type]),"") | D42: =IFERROR(_xlfn.XLOOKUP(B42,DormRegistry[Dorm Name],DormRegistry[Bed Capacity]),0) | E42: =$B$6*(1+$B$8)^(YEAR(A42)-YEAR(StartDate)) | F42: =$B$7 | G42: =$B$8 | H42: =D42*E42 | J42: =D42*F42*E42 | K42: 75 | L42: 50 | M42: 150 | N42: 125 | O42: 60 | P42: 80 | Q42: 40 | R42: =IF(C42="Owned",0,2500) | S42: =SUM(K42:R42) | T42: =I42-S42 | U42: =IFERROR(T42/I42,0)
A43: =EDATE(StartDate,9) | B43: Dorm 3 | C43: =IFERROR(_xlfn.XLOOKUP(B43,DormRegistry[Dorm Name],DormRegistry[Ownership Type]),"") | D43: =IFERROR(_xlfn.XLOOKUP(B43,DormRegistry[Dorm Name],DormRegistry[Bed Capacity]),0) | E43: =$B$6*(1+$B$8)^(YEAR(A43)-YEAR(StartDate)) | F43: =$B$7 | G43: =$B$8 | H43: =D43*E43 | J43: =D43*F43*E43 | K43: 75 | L43: 50 | M43: 150 | N43: 125 | O43: 60 | P43: 80 | Q43: 40 | R43: =IF(C43="Owned",0,2500) | S43: =SUM(K43:R43) | T43: =I43-S43 | U43: =IFERROR(T43/I43,0)
A44: =EDATE(StartDate,10) | B44: Dorm 1 | C44: =IFERROR(_xlfn.XLOOKUP(B44,DormRegistry[Dorm Name],DormRegistry[Ownership Type]),"") | D44: =IFERROR(_xlfn.XLOOKUP(B44,DormRegistry[Dorm Name],DormRegistry[Bed Capacity]),0) | E44: =$B$6*(1+$B$8)^(YEAR(A44)-YEAR(StartDate)) | F44: =$B$7 | G44: =$B$8 | H44: =D44*E44 | J44: =D44*F44*E44 | K44: 75 | L44: 50 | M44: 150 | N44: 125 | O44: 60 | P44: 80 | Q44: 40 | R44: =IF(C44="Owned",0,2500) | S44: =SUM(K44:R44) | T44: =I44-S44 | U44: =IFERROR(T44/I44,0)
A45: =EDATE(StartDate,10) | B45: Dorm 2 | C45: =IFERROR(_xlfn.XLOOKUP(B45,DormRegistry[Dorm Name],DormRegistry[Ownership Type]),"") | D45: =IFERROR(_xlfn.XLOOKUP(B45,DormRegistry[Dorm Name],DormRegistry[Bed Capacity]),0) | E45: =$B$6*(1+$B$8)^(YEAR(A45)-YEAR(StartDate)) | F45: =$B$7 | G45: =$B$8 | H45: =D45*E45 | J45: =D45*F45*E45 | K45: 75 | L45: 50 | M45: 150 | N45: 125 | O45: 60 | P45: 80 | Q45: 40 | R45: =IF(C45="Owned",0,2500) | S45: =SUM(K45:R45) | T45: =I45-S45 | U45: =IFERROR(T45/I45,0)
A46: =EDATE(StartDate,10) | B46: Dorm 3 | C46: =IFERROR(_xlfn.XLOOKUP(B46,DormRegistry[Dorm Name],DormRegistry[Ownership Type]),"") | D46: =IFERROR(_xlfn.XLOOKUP(B46,DormRegistry[Dorm Name],DormRegistry[Bed Capacity]),0) | E46: =$B$6*(1+$B$8)^(YEAR(A46)-YEAR(StartDate)) | F46: =$B$7 | G46: =$B$8 | H46: =D46*E46 | J46: =D46*F46*E46 | K46: 75 | L46: 50 | M46: 150 | N46: 125 | O46: 60 | P46: 80 | Q46: 40 | R46: =IF(C46="Owned",0,2500) | S46: =SUM(K46:R46) | T46: =I46-S46 | U46: =IFERROR(T46/I46,0)
A47: =EDATE(StartDate,11) | B47: Dorm 1 | C47: =IFERROR(_xlfn.XLOOKUP(B47,DormRegistry[Dorm Name],DormRegistry[Ownership Type]),"") | D47: =IFERROR(_xlfn.XLOOKUP(B47,DormRegistry[Dorm Name],DormRegistry[Bed Capacity]),0) | E47: =$B$6*(1+$B$8)^(YEAR(A47)-YEAR(StartDate)) | F47: =$B$7 | G47: =$B$8 | H47: =D47*E47 | J47: =D47*F47*E47 | K47: 75 | L47: 50 | M47: 150 | N47: 125 | O47: 60 | P47: 80 | Q47: 40 | R47: =IF(C47="Owned",0,2500) | S47: =SUM(K47:R47) | T47: =I47-S47 | U47: =IFERROR(T47/I47,0)
A48: =EDATE(StartDate,11) | B48: Dorm 2 | C48: =IFERROR(_xlfn.XLOOKUP(B48,DormRegistry[Dorm Name],DormRegistry[Ownership Type]),"") | D48: =IFERROR(_xlfn.XLOOKUP(B48,DormRegistry[Dorm Name],DormRegistry[Bed Capacity]),0) | E48: =$B$6*(1+$B$8)^(YEAR(A48)-YEAR(StartDate)) | F48: =$B$7 | G48: =$B$8 | H48: =D48*E48 | J48: =D48*F48*E48 | K48: 75 | L48: 50 | M48: 150 | N48: 125 | O48: 60 | P48: 80 | Q48: 40 | R48: =IF(C48="Owned",0,2500) | S48: =SUM(K48:R48) | T48: =I48-S48 | U48: =IFERROR(T48/I48,0)
A49: =EDATE(StartDate,11) | B49: Dorm 3 | C49: =IFERROR(_xlfn.XLOOKUP(B49,DormRegistry[Dorm Name],DormRegistry[Ownership Type]),"") | D49: =IFERROR(_xlfn.XLOOKUP(B49,DormRegistry[Dorm Name],DormRegistry[Bed Capacity]),0) | E49: =$B$6*(1+$B$8)^(YEAR(A49)-YEAR(StartDate)) | F49: =$B$7 | G49: =$B$8 | H49: =D49*E49 | J49: =D49*F49*E49 | K49: 75 | L49: 50 | M49: 150 | N49: 125 | O49: 60 | P49: 80 | Q49: 40 | R49: =IF(C49="Owned",0,2500) | S49: =SUM(K49:R49) | T49: =I49-S49 | U49: =IFERROR(T49/I49,0)
C50: =IFERROR(_xlfn.XLOOKUP(B50,DormRegistry[Dorm Name],DormRegistry[Ownership Type]),"") | D50: 2 | E50: =IF(A50="","",$B$6*(1+$B$8)^(YEAR(A50)-YEAR(StartDate))) | F50: =$B$7 | G50: =$B$8 | H50: =IFERROR(D50*E50,0) | J50: =IFERROR(D50*F50*E50,0) | R50: =IF(C50="Owned",0,IF(B50<>"",2500,0)) | S50: =SUM(K50:R50) | T50: =I50-S50 | U50: =IFERROR(T50/I50,0)
C51: =IFERROR(_xlfn.XLOOKUP(B51,DormRegistry[Dorm Name],DormRegistry[Ownership Type]),"") | D51: 2 | E51: =IF(A51="","",$B$6*(1+$B$8)^(YEAR(A51)-YEAR(StartDate))) | F51: =$B$7 | G51: =$B$8 | H51: =IFERROR(D51*E51,0) | J51: =IFERROR(D51*F51*E51,0) | R51: =IF(C51="Owned",0,IF(B51<>"",2500,0)) | S51: =SUM(K51:R51) | T51: =I51-S51 | U51: =IFERROR(T51/I51,0)
C52: =IFERROR(_xlfn.XLOOKUP(B52,DormRegistry[Dorm Name],DormRegistry[Ownership Type]),"") | D52: 2 | E52: =IF(A52="","",$B$6*(1+$B$8)^(YEAR(A52)-YEAR(StartDate))) | F52: =$B$7 | G52: =$B$8 | H52: =IFERROR(D52*E52,0) | J52: =IFERROR(D52*F52*E52,0) | R52: =IF(C52="Owned",0,IF(B52<>"",2500,0)) | S52: =SUM(K52:R52) | T52: =I52-S52 | U52: =IFERROR(T52/I52,0)
C53: =IFERROR(_xlfn.XLOOKUP(B53,DormRegistry[Dorm Name],DormRegistry[Ownership Type]),"") | D53: 2 | E53: =IF(A53="","",$B$6*(1+$B$8)^(YEAR(A53)-YEAR(StartDate))) | F53: =$B$7 | G53: =$B$8 | H53: =IFERROR(D53*E53,0) | J53: =IFERROR(D53*F53*E53,0) | R53: =IF(C53="Owned",0,IF(B53<>"",2500,0)) | S53: =SUM(K53:R53) | T53: =I53-S53 | U53: =IFERROR(T53/I53,0)
C54: =IFERROR(_xlfn.XLOOKUP(B54,DormRegistry[Dorm Name],DormRegistry[Ownership Type]),"") | D54: 2 | E54: =IF(A54="","",$B$6*(1+$B$8)^(YEAR(A54)-YEAR(StartDate))) | F54: =$B$7 | G54: =$B$8 | H54: =IFERROR(D54*E54,0) | J54: =IFERROR(D54*F54*E54,0) | R54: =IF(C54="Owned",0,IF(B54<>"",2500,0)) | S54: =SUM(K54:R54) | T54: =I54-S54 | U54: =IFERROR(T54/I54,0)
C55: =IFERROR(_xlfn.XLOOKUP(B55,DormRegistry[Dorm Name],DormRegistry[Ownership Type]),"") | D55: 2 | E55: =IF(A55="","",$B$6*(1+$B$8)^(YEAR(A55)-YEAR(StartDate))) | F55: =$B$7 | G55: =$B$8 | H55: =IFERROR(D55*E55,0) | J55: =IFERROR(D55*F55*E55,0) | R55: =IF(C55="Owned",0,IF(B55<>"",2500,0)) | S55: =SUM(K55:R55) | T55: =I55-S55 | U55: =IFERROR(T55/I55,0)
C56: =IFERROR(_xlfn.XLOOKUP(B56,DormRegistry[Dorm Name],DormRegistry[Ownership Type]),"") | D56: 2 | E56: =IF(A56="","",$B$6*(1+$B$8)^(YEAR(A56)-YEAR(StartDate))) | F56: =$B$7 | G56: =$B$8 | H56: =IFERROR(D56*E56,0) | J56: =IFERROR(D56*F56*E56,0) | R56: =IF(C56="Owned",0,IF(B56<>"",2500,0)) | S56: =SUM(K56:R56) | T56: =I56-S56 | U56: =IFERROR(T56/I56,0)
C57: =IFERROR(_xlfn.XLOOKUP(B57,DormRegistry[Dorm Name],DormRegistry[Ownership Type]),"") | D57: 2 | E57: =IF(A57="","",$B$6*(1+$B$8)^(YEAR(A57)-YEAR(StartDate))) | F57: =$B$7 | G57: =$B$8 | H57: =IFERROR(D57*E57,0) | J57: =IFERROR(D57*F57*E57,0) | R57: =IF(C57="Owned",0,IF(B57<>"",2500,0)) | S57: =SUM(K57:R57) | T57: =I57-S57 | U57: =IFERROR(T57/I57,0)
C58: =IFERROR(_xlfn.XLOOKUP(B58,DormRegistry[Dorm Name],DormRegistry[Ownership Type]),"") | D58: 2 | E58: =IF(A58="","",$B$6*(1+$B$8)^(YEAR(A58)-YEAR(StartDate))) | F58: =$B$7 | G58: =$B$8 | H58: =IFERROR(D58*E58,0) | J58: =IFERROR(D58*F58*E58,0) | R58: =IF(C58="Owned",0,IF(B58<>"",2500,0)) | S58: =SUM(K58:R58) | T58: =I58-S58 | U58: =IFERROR(T58/I58,0)
C59: =IFERROR(_xlfn.XLOOKUP(B59,DormRegistry[Dorm Name],DormRegistry[Ownership Type]),"") | D59: 2 | E59: =IF(A59="","",$B$6*(1+$B$8)^(YEAR(A59)-YEAR(StartDate))) | F59: =$B$7 | G59: =$B$8 | H59: =IFERROR(D59*E59,0) | J59: =IFERROR(D59*F59*E59,0) | R59: =IF(C59="Owned",0,IF(B59<>"",2500,0)) | S59: =SUM(K59:R59) | T59: =I59-S59 | U59: =IFERROR(T59/I59,0)
C60: =IFERROR(_xlfn.XLOOKUP(B60,DormRegistry[Dorm Name],DormRegistry[Ownership Type]),"") | D60: 2 | E60: =IF(A60="","",$B$6*(1+$B$8)^(YEAR(A60)-YEAR(StartDate))) | F60: =$B$7 | G60: =$B$8 | H60: =IFERROR(D60*E60,0) | J60: =IFERROR(D60*F60*E60,0) | R60: =IF(C60="Owned",0,IF(B60<>"",2500,0)) | S60: =SUM(K60:R60) | T60: =I60-S60 | U60: =IFERROR(T60/I60,0)
C61: =IFERROR(_xlfn.XLOOKUP(B61,DormRegistry[Dorm Name],DormRegistry[Ownership Type]),"") | D61: 2 | E61: =IF(A61="","",$B$6*(1+$B$8)^(YEAR(A61)-YEAR(StartDate))) | F61: =$B$7 | G61: =$B$8 | H61: =IFERROR(D61*E61,0) | J61: =IFERROR(D61*F61*E61,0) | R61: =IF(C61="Owned",0,IF(B61<>"",2500,0)) | S61: =SUM(K61:R61) | T61: =I61-S61 | U61: =IFERROR(T61/I61,0)
C62: =IFERROR(_xlfn.XLOOKUP(B62,DormRegistry[Dorm Name],DormRegistry[Ownership Type]),"") | D62: =IFERROR(_xlfn.XLOOKUP(B62,DormRegistry[Dorm Name],DormRegistry[Bed Capacity]),0) | E62: =IF(A62="","",$B$6*(1+$B$8)^(YEAR(A62)-YEAR(StartDate))) | F62: =$B$7 | G62: =$B$8 | H62: =IFERROR(D62*E62,0) | J62: =IFERROR(D62*F62*E62,0) | R62: =IF(C62="Owned",0,IF(B62<>"",2500,0)) | S62: =SUM(K62:R62) | T62: =I62-S62 | U62: =IFERROR(T62/I62,0)
C63: =IFERROR(_xlfn.XLOOKUP(B63,DormRegistry[Dorm Name],DormRegistry[Ownership Type]),"") | D63: =IFERROR(_xlfn.XLOOKUP(B63,DormRegistry[Dorm Name],DormRegistry[Bed Capacity]),0) | E63: =IF(A63="","",$B$6*(1+$B$8)^(YEAR(A63)-YEAR(StartDate))) | F63: =$B$7 | G63: =$B$8 | H63: =IFERROR(D63*E63,0) | J63: =IFERROR(D63*F63*E63,0) | R63: =IF(C63="Owned",0,IF(B63<>"",2500,0)) | S63: =SUM(K63:R63) | T63: =I63-S63 | U63: =IFERROR(T63/I63,0)
C64: =IFERROR(_xlfn.XLOOKUP(B64,DormRegistry[Dorm Name],DormRegistry[Ownership Type]),"") | D64: =IFERROR(_xlfn.XLOOKUP(B64,DormRegistry[Dorm Name],DormRegistry[Bed Capacity]),0) | E64: =IF(A64="","",$B$6*(1+$B$8)^(YEAR(A64)-YEAR(StartDate))) | F64: =$B$7 | G64: =$B$8 | H64: =IFERROR(D64*E64,0) | J64: =IFERROR(D64*F64*E64,0) | R64: =IF(C64="Owned",0,IF(B64<>"",2500,0)) | S64: =SUM(K64:R64) | T64: =I64-S64 | U64: =IFERROR(T64/I64,0)
C65: =IFERROR(_xlfn.XLOOKUP(B65,DormRegistry[Dorm Name],DormRegistry[Ownership Type]),"") | D65: =IFERROR(_xlfn.XLOOKUP(B65,DormRegistry[Dorm Name],DormRegistry[Bed Capacity]),0) | E65: =IF(A65="","",$B$6*(1+$B$8)^(YEAR(A65)-YEAR(StartDate))) | F65: =$B$7 | G65: =$B$8 | H65: =IFERROR(D65*E65,0) | J65: =IFERROR(D65*F65*E65,0) | R65: =IF(C65="Owned",0,IF(B65<>"",2500,0)) | S65: =SUM(K65:R65) | T65: =I65-S65 | U65: =IFERROR(T65/I65,0)
C66: =IFERROR(_xlfn.XLOOKUP(B66,DormRegistry[Dorm Name],DormRegistry[Ownership Type]),"") | D66: =IFERROR(_xlfn.XLOOKUP(B66,DormRegistry[Dorm Name],DormRegistry[Bed Capacity]),0) | E66: =IF(A66="","",$B$6*(1+$B$8)^(YEAR(A66)-YEAR(StartDate))) | F66: =$B$7 | G66: =$B$8 | H66: =IFERROR(D66*E66,0) | J66: =IFERROR(D66*F66*E66,0) | R66: =IF(C66="Owned",0,IF(B66<>"",2500,0)) | S66: =SUM(K66:R66) | T66: =I66-S66 | U66: =IFERROR(T66/I66,0)
C67: =IFERROR(_xlfn.XLOOKUP(B67,DormRegistry[Dorm Name],DormRegistry[Ownership Type]),"") | D67: =IFERROR(_xlfn.XLOOKUP(B67,DormRegistry[Dorm Name],DormRegistry[Bed Capacity]),0) | E67: =IF(A67="","",$B$6*(1+$B$8)^(YEAR(A67)-YEAR(StartDate))) | F67: =$B$7 | G67: =$B$8 | H67: =IFERROR(D67*E67,0) | J67: =IFERROR(D67*F67*E67,0) | R67: =IF(C67="Owned",0,IF(B67<>"",2500,0)) | S67: =SUM(K67:R67) | T67: =I67-S67 | U67: =IFERROR(T67/I67,0)
C68: =IFERROR(_xlfn.XLOOKUP(B68,DormRegistry[Dorm Name],DormRegistry[Ownership Type]),"") | D68: =IFERROR(_xlfn.XLOOKUP(B68,DormRegistry[Dorm Name],DormRegistry[Bed Capacity]),0) | E68: =IF(A68="","",$B$6*(1+$B$8)^(YEAR(A68)-YEAR(StartDate))) | F68: =$B$7 | G68: =$B$8 | H68: =IFERROR(D68*E68,0) | J68: =IFERROR(D68*F68*E68,0) | R68: =IF(C68="Owned",0,IF(B68<>"",2500,0)) | S68: =SUM(K68:R68) | T68: =I68-S68 | U68: =IFERROR(T68/I68,0)
C69: =IFERROR(_xlfn.XLOOKUP(B69,DormRegistry[Dorm Name],DormRegistry[Ownership Type]),"") | D69: =IFERROR(_xlfn.XLOOKUP(B69,DormRegistry[Dorm Name],DormRegistry[Bed Capacity]),0) | E69: =IF(A69="","",$B$6*(1+$B$8)^(YEAR(A69)-YEAR(StartDate))) | F69: =$B$7 | G69: =$B$8 | H69: =IFERROR(D69*E69,0) | J69: =IFERROR(D69*F69*E69,0) | R69: =IF(C69="Owned",0,IF(B69<>"",2500,0)) | S69: =SUM(K69:R69) | T69: =I69-S69 | U69: =IFERROR(T69/I69,0)
C70: =IFERROR(_xlfn.XLOOKUP(B70,DormRegistry[Dorm Name],DormRegistry[Ownership Type]),"") | D70: =IFERROR(_xlfn.XLOOKUP(B70,DormRegistry[Dorm Name],DormRegistry[Bed Capacity]),0) | E70: =IF(A70="","",$B$6*(1+$B$8)^(YEAR(A70)-YEAR(StartDate))) | F70: =$B$7 | G70: =$B$8 | H70: =IFERROR(D70*E70,0) | J70: =IFERROR(D70*F70*E70,0) | R70: =IF(C70="Owned",0,IF(B70<>"",2500,0)) | S70: =SUM(K70:R70) | T70: =I70-S70 | U70: =IFERROR(T70/I70,0)
C71: =IFERROR(_xlfn.XLOOKUP(B71,DormRegistry[Dorm Name],DormRegistry[Ownership Type]),"") | D71: =IFERROR(_xlfn.XLOOKUP(B71,DormRegistry[Dorm Name],DormRegistry[Bed Capacity]),0) | E71: =IF(A71="","",$B$6*(1+$B$8)^(YEAR(A71)-YEAR(StartDate))) | F71: =$B$7 | G71: =$B$8 | H71: =IFERROR(D71*E71,0) | J71: =IFERROR(D71*F71*E71,0) | R71: =IF(C71="Owned",0,IF(B71<>"",2500,0)) | S71: =SUM(K71:R71) | T71: =I71-S71 | U71: =IFERROR(T71/I71,0)
C72: =IFERROR(_xlfn.XLOOKUP(B72,DormRegistry[Dorm Name],DormRegistry[Ownership Type]),"") | D72: =IFERROR(_xlfn.XLOOKUP(B72,DormRegistry[Dorm Name],DormRegistry[Bed Capacity]),0) | E72: =IF(A72="","",$B$6*(1+$B$8)^(YEAR(A72)-YEAR(StartDate))) | F72: =$B$7 | G72: =$B$8 | H72: =IFERROR(D72*E72,0) | J72: =IFERROR(D72*F72*E72,0) | R72: =IF(C72="Owned",0,IF(B72<>"",2500,0)) | S72: =SUM(K72:R72) | T72: =I72-S72 | U72: =IFERROR(T72/I72,0)
C73: =IFERROR(_xlfn.XLOOKUP(B73,DormRegistry[Dorm Name],DormRegistry[Ownership Type]),"") | D73: =IFERROR(_xlfn.XLOOKUP(B73,DormRegistry[Dorm Name],DormRegistry[Bed Capacity]),0) | E73: =IF(A73="","",$B$6*(1+$B$8)^(YEAR(A73)-YEAR(StartDate))) | F73: =$B$7 | G73: =$B$8 | H73: =IFERROR(D73*E73,0) | J73: =IFERROR(D73*F73*E73,0) | R73: =IF(C73="Owned",0,IF(B73<>"",2500,0)) | S73: =SUM(K73:R73) | T73: =I73-S73 | U73: =IFERROR(T73/I73,0)
... C300: =IFERROR(_xlfn.XLOOKUP(B300,DormRegistry[Dorm Name],DormRegistry[Ownership Type]),"") | D300: =IFERROR(_xlfn.XLOOKUP(B300,DormRegistry[Dorm Name],DormRegistry[Bed Capacity]),0) | E300: =IF(A300="","",$B$6*(1+$B$8)^(YEAR(A300)-YEAR(StartDate))) | F300: =$B$7 | G300: =$B$8 | H300: =IFERROR(D300*E300,0) | J300: =IFERROR(D300*F300*E300,0) | R300: =IF(C300="Owned",0,IF(B300<>"",2500,0)) | S300: =SUM(K300:R300) | T300: =I300-S300 | U300: =IFERROR(T300/I300,0)

Sheet Settings & Master Config
A1: Settings & Master Configuration
A2: Central control panel for standalone DooRm workbook variables. | J2: Month List | K2: Payment Status List | L2: Ownership List | M2: Project Status List | N2: Yes No List | O2: Dashboard Dorm Filter List | P2: Renovation Categories | R2: Year List | T2: Expansion Note
I3: Occupied | J3: 46023 | K3: Unpaid | L3: Owned | M3: Operational | N3: No | O3: All Dorms | P3: Painting | R3: 2025 | T3: Add Dorm 4+ in DormRegistry. Default room capacity is 6 beds max; tables/formulas can be extended without rebuilding formulas.
A4: Editable Variables | H4: Invoice Selector Type | I4: Vacant | J4: 46054 | K4: Paid | L4: Rented | M4: Under Construction | N4: Yes | O4: =IF(A21="","",A21) | P4: Beds & Mattresses | R4: 2026
A5: Variable | B5: Default | C5: Current Value | H5: Client Name | I5: Reserved | J5: 46082 | K5: Partially Paid | M5: Planned | O5: =IF(A22="","",A22) | P5: Kitchen Appliances | R5: 2027
A6: Generator Rate | B6: 0.5 | C6: 0.5 | H6: Bed ID | J6: 46113 | K6: Overdue | O6: =IF(A23="","",A23) | P6: Plumbing | R6: 2028
A7: Government Rate | B7: 0.4 | C7: 0.4 | J7: 46143 | O7: =IF(A24="","",A24) | P7: Furniture | R7: 2029
A8: Fixed Generator Fee | B8: 5 | C8: 5 | J8: 46174 | O8: =IF(A25="","",A25) | P8: Electricity & Wiring | R8: 2030
A9: Fixed Government Fee | B9: 6 | C9: 6 | J9: 46204 | O9: =IF(A26="","",A26) | P9: CCTV Installation | R9: 2031
A10: Default Rent Per Bed | B10: 350 | C10: 350 | J10: 46235 | O10: =IF(A27="","",A27) | P10: Internet Infrastructure | R10: 2032
A11: Target Occupancy | B11: 0.9 | C11: 0.9 | J11: 46266 | O11: =IF(A28="","",A28) | P11: Curtains & Decorations | R11: 2033
A12: Inflation Rate | B12: 0.03 | C12: 0.03 | J12: 46296 | O12: =IF(A29="","",A29) | P12: Cleaning Equipment | R12: 2034
A13: Currency Symbol | B13: $ | C13: $ | J13: 46327 | O13: =IF(A30="","",A30) | P13: Contingency / Miscellaneous | R13: 2035
J14: 46357 | O14: =IF(A31="","",A31)
O15: =IF(A32="","",A32)
O16: =IF(A33="","",A33)
A17: Dorm Registry Table | O17: =IF(A34="","",A34)
O18: =IF(A35="","",A35)
O19: =IF(A36="","",A36)
A20: Dorm Name | B20: Status | C20: Ownership Type | D20: Number of Rooms | E20: Beds per Room | F20: Bed Capacity | G20: Notes | O20: =IF(A37="","",A37)
A21: Dorm 1 | B21: Operational | C21: Owned | D21: 6 | E21: 2 | F21: =D21*E21 | G21: Operational owned building - no rent expense | Room capacity: 2 beds | O21: =IF(A38="","",A38)
A22: Dorm 2 | B22: Under Construction | C22: Rented | D22: 6 | E22: 2 | F22: =D22*E22 | G22: Rental property / project tracker focus | Room capacity: 2 beds | O22: =IF(A39="","",A39)
A23: Dorm 3 | B23: Planned | C23: Rented | D23: 6 | E23: 2 | F23: =D23*E23 | G23: Future rental property | Room capacity: 2 beds | O23: =IF(A40="","",A40)
F24: =IF(OR(D24="",E24=""),"",D24*E24) | O24: =IF(A41="","",A41)
F25: =IF(OR(D25="",E25=""),"",D25*E25) | O25: =IF(A42="","",A42)
F26: =IF(OR(D26="",E26=""),"",D26*E26) | O26: =IF(A43="","",A43)
F27: =IF(OR(D27="",E27=""),"",D27*E27) | O27: =IF(A44="","",A44)
F28: =IF(OR(D28="",E28=""),"",D28*E28) | O28: =IF(A45="","",A45)
F29: =IF(OR(D29="",E29=""),"",D29*E29) | O29: =IF(A46="","",A46)
F30: =IF(OR(D30="",E30=""),"",D30*E30) | O30: =IF(A47="","",A47)
F31: =IF(OR(D31="",E31=""),"",D31*E31) | O31: =IF(A48="","",A48)
F32: =IF(OR(D32="",E32=""),"",D32*E32) | O32: =IF(A49="","",A49)
F33: =IF(OR(D33="",E33=""),"",D33*E33) | O33: =IF(A50="","",A50)
F34: =IF(OR(D34="",E34=""),"",D34*E34) | O34: =IF(A51="","",A51)
F35: =IF(OR(D35="",E35=""),"",D35*E35) | O35: =IF(A52="","",A52)
... F120: =IF(OR(D120="",E120=""),"",D120*E120) | O120: =IF(A137="","",A137)

Sheet Settings & Master Config (2)
A1: Settings & Master Configuration
A2: Central control panel for standalone DooRm workbook variables. | H2: Invoice Selector Type | I2: STATUE | J2: Month List | K2: Payment Status List | L2: Ownership List | M2: Project Status List | N2: Yes No List | O2: Dashboard Dorm Filter List | P2: Renovation Categories | Q2: Year List | R2: Expansion Note
H3: Client Name | I3: Occupied | J3: 46023 | K3: Unpaid | L3: Owned | M3: Operational | N3: No | O3: All Dorms | P3: Painting | Q3: 2025 | R3: Add Dorm 4+ in DormRegistry. Default room capacity is 6 beds max; tables/formulas can be extended without rebuilding formulas.
A4: Editable Variables | H4: Bed ID | I4: Vacant | J4: 46054 | K4: Paid | L4: Rented | M4: Under Construction | N4: Yes | O4: =IF(A21="","",A21) | P4: Beds & Mattresses | Q4: 2026
A5: Variable | B5: Default | C5: Current Value | I5: Reserved | J5: 46082 | K5: Partially Paid | M5: Planned | O5: =IF(A22="","",A22) | P5: Kitchen Appliances | Q5: 2027
A6: Generator Rate | B6: 0.5 | C6: 0.5 | J6: 46113 | K6: Overdue | O6: =IF(A23="","",A23) | P6: Plumbing | Q6: 2028
A7: Government Rate | B7: 0.4 | C7: 0.4 | J7: 46143 | O7: =IF(A24="","",A24) | P7: Furniture | Q7: 2029
A8: Fixed Generator Fee | B8: 5 | C8: 5 | J8: 46174 | O8: =IF(A25="","",A25) | P8: Electricity & Wiring | Q8: 2030
A9: Fixed Government Fee | B9: 6 | C9: 6 | J9: 46204 | O9: =IF(A26="","",A26) | P9: CCTV Installation | Q9: 2031
A10: Default Rent Per Bed | B10: 350 | C10: 350 | J10: 46235 | O10: =IF(A27="","",A27) | P10: Internet Infrastructure | Q10: 2032
A11: Target Occupancy | B11: 0.9 | C11: 0.9 | J11: 46266 | O11: =IF(A28="","",A28) | P11: Curtains & Decorations | Q11: 2033
A12: Inflation Rate | B12: 0.03 | C12: 0.03 | J12: 46296 | O12: =IF(A29="","",A29) | P12: Cleaning Equipment | Q12: 2034
A13: Currency Symbol | B13: $ | C13: $ | J13: 46327 | O13: =IF(A30="","",A30) | P13: Contingency / Miscellaneous | Q13: 2035
J14: 46357 | O14: =IF(A31="","",A31)
O15: =IF(A32="","",A32)
O16: =IF(A33="","",A33)
A17: Dorm Registry Table | O17: =IF(A34="","",A34)
O18: =IF(A35="","",A35)
O19: =IF(A36="","",A36)
A20: Dorm Name | B20: Status | C20: Ownership Type | D20: Number of Rooms | E20: Beds per Room | F20: Bed Capacity | G20: Notes | O20: =IF(A37="","",A37)
A21: Dorm 1 | B21: Operational | C21: Owned | D21: 6 | E21: 2 | F21: =D21*E21 | G21: Operational owned building - no rent expense | Room capacity: 2 beds | O21: =IF(A38="","",A38)
A22: Dorm 2 | B22: Under Construction | C22: Rented | D22: 6 | E22: 2 | F22: =D22*E22 | G22: Rental property / project tracker focus | Room capacity: 2 beds | O22: =IF(A39="","",A39)
A23: Dorm 3 | B23: Planned | C23: Rented | D23: 6 | E23: 2 | F23: =D23*E23 | G23: Future rental property | Room capacity: 2 beds | O23: =IF(A40="","",A40)
F24: =IF(OR(D24="",E24=""),"",D24*E24) | O24: =IF(A41="","",A41)
F25: =IF(OR(D25="",E25=""),"",D25*E25) | O25: =IF(A42="","",A42)
F26: =IF(OR(D26="",E26=""),"",D26*E26) | O26: =IF(A43="","",A43)
F27: =IF(OR(D27="",E27=""),"",D27*E27) | O27: =IF(A44="","",A44)
F28: =IF(OR(D28="",E28=""),"",D28*E28) | O28: =IF(A45="","",A45)
F29: =IF(OR(D29="",E29=""),"",D29*E29) | O29: =IF(A46="","",A46)
F30: =IF(OR(D30="",E30=""),"",D30*E30) | O30: =IF(A47="","",A47)
F31: =IF(OR(D31="",E31=""),"",D31*E31) | O31: =IF(A48="","",A48)
F32: =IF(OR(D32="",E32=""),"",D32*E32) | O32: =IF(A49="","",A49)
F33: =IF(OR(D33="",E33=""),"",D33*E33) | O33: =IF(A50="","",A50)
F34: =IF(OR(D34="",E34=""),"",D34*E34) | O34: =IF(A51="","",A51)
F35: =IF(OR(D35="",E35=""),"",D35*E35) | O35: =IF(A52="","",A52)
... F120: =IF(OR(D120="",E120=""),"",D120*E120) | O120: =IF(A137="","",A137)

Sheet Feuille15
